{
  "Bhavdate": "12-Mar-2026",
  "HDFCBANK": "833.95",
  "ATGL": "607.60",
  "RELIANCE": "1390.20",
  "ICICIBANK": "1294.60",
  "BHARTIARTL": "1807.00",
  "M&M": "3031.20",
  "JINDALSAW": "198.80",
  "NTPCGREEN": "97.65",
  "LT": "3838.80",
  "SBIN": "1091.10",
  "DOMS": "2154.00",
  "ETERNAL": "223.80",
  "BAJFINANCE": "863.10",
  "COALINDIA": "470.10",
  "AXISBANK": "1255.80",
  "ADANIPOWER": "138.85",
  "SILVERBEES": "253.50",
  "DIXON": "10803.00",
  "JSWENERGY": "488.00",
  "TATAPOWER": "385.75",
  "INFY": "1276.30",
  "KOTAKBANK": "383.20",
  "NTPC": "390.55",
  "TVSMOTOR": "3600.80",
  "EICHERMOT": "6975.50",
  "POWERGRID": "303.60",
  "JIOFIN": "242.20",
  "ADANIENT": "2002.00",
  "MARUTI": "13011.00",
  "ULTRACEMCO": "11089.00",
  "20MICRONS": "163.09",
  "21STCENMGM": "33.64",
  "360ONE": "1043.40",
  "3IINFOLTD": "13.14",
  "3MINDIA": "34305.00",
  "3PLAND": "31.22",
  "5PAISA": "301.80",
  "63MOONS": "594.05",
  "AAATECH": "93.17",
  "AADHARHFC": "475.95",
  "AAREYDRUGS": "68.26",
  "AARNAV": "25.31",
  "AARON": "142.52",
  "AARTECH": "39.80",
  "AARTIDRUGS": "356.45",
  "AARTIIND": "446.20",
  "AARTIPHARM": "678.65",
  "AARTISURF": "376.15",
  "AARVI": "128.88",
  "AAVAS": "1179.80",
  "ABBOTINDIA": "26685.00",
  "ABCAPITAL": "319.95",
  "ABCOTS": "405.20",
  "ABDL": "463.60",
  "ABFRL": "62.07",
  "ABGSEC": "112.27",
  "ABINFRA": "17.01",
  "ABLBL": "101.10",
  "ABREL": "1189.80",
  "ABSL10BANK": "165.13",
  "ABSLAMC": "1000.15",
  "ABSLBANETF": "56.29",
  "ABSLLIQUID": "1000.00",
  "ABSLMSCIN": "29.21",
  "ABSLNN50ET": "69.70",
  "ABSLPSE": "10.70",
  "ACC": "1433.40",
  "ACCELYA": "1200.30",
  "ACCURACY": "4.01",
  "ACE": "865.85",
  "ACEINTEG": "17.77",
  "ACI": "565.85",
  "ACL": "53.77",
  "ACMESOLAR": "240.08",
  "ACUTAAS": "2187.70",
  "ADFFOODS": "186.05",
  "ADL": "71.92",
  "ADOR": "998.50",
  "ADROITINFO": "9.66",
  "ADSL": "103.57",
  "ADVAIT": "1580.60",
  "ADVANCE": "101.66",
  "ADVANIHOTR": "52.11",
  "ADVENTHTL": "170.46",
  "ADVENZYMES": "290.45",
  "AEGISLOG": "637.25",
  "AEGISVOPAK": "193.47",
  "AEPL": "18.19",
  "AEQUS": "115.59",
  "AEROENTER": "71.03",
  "AEROFLEX": "237.13",
  "AERONEU": "68.68",
  "AETHER": "1047.65",
  "AFCONS": "278.50",
  "AFFLE": "1377.80",
  "AFFORDABLE": "164.34",
  "AFSL": "201.57",
  "AGARIND": "444.25",
  "AGARWALEYE": "435.30",
  "AGI": "540.45",
  "AGIIL": "312.15",
  "AGROPHOS": "32.61",
  "AHCL": "122.75",
  "AHLADA": "41.03",
  "AHLEAST": "153.40",
  "AHLUCONT": "762.50",
  "AIAENG": "3722.80",
  "AIIL": "449.45",
  "AIRAN": "16.03",
  "AIROLAM": "87.20",
  "AJANTPHARM": "3119.50",
  "AJAXENGG": "470.55",
  "AJMERA": "122.16",
  "AJOONI": "4.44",
  "AKASH": "24.66",
  "AKG": "11.00",
  "AKI": "5.05",
  "AKSHAR": "0.39",
  "AKSHARCHEM": "170.47",
  "AKSHOPTFBR": "4.73",
  "AKUMS": "498.95",
  "AKZOINDIA": "2916.90",
  "ALANKIT": "7.87",
  "ALBERTDAVD": "686.95",
  "ALEMBICLTD": "82.97",
  "ALGOQUANT": "55.47",
  "ALICON": "698.35",
  "ALIVUS": "939.40",
  "ALKALI": "60.33",
  "ALKEM": "5444.00",
  "ALKYLAMINE": "1304.10",
  "ALLCARGO": "7.90",
  "ALLDIGI": "806.70",
  "ALLTIME": "209.99",
  "ALMONDZ": "14.27",
  "ALOKINDS": "13.21",
  "ALPA": "61.49",
  "ALPHA": "45.96",
  "ALPHAETF": "23.70",
  "ALPHAGEO": "196.78",
  "ALPL30IETF": "26.21",
  "AMAGI": "380.65",
  "AMANTA": "98.38",
  "AMBER": "6929.50",
  "AMBICAAGAR": "23.54",
  "AMBIKCO": "1371.50",
  "AMDIND": "38.04",
  "AMJLAND": "37.84",
  "AMNPLST": "151.28",
  "AMRUTANJAN": "548.00",
  "ANANDRATHI": "3075.10",
  "ANANTRAJ": "469.60",
  "ANDHRAPAP": "62.91",
  "ANDHRSUGAR": "72.28",
  "ANGELONE": "213.07",
  "ANIKINDS": "40.09",
  "ANMOL": "10.98",
  "ANTELOPUS": "575.85",
  "ANTGRAPHIC": "0.79",
  "ANTHEM": "640.95",
  "ANUHPHR": "78.26",
  "ANUP": "1556.60",
  "ANURAS": "1267.10",
  "AONEGOLD": "14.91",
  "AONELIQUID": "1050.35",
  "AONENIFTY": "9.71",
  "AONESILVER": "10.13",
  "AONETMMQ50": "9.35",
  "AONETOTAL": "11.08",
  "APARINDS": "9456.00",
  "APCL": "116.58",
  "APCOTEXIND": "358.20",
  "APEX": "346.30",
  "APLAPOLLO": "2009.20",
  "APLLTD": "703.30",
  "APOLLO": "210.84",
  "APOLLOPIPE": "415.30",
  "APOLLOTYRE": "417.65",
  "APOLSINHOT": "1141.80",
  "APTECHT": "81.27",
  "APTUS": "227.24",
  "AQYLON": "88.70",
  "ARCHIDPLY": "73.96",
  "ARCHIES": "13.91",
  "ARE&M": "789.80",
  "ARENTERP": "40.20",
  "ARFIN": "80.26",
  "ARIES": "338.95",
  "ARIHANTCAP": "71.10",
  "ARIHANTSUP": "227.00",
  "ARIS": "109.33",
  "ARKADE": "106.95",
  "ARMANFIN": "1378.90",
  "AROGRANITE": "24.05",
  "ARROWGREEN": "365.85",
  "ARSSBL": "492.90",
  "ARTEMISMED": "229.64",
  "ARTNIRMAN": "36.46",
  "ARVIND": "348.30",
  "ARVINDFASN": "393.35",
  "ARVSMART": "537.50",
  "ASAHIINDIA": "856.20",
  "ASAHISONG": "188.74",
  "ASAL": "430.10",
  "ASALCBR": "731.20",
  "ASHAPURMIN": "531.55",
  "ASHIANA": "314.10",
  "ASHIMASYN": "15.06",
  "ASHOKA": "121.05",
  "ASHOKAMET": "14.44",
  "ASHOKLEY": "178.47",
  "ASIANENE": "279.00",
  "ASIANHOTNR": "306.45",
  "ASIANTILES": "64.59",
  "ASKAUTOLTD": "406.40",
  "ASMS": "8.76",
  "ASPINWALL": "213.01",
  "ASTEC": "626.35",
  "ASTERDM": "684.05",
  "ASTRAL": "1696.00",
  "ASTRAMICRO": "1034.40",
  "ASTRAZEN": "8609.00",
  "ASTRON": "4.21",
  "ATALREAL": "22.79",
  "ATAM": "59.24",
  "ATHERENERG": "710.55",
  "ATL": "23.60",
  "ATLANTAA": "36.76",
  "ATLANTAELE": "1046.40",
  "ATLASCYCLE": "84.43",
  "ATUL": "6302.50",
  "ATULAUTO": "424.80",
  "AUBANK": "902.20",
  "AURIONPRO": "921.45",
  "AUROPHARMA": "1311.90",
  "AURUM": "175.03",
  "AUTOAXLES": "1822.80",
  "AUTOBEES": "258.28",
  "AUTOIETF": "25.85",
  "AUTOIND": "65.15",
  "AVADHSUGAR": "426.05",
  "AVALON": "912.90",
  "AVANTEL": "143.95",
  "AVANTIFEED": "1250.00",
  "AVG": "133.70",
  "AVL": "454.05",
  "AVONMORE": "12.56",
  "AVROIND": "135.86",
  "AVTNPL": "61.09",
  "AWFIS": "286.15",
  "AWHCL": "485.45",
  "AWL": "176.15",
  "AXISBNKETF": "565.40",
  "AXISBPSETF": "13.21",
  "AXISCADES": "1385.20",
  "AXISCETF": "110.71",
  "AXISGOLD": "133.64",
  "AXISHCETF": "150.86",
  "AXISILVER": "263.30",
  "AXISNIFTY": "260.48",
  "AXISTECETF": "324.09",
  "AXISVALUE": "33.01",
  "AXSENSEX": "78.90",
  "AYE": "105.41",
  "AYMSYNTEX": "182.09",
  "AZAD": "1584.90",
  "BAFNAPH": "103.78",
  "BAGFILMS": "4.85",
  "BAIDFIN": "11.08",
  "BAJAJCON": "352.85",
  "BAJAJELEC": "383.30",
  "BAJAJHCARE": "300.45",
  "BAJAJHIND": "16.53",
  "BAJAJINDEF": "254.75",
  "BAJEL": "145.93",
  "BALAJEE": "26.37",
  "BALAJITELE": "97.23",
  "BALAMINES": "1035.00",
  "BALAXI": "20.03",
  "BALKRISHNA": "14.77",
  "BALKRISIND": "2280.20",
  "BALMLAWRIE": "167.96",
  "BALPHARMA": "71.49",
  "BALRAMCHIN": "509.30",
  "BALUFORGE": "466.85",
  "BANARBEADS": "114.42",
  "BANARISUG": "3600.10",
  "BANCOINDIA": "575.25",
  "BANDHANBNK": "178.01",
  "BANG": "36.02",
  "BANK10ADD": "16.50",
  "BANKA": "51.38",
  "BANKADD": "56.30",
  "BANKBEES": "569.24",
  "BANKBETA": "56.85",
  "BANKBETF": "55.91",
  "BANKETF": "559.53",
  "BANKIETF": "56.40",
  "BANKINDIA": "154.78",
  "BANKNIFTY1": "56.89",
  "BANKPSU": "88.80",
  "BANSALWIRE": "245.30",
  "BANSWRAS": "111.89",
  "BASF": "3469.70",
  "BASML": "20.49",
  "BATAINDIA": "713.95",
  "BAYERCROP": "4502.50",
  "BBETF0432": "1319.18",
  "BBL": "2408.10",
  "BBNPNBETF": "55.53",
  "BBNPPGOLD": "155.25",
  "BBOX": "522.15",
  "BBTC": "1570.90",
  "BBTCL": "165.00",
  "BCLIND": "28.26",
  "BCONCEPTS": "242.75",
  "BDL": "1349.40",
  "BEARDSELL": "23.50",
  "BECTORFOOD": "184.61",
  "BELLACASA": "283.35",
  "BELRISE": "188.08",
  "BEML": "1614.20",
  "BEPL": "83.81",
  "BERGEPAINT": "422.70",
  "BETA": "1109.20",
  "BFINVEST": "374.30",
  "BFSI": "26.53",
  "BHAGCHEM": "197.51",
  "BHAGERIA": "151.19",
  "BHAGYANGR": "157.70",
  "BHANDARI": "2.62",
  "BHARATCOAL": "35.81",
  "BHARATFORG": "1779.60",
  "BHARATGEAR": "98.20",
  "BHARATRAS": "1339.80",
  "BHARATSE": "169.45",
  "BHARATWIRE": "163.47",
  "BHARTIHEXA": "1521.90",
  "BHEL": "267.85",
  "BIGBLOC": "52.13",
  "BIKAJI": "619.00",
  "BIL": "719.90",
  "BIOCON": "392.20",
  "BIOFILCHEM": "30.63",
  "BIRLACABLE": "137.93",
  "BIRLACORPN": "820.10",
  "BIRLAMONEY": "120.78",
  "BIRLANU": "1334.90",
  "BLACKBUCK": "572.50",
  "BLAL": "176.33",
  "BLISSGVS": "209.20",
  "BLKASHYAP": "50.89",
  "BLS": "251.75",
  "BLSE": "142.55",
  "BLUECOAST": "20.81",
  "BLUEDART": "5303.50",
  "BLUEJET": "377.35",
  "BLUESTARCO": "1953.50",
  "BLUESTONE": "518.00",
  "BLUSPRING": "46.91",
  "BMWVENTLTD": "57.43",
  "BODALCHEM": "44.22",
  "BOMDYEING": "108.68",
  "BOROLTD": "241.41",
  "BORORENEW": "422.15",
  "BOROSCI": "107.02",
  "BOSCH-HCIL": "1326.80",
  "BPL": "51.18",
  "BRIGADE": "665.00",
  "BRIGHOTEL": "60.68",
  "BRNL": "18.34",
  "BROOKS": "62.18",
  "BSE": "2850.60",
  "BSE500IETF": "36.98",
  "BSHSL": "84.39",
  "BSL": "125.56",
  "BSLGOLDETF": "140.58",
  "BSLNIFTY": "27.57",
  "BSLSENETFG": "76.33",
  "BSOFT": "374.60",
  "BTML": "6.78",
  "BUILDPRO": "965.60",
  "BUTTERFLY": "697.10",
  "BVCL": "39.46",
  "BYKE": "39.44",
  "CALSOFT": "12.70",
  "CAMLINFINE": "144.93",
  "CAMPUS": "240.00",
  "CAMS": "663.75",
  "CANFINHOME": "872.55",
  "CANHLIFE": "145.87",
  "CANTABIL": "256.65",
  "CAPACITE": "202.07",
  "CAPILLARY": "515.35",
  "CAPITALSFB": "241.75",
  "CAPLIPOINT": "1687.60",
  "CARBORUNIV": "787.50",
  "CARERATING": "1631.20",
  "CARRARO": "472.60",
  "CARTRADE": "1678.70",
  "CARYSIL": "815.30",
  "CASHIETF": "1053.02",
  "CASTROLIND": "185.59",
  "CCAVENUE": "14.64",
  "CCCL": "15.72",
  "CCHHL": "12.89",
  "CCL": "1060.60",
  "CDSL": "1210.80",
  "CEATLTD": "3806.50",
  "CEIGALL": "271.85",
  "CEINSYS": "1009.25",
  "CELEBRITY": "7.84",
  "CELLO": "404.95",
  "CEMPRO": "546.40",
  "CENTENKA": "413.10",
  "CENTEXT": "19.89",
  "CENTRALBK": "36.61",
  "CENTRUM": "20.38",
  "CENTUM": "2774.50",
  "CENTURYPLY": "685.00",
  "CERA": "4667.90",
  "CESC": "159.42",
  "CEWATER": "246.50",
  "CGCL": "169.05",
  "CHALET": "774.55",
  "CHAMBLFERT": "434.10",
  "CHEMBOND": "143.23",
  "CHEMBONDCH": "134.82",
  "CHEMCON": "155.39",
  "CHEMFAB": "376.00",
  "CHEMICAL": "27.13",
  "CHEMPLASTS": "275.63",
  "CHENNPETRO": "943.80",
  "CHEVIOT": "991.80",
  "CHOICEGOLD": "158.54",
  "CHOICEIN": "645.25",
  "CHOLAHLDNG": "1486.60",
  "CIEINDIA": "456.70",
  "CIFL": "27.86",
  "CIGNITITEC": "1091.80",
  "CINELINE": "88.00",
  "CINEVISTA": "15.97",
  "CLEAN": "733.90",
  "CLEANMAX": "901.10",
  "CLEDUCATE": "48.90",
  "CLSEL": "249.55",
  "CMSINFO": "299.35",
  "CNL": "652.25",
  "COASTCORP": "43.10",
  "COCHINSHIP": "1444.30",
  "COFFEEDAY": "25.45",
  "COFORGE": "1107.90",
  "COHANCE": "289.35",
  "COLPAL": "1975.80",
  "COMMOIETF": "97.15",
  "COMPUSOFT": "12.72",
  "COMSYN": "153.34",
  "CONCOR": "467.15",
  "CONCORDBIO": "1174.50",
  "CONFIPET": "35.45",
  "CONS": "11.00",
  "CONSUMBEES": "119.41",
  "CONSUMER": "10.30",
  "CONSUMIETF": "111.40",
  "CONTROLPR": "628.05",
  "CORALFINAC": "32.04",
  "CORDSCABLE": "153.41",
  "COROMANDEL": "2008.50",
  "CORONA": "1588.60",
  "COSMOFIRST": "661.15",
  "COUNCODOS": "5.00",
  "CPCAP": "86.00",
  "CPEDU": "180.84",
  "CPPLUS": "1608.80",
  "CPSEETF": "104.47",
  "CRAFTSMAN": "7354.00",
  "CRAMC": "243.10",
  "CREATIVEYE": "6.84",
  "CREDITACC": "1177.20",
  "CREST": "340.65",
  "CRISIL": "4235.30",
  "CRIZAC": "210.67",
  "CROMPTON": "247.20",
  "CROWN": "118.79",
  "CSBBANK": "347.05",
  "CSLFINANCE": "245.65",
  "CTE": "24.79",
  "CUB": "243.85",
  "CUBEXTUB": "92.31",
  "CUMMINSIND": "4753.60",
  "CUPID": "81.35",
  "CYBERMEDIA": "13.58",
  "CYBERTECH": "104.40",
  "CYIENT": "902.55",
  "CYIENTDLM": "309.65",
  "DABUR": "459.35",
  "DALBHARAT": "1894.50",
  "DALMIASUG": "310.85",
  "DAMCAPITAL": "131.12",
  "DAMODARIND": "23.93",
  "DANGEE": "2.86",
  "DATAMATICS": "731.95",
  "DATAPATTNS": "3332.00",
  "DAVANGERE": "3.91",
  "DBCORP": "206.82",
  "DBEIL": "71.64",
  "DBL": "454.15",
  "DBOL": "103.15",
  "DBREALTY": "103.53",
  "DBSTOCKBRO": "25.19",
  "DCAL": "165.22",
  "DCBBANK": "174.01",
  "DCI": "255.65",
  "DCM": "60.88",
  "DCMFINSERV": "6.74",
  "DCMNVL": "113.46",
  "DCMSHRIRAM": "1015.70",
  "DCMSIL": "68.83",
  "DCMSRIND": "35.15",
  "DCW": "42.65",
  "DCXINDIA": "184.60",
  "DDEVPLSTIK": "260.10",
  "DECCANCE": "681.75",
  "DEEDEV": "309.90",
  "DEEPAKFERT": "978.30",
  "DEEPAKNTR": "1480.50",
  "DEEPINDS": "341.20",
  "DEFENCE": "67.42",
  "DELHIVERY": "408.20",
  "DELPHIFX": "11.15",
  "DELTACORP": "55.34",
  "DELTAMAGNT": "56.46",
  "DEN": "27.01",
  "DENORA": "705.70",
  "DENTA": "248.25",
  "DEVIT": "25.74",
  "DEVX": "37.52",
  "DEVYANI": "116.96",
  "DGCONTENT": "24.98",
  "DHAMPURSUG": "123.45",
  "DHANBANK": "23.31",
  "DHANUKA": "960.50",
  "DHARMAJ": "245.32",
  "DHRUV": "30.45",
  "DHUNINV": "867.05",
  "DIACABS": "136.82",
  "DIAMINESQ": "223.03",
  "DIAMONDYD": "956.00",
  "DICIND": "536.85",
  "DIFFNKG": "252.75",
  "DIGIDRIVE": "21.21",
  "DIGISPICE": "17.64",
  "DIGITIDE": "86.71",
  "DIGJAMLMTD": "40.50",
  "DISHTV": "2.55",
  "DIVGIITTS": "711.80",
  "DIVIDEND": "35.64",
  "DIVOPPBEES": "79.11",
  "DLINKINDIA": "394.15",
  "DMCC": "225.84",
  "DNAMEDIA": "3.30",
  "DODLA": "1001.30",
  "DOLATALGO": "73.84",
  "DOLLAR": "257.30",
  "DOLPHIN": "398.65",
  "DONEAR": "87.76",
  "DPABHUSHAN": "1023.70",
  "DPSCLTD": "8.66",
  "DPWIRES": "147.98",
  "DRCSYSTEMS": "13.34",
  "DREAMFOLKS": "74.78",
  "DREDGECORP": "947.60",
  "DSFCL": "25.12",
  "DSSL": "907.60",
  "DTIL": "132.01",
  "DUCON": "3.12",
  "DVL": "225.84",
  "DWARKESH": "38.83",
  "DYCL": "284.30",
  "DYNAMATECH": "9685.00",
  "DYNPRO": "209.12",
  "EASEMYTRIP": "7.24",
  "EBANKNIFTY": "55.55",
  "EBBETF0430": "1567.00",
  "EBBETF0431": "1401.98",
  "EBBETF0433": "1275.31",
  "EBGNG": "388.30",
  "ECAPINSURE": "22.97",
  "ECLERX": "3151.80",
  "ECOSMOBLTY": "134.87",
  "EDELWEISS": "108.09",
  "EFCIL": "218.38",
  "EGOLD": "159.80",
  "EIDPARRY": "810.35",
  "EIEL": "159.98",
  "EIFFL": "228.54",
  "EIHAHOTELS": "315.75",
  "EIHOTEL": "331.80",
  "EIMCOELECO": "1535.40",
  "EKC": "108.31",
  "ELDEHSG": "831.30",
  "ELECON": "391.00",
  "ELECTCAST": "79.19",
  "ELECTHERM": "612.00",
  "ELGIEQUIP": "490.65",
  "ELGIRUBCO": "40.95",
  "ELIN": "117.67",
  "ELIQUID": "1021.88",
  "ELLEN": "217.05",
  "ELM250": "15.59",
  "EMAMILTD": "428.10",
  "EMAMIPAP": "75.05",
  "EMAMIREAL": "58.14",
  "EMCURE": "1514.20",
  "EMIL": "94.65",
  "EMKAY": "219.20",
  "EMMBI": "82.87",
  "EMMVEE": "207.31",
  "EMSLIMITED": "304.60",
  "EMUDHRA": "432.75",
  "EMULTIMQ": "39.13",
  "ENDURANCE": "2460.50",
  "ENERGY": "37.02",
  "ENERGYDEV": "15.10",
  "ENGINERSIN": "200.69",
  "ENIFTY": "23.68",
  "ENIL": "106.79",
  "ENTERO": "1018.20",
  "EPACK": "266.90",
  "EPACKPEB": "161.76",
  "EPIGRAL": "882.10",
  "EPL": "192.89",
  "EQUAL200": "12.72",
  "EQUAL50": "314.63",
  "EQUAL50ADD": "325.10",
  "EQUITASBNK": "56.75",
  "ERIS": "1351.60",
  "ESABINDIA": "5326.00",
  "ESAFSFB": "24.79",
  "ESCORTS": "3229.80",
  "ESENSEX": "76.16",
  "ESG": "39.87",
  "ESILVER": "265.29",
  "ESSARSHPNG": "24.88",
  "ESSENTIA": "1.28",
  "ESTER": "95.93",
  "ETHOSLTD": "2107.40",
  "EUREKAFORB": "445.20",
  "EUROBOND": "155.88",
  "EUROPRATIK": "238.90",
  "EVEREADY": "313.10",
  "EVERESTIND": "372.40",
  "EVIETF": "28.24",
  "EVINDIA": "28.20",
  "EXCEL": "1.13",
  "EXCELINDUS": "883.65",
  "EXCELSOFT": "78.45",
  "EXICOM": "86.79",
  "EXIDEIND": "310.00",
  "EXPLEOSOL": "743.10",
  "EXXARO": "6.96",
  "FABTECH": "149.89",
  "FACT": "845.10",
  "FAIRCHEMOR": "548.10",
  "FCL": "22.50",
  "FCSSOFT": "1.47",
  "FDC": "366.90",
  "FEDERALBNK": "270.25",
  "FEDFINA": "128.23",
  "FIEMIND": "2101.60",
  "FILATEX": "42.74",
  "FILATFASH": "0.18",
  "FINCABLES": "894.45",
  "FINEORG": "4335.70",
  "FINIETF": "30.05",
  "FINKURVE": "59.99",
  "FINOPB": "177.69",
  "FINPIPE": "188.31",
  "FIRSTCRY": "223.17",
  "FISCHER": "35.15",
  "FIVESTAR": "368.85",
  "FLAIR": "298.20",
  "FLEXIADD": "9.40",
  "FLEXITUFF": "6.93",
  "FLUOROCHEM": "3185.30",
  "FMCGIETF": "51.43",
  "FMGOETZE": "394.05",
  "FMNL": "8.26",
  "FOCUS": "67.03",
  "FOODSIN": "58.25",
  "FORCEMOT": "21560.00",
  "FORTIS": "859.50",
  "FOSECOIND": "5074.50",
  "FRACTAL": "847.10",
  "FSL": "222.06",
  "FUSION": "167.60",
  "GABRIEL": "879.80",
  "GAEL": "130.37",
  "GALAPREC": "749.00",
  "GALAXYSURF": "1852.80",
  "GALLANTT": "551.65",
  "GANDHAR": "129.96",
  "GANDHITUBE": "771.35",
  "GANECOS": "768.20",
  "GANESHBE": "78.18",
  "GANESHCP": "169.69",
  "GANESHHOU": "634.65",
  "GANGAFORGE": "2.88",
  "GANGESSECU": "119.98",
  "GARFIBRES": "605.15",
  "GARUDA": "166.96",
  "GATECH": "0.48",
  "GATECHDVR": "0.44",
  "GATEWAY": "55.46",
  "GAYAHWS": "2.28",
  "GEECEE": "262.65",
  "GEEKAYWIRE": "20.89",
  "GENCON": "43.38",
  "GENESYS": "271.30",
  "GENUSPAPER": "11.77",
  "GENUSPOWER": "255.85",
  "GEOJITFSL": "59.53",
  "GESHIP": "1486.50",
  "GFLLIMITED": "46.15",
  "GHCL": "463.40",
  "GHCLTEXTIL": "72.94",
  "GICHSGFIN": "146.23",
  "GICRE": "369.30",
  "GILLANDERS": "82.58",
  "GILLETTE": "7991.50",
  "GILT10BETA": "26.12",
  "GILT5BETA": "64.67",
  "GILT5YBEES": "64.61",
  "GINNIFILA": "37.34",
  "GIPCL": "136.97",
  "GKENERGY": "108.07",
  "GKSL": "106.66",
  "GKWLIMITED": "1649.90",
  "GLAND": "1655.30",
  "GLAXO": "2504.40",
  "GLENMARK": "2256.40",
  "GLOBAL": "103.52",
  "GLOBALE": "10.76",
  "GLOBALVECT": "163.42",
  "GLOBE": "2.52",
  "GLOBECIVIL": "46.50",
  "GLOBUSSPR": "837.40",
  "GLOSTERLTD": "548.55",
  "GLOTTIS": "45.00",
  "GMBREW": "1000.65",
  "GMDCLTD": "555.50",
  "GMMPFAUDLR": "890.75",
  "GMRAIRPORT": "93.29",
  "GMRP&UI": "107.69",
  "GNA": "415.95",
  "GNFC": "433.00",
  "GOACARBON": "327.10",
  "GOCLCORP": "251.50",
  "GOCOLORS": "274.00",
  "GODAVARIB": "288.70",
  "GODFRYPHLP": "2091.60",
  "GODIGIT": "344.50",
  "GODREJAGRO": "586.55",
  "GODREJIND": "892.85",
  "GODREJPROP": "1616.30",
  "GOKEX": "602.90",
  "GOKUL": "41.22",
  "GOKULAGRO": "160.30",
  "GOLD1": "133.27",
  "GOLD360": "155.75",
  "GOLDADD": "155.57",
  "GOLDBEES": "132.43",
  "GOLDBETA": "134.80",
  "GOLDBND": "160.95",
  "GOLDCASE": "25.21",
  "GOLDETF": "155.50",
  "GOLDIAM": "312.00",
  "GOLDIETF": "137.07",
  "GOLDTECH": "37.71",
  "GOODLUCK": "1054.40",
  "GOPAL": "281.90",
  "GPIL": "264.70",
  "GPPL": "159.42",
  "GPTHEALTH": "127.03",
  "GPTINFRA": "106.90",
  "GRANULES": "586.75",
  "GRAPHITE": "645.70",
  "GRAVITA": "1503.20",
  "GREAVESCOT": "143.32",
  "GREENLAM": "223.40",
  "GREENPANEL": "205.29",
  "GREENPLY": "197.80",
  "GREENPOWER": "9.85",
  "GRINDWELL": "1488.00",
  "GRINFRA": "921.50",
  "GRMOVER": "157.31",
  "GROBTEA": "906.05",
  "GROWW": "158.23",
  "GROWWCAPM": "9.55",
  "GROWWCHEM": "27.05",
  "GROWWDEFNC": "82.44",
  "GROWWEV": "28.23",
  "GROWWGOLD": "15.64",
  "GROWWHOSPI": "46.97",
  "GROWWLIQID": "108.18",
  "GROWWLOVOL": "10.10",
  "GROWWMC150": "208.61",
  "GROWWMETAL": "11.24",
  "GROWWMOM50": "9.84",
  "GROWWN200": "10.81",
  "GROWWNET": "8.20",
  "GROWWNIFTY": "9.58",
  "GROWWNXT50": "66.61",
  "GROWWPOWER": "10.66",
  "GROWWPSE": "103.47",
  "GROWWRAIL": "30.74",
  "GROWWRLTY": "8.08",
  "GROWWSC250": "8.78",
  "GROWWSLVR": "25.95",
  "GRPLTD": "1807.90",
  "GRSE": "2423.80",
  "GRWRHITECH": "4078.80",
  "GSEC10ABSL": "110.85",
  "GSEC10IETF": "261.73",
  "GSEC10YEAR": "29.97",
  "GSEC5IETF": "64.54",
  "GSFC": "159.46",
  "GSLSU": "70.19",
  "GSPL": "278.80",
  "GSS": "11.98",
  "GTECJAINX": "20.39",
  "GTL": "6.79",
  "GTLINFRA": "1.08",
  "GTPL": "60.11",
  "GUFICBIO": "287.40",
  "GUJALKALI": "440.95",
  "GUJAPOLLO": "403.65",
  "GUJGASLTD": "388.40",
  "GUJRAFFIA": "37.08",
  "GUJTHEM": "297.85",
  "GULFOILLUB": "1010.00",
  "GULFPETRO": "31.47",
  "GULPOLY": "158.88",
  "GVPTECH": "6.11",
  "GVT&D": "3749.80",
  "HALDER": "255.00",
  "HALEOSLABS": "1262.00",
  "HAPPSTMNDS": "409.05",
  "HAPPYFORGE": "1277.00",
  "HARIOMPIPE": "324.15",
  "HARRMALAYA": "181.98",
  "HARSHA": "354.75",
  "HATHWAY": "10.04",
  "HATSUN": "945.95",
  "HAVISHA": "1.39",
  "HBLENGINE": "689.80",
  "HBSL": "50.91",
  "HCC": "16.09",
  "HCG": "560.30",
  "HCL-INSYS": "12.14",
  "HDBFS": "650.10",
  "HDFCAMC": "2429.00",
  "HDFCBSE500": "35.14",
  "HDFCGOLD": "136.82",
  "HDFCGROWTH": "112.81",
  "HDFCLIQUID": "1051.55",
  "HDFCLOWVOL": "19.78",
  "HDFCMID150": "21.05",
  "HDFCMOMENT": "29.49",
  "HDFCNEXT50": "67.73",
  "HDFCNIF100": "25.15",
  "HDFCNIFBAN": "56.57",
  "HDFCNIFIT": "31.44",
  "HDFCNIFTY": "265.02",
  "HDFCPSUBK": "89.22",
  "HDFCPVTBAN": "26.51",
  "HDFCQUAL": "55.44",
  "HDFCSENSEX": "85.83",
  "HDFCSILVER": "253.53",
  "HDFCSML250": "153.89",
  "HDFCVALUE": "128.70",
  "HEADSUP": "7.13",
  "HEALTHADD": "150.29",
  "HEALTHCARE": "18.72",
  "HEALTHIETF": "152.73",
  "HEALTHY": "15.30",
  "HECPROJECT": "111.08",
  "HEG": "519.15",
  "HEIDELBERG": "156.23",
  "HEMIPROP": "136.92",
  "HERANBA": "182.89",
  "HERITGFOOD": "322.10",
  "HEROMOTOCO": "5394.50",
  "HESTERBIO": "1435.50",
  "HEXATRADEX": "159.06",
  "HEXT": "418.70",
  "HFCL": "74.47",
  "HGINFRA": "507.65",
  "HGM": "52.12",
  "HGS": "374.25",
  "HIKAL": "180.25",
  "HILINFRA": "50.94",
  "HILTON": "16.78",
  "HIMATSEIDE": "87.14",
  "HINDCOMPOS": "404.40",
  "HINDCON": "19.13",
  "HINDCOPPER": "527.35",
  "HINDOILEXP": "147.44",
  "HINDPETRO": "384.35",
  "HINDWAREAP": "211.32",
  "HIRECT": "1510.20",
  "HISARMETAL": "154.56",
  "HITECH": "80.52",
  "HITECHCORP": "131.67",
  "HLEGLAS": "305.70",
  "HLVLTD": "7.70",
  "HMAAGRO": "24.77",
  "HMVL": "62.46",
  "HNDFDS": "480.40",
  "HNGSNGBEES": "510.07",
  "HOMEFIRST": "1002.60",
  "HONASA": "280.50",
  "HONAUT": "30580.00",
  "HONDAPOWER": "2029.20",
  "HPAL": "33.19",
  "HPIL": "121.23",
  "HPL": "322.10",
  "HSCL": "453.05",
  "HTMEDIA": "21.34",
  "HUBTOWN": "203.80",
  "HUDCO": "176.66",
  "HUHTAMAKI": "167.26",
  "HYBRIDFIN": "16.46",
  "IBULLSLTD": "9.94",
  "ICDSLTD": "45.37",
  "ICEMAKE": "820.20",
  "ICICIAMC": "2936.30",
  "ICICIB22": "122.13",
  "ICICIPRULI": "592.95",
  "ICIL": "244.05",
  "ICRA": "5416.50",
  "IDBI": "98.81",
  "IDEA": "9.56",
  "IDEAFORGE": "426.15",
  "IDFCFIRSTB": "64.78",
  "IDFNIFTYET": "259.93",
  "IEX": "122.76",
  "IFBAGRO": "743.70",
  "IFBIND": "1021.20",
  "IFCI": "53.95",
  "IFGLEXPOR": "153.90",
  "IGARASHI": "321.90",
  "IGCL": "63.66",
  "IGIL": "320.90",
  "IGL": "161.91",
  "IGPL": "356.55",
  "IIFL": "480.70",
  "IIFLCAPS": "292.00",
  "IITL": "133.53",
  "IKIO": "133.52",
  "IKS": "1373.90",
  "IMAGICAA": "43.08",
  "IMFA": "1263.10",
  "IMPAL": "1018.40",
  "INA": "98.02",
  "INCREDIBLE": "33.00",
  "INDBANK": "32.39",
  "INDGN": "443.45",
  "INDIACEM": "365.95",
  "INDIAGLYCO": "880.25",
  "INDIAMART": "2100.30",
  "INDIANB": "909.60",
  "INDIANCARD": "193.75",
  "INDIANHUME": "339.55",
  "INDIASHLTR": "689.90",
  "INDIGOPNTS": "818.05",
  "INDIQUBE": "156.47",
  "INDNIPPON": "790.60",
  "INDOAMIN": "99.92",
  "INDOBORAX": "244.29",
  "INDOCO": "200.01",
  "INDOFARM": "125.51",
  "INDORAMA": "35.25",
  "INDOSTAR": "203.84",
  "INDOTECH": "1375.40",
  "INDOTHAI": "248.75",
  "INDOUS": "99.67",
  "INDOWIND": "8.29",
  "INDRAMEDCO": "398.65",
  "INDSWFTLAB": "143.47",
  "INDTERRAIN": "29.13",
  "INDUSINDBK": "831.35",
  "INDUSTOWER": "442.05",
  "INFOBEAN": "129.10",
  "INFOMEDIA": "5.15",
  "INFRA": "10.99",
  "INFRABEES": "928.56",
  "INFRAIETF": "92.38",
  "INGERRAND": "3810.00",
  "INNOVACAP": "713.95",
  "INNOVANA": "375.35",
  "INOXGREEN": "151.50",
  "INOXINDIA": "1196.50",
  "INOXWIND": "83.68",
  "INSECTICID": "609.95",
  "INTELLECT": "667.10",
  "INTENTECH": "91.24",
  "INTERARCH": "1792.00",
  "INTERNET": "11.04",
  "INTLCONV": "75.27",
  "INVENTURE": "1.02",
  "IOB": "33.86",
  "IOLCP": "70.63",
  "IONEXCHANG": "355.70",
  "IPCALAB": "1560.80",
  "IPL": "148.24",
  "IRB": "42.57",
  "IRCON": "136.55",
  "IRCTC": "536.70",
  "IREDA": "117.03",
  "IRIS": "237.40",
  "IRISDOREME": "30.49",
  "IRMENERGY": "211.59",
  "ISFT": "73.20",
  "ISGEC": "937.60",
  "ISHANCH": "56.48",
  "IT": "32.66",
  "ITADD": "31.19",
  "ITBEES": "32.69",
  "ITBETA": "309.69",
  "ITCHOTELS": "157.96",
  "ITDC": "464.25",
  "ITETF": "31.10",
  "ITI": "258.95",
  "ITIETF": "32.68",
  "IVALUE": "230.26",
  "IVC": "6.99",
  "IVP": "132.61",
  "IVZINGOLD": "13935.70",
  "IVZINNIFTY": "2762.00",
  "IXIGO": "168.19",
  "J&KBANK": "127.51",
  "JAGRAN": "62.86",
  "JAGSNPHARM": "189.61",
  "JAIBALAJI": "66.56",
  "JAICORPLTD": "102.73",
  "JAINREC": "428.55",
  "JAIPURKURT": "30.27",
  "JAMNAAUTO": "122.42",
  "JARO": "405.45",
  "JASH": "375.40",
  "JAYAGROGN": "183.80",
  "JAYBARMARU": "90.90",
  "JAYKAY": "135.98",
  "JAYNECOIND": "75.36",
  "JAYSREETEA": "88.32",
  "JBCHEPHARM": "2131.40",
  "JBMA": "514.05",
  "JETFREIGHT": "18.88",
  "JGCHEM": "343.15",
  "JHS": "8.97",
  "JINDALPHOT": "1237.40",
  "JINDALPOLY": "939.30",
  "JINDRILL": "515.00",
  "JINDWORLD": "21.78",
  "JISLDVREQS": "22.26",
  "JISLJALEQS": "34.38",
  "JKCEMENT": "5199.00",
  "JKIL": "500.45",
  "JKIPL": "54.51",
  "JKLAKSHMI": "608.60",
  "JKPAPER": "347.70",
  "JKTYRE": "430.70",
  "JLHL": "1254.00",
  "JMA": "84.16",
  "JMFINANCIL": "123.38",
  "JNKINDIA": "243.92",
  "JOCIL": "125.08",
  "JPOLYINVST": "1312.70",
  "JPPOWER": "14.17",
  "JSFB": "351.85",
  "JSL": "746.65",
  "JSLL": "598.25",
  "JSWCEMENT": "119.84",
  "JSWHL": "15972.00",
  "JSWINFRA": "258.95",
  "JTEKTINDIA": "135.17",
  "JTLIND": "54.25",
  "JUBLCPL": "1738.60",
  "JUBLFOOD": "461.75",
  "JUBLINGREA": "577.95",
  "JUBLPHARMA": "827.65",
  "JUNIORBEES": "715.84",
  "JUNIPER": "204.35",
  "JUSTDIAL": "525.25",
  "JWL": "272.20",
  "JYOTHYLAB": "229.10",
  "JYOTICNC": "759.80",
  "JYOTISTRUC": "11.10",
  "KABRAEXTRU": "230.60",
  "KAJARIACER": "940.00",
  "KAKATCEM": "106.17",
  "KALAMANDIR": "99.19",
  "KALPATARU": "299.50",
  "KALYANIFRG": "571.45",
  "KALYANKJIL": "389.95",
  "KAMATHOTEL": "188.84",
  "KAMDHENU": "22.24",
  "KAMOPAINTS": "4.54",
  "KANANIIND": "1.35",
  "KANORICHEM": "62.26",
  "KANPRPLA": "175.89",
  "KANSAINER": "188.06",
  "KARMAENG": "40.30",
  "KARURVYSYA": "295.70",
  "KAUSHALYA": "821.85",
  "KAYA": "313.15",
  "KAYNES": "3700.30",
  "KCP": "147.29",
  "KCPSUGIND": "24.02",
  "KDDL": "2302.20",
  "KEC": "560.55",
  "KECL": "82.97",
  "KEEPLEARN": "1.96",
  "KEI": "4330.00",
  "KELLTONTEC": "17.15",
  "KERNEX": "993.50",
  "KEYFINSERV": "261.60",
  "KFINTECH": "907.60",
  "KHADIM": "105.77",
  "KHAICHEM": "54.26",
  "KHAITANLTD": "98.32",
  "KHANDSE": "18.10",
  "KICL": "4691.50",
  "KILITCH": "327.75",
  "KIMS": "664.40",
  "KINGFA": "4092.00",
  "KIOCL": "318.90",
  "KIRIINDUS": "401.30",
  "KIRLOSBROS": "1590.00",
  "KIRLOSENG": "1468.90",
  "KIRLOSIND": "2811.40",
  "KIRLPNU": "1120.20",
  "KITEX": "169.45",
  "KKCL": "475.95",
  "KMEW": "1568.40",
  "KMSUGAR": "25.66",
  "KNAGRI": "179.66",
  "KNRCON": "126.65",
  "KOHINOOR": "24.40",
  "KOKUYOCMLN": "78.11",
  "KOLTEPATIL": "333.90",
  "KOPRAN": "122.01",
  "KOTARISUG": "24.51",
  "KOTHARIPET": "112.05",
  "KOTHARIPRO": "64.04",
  "KOTYARK": "360.65",
  "KPEL": "295.00",
  "KPIGREEN": "394.70",
  "KPIL": "1147.10",
  "KPITTECH": "671.25",
  "KPRMILL": "909.40",
  "KRBL": "319.35",
  "KREBSBIO": "53.72",
  "KRIDHANINF": "2.76",
  "KRISHANA": "507.40",
  "KRISHIVAL": "317.20",
  "KRISHNADEF": "1077.50",
  "KRITI": "81.33",
  "KRITIKA": "5.89",
  "KRITINUT": "64.13",
  "KRN": "895.90",
  "KRONOX": "112.40",
  "KROSS": "188.19",
  "KRSNAA": "611.80",
  "KRYSTAL": "585.05",
  "KSB": "768.15",
  "KSCL": "800.10",
  "KSHINTL": "412.65",
  "KSL": "699.45",
  "KSOLVES": "282.40",
  "KTKBANK": "226.70",
  "KUANTUM": "81.69",
  "KWIL": "25.54",
  "LAGNAM": "68.30",
  "LAL": "6.99",
  "LALPATHLAB": "1377.00",
  "LAMBODHARA": "98.24",
  "LANDMARK": "353.70",
  "LAOPALA": "193.21",
  "LASA": "7.48",
  "LATENTVIEW": "295.05",
  "LATTEYS": "20.40",
  "LAURUSLABS": "1046.80",
  "LAXMIDENTL": "183.67",
  "LAXMIINDIA": "83.63",
  "LCCINFOTEC": "5.42",
  "LEMERITE": "441.20",
  "LEMONTREE": "105.44",
  "LENSKART": "504.55",
  "LFIC": "125.92",
  "LGBBROSLTD": "1858.50",
  "LGEINDIA": "1577.00",
  "LGHL": "272.30",
  "LIBAS": "10.29",
  "LIBERTSHOE": "239.91",
  "LICHSGFIN": "498.50",
  "LICMFGOLD": "143.90",
  "LICNETFGSC": "29.00",
  "LICNETFN50": "264.00",
  "LICNETFSEN": "855.25",
  "LICNFNHGP": "265.06",
  "LICNMID100": "56.69",
  "LIKHITHA": "149.81",
  "LINC": "101.50",
  "LINCOLN": "617.65",
  "LINDEINDIA": "7189.50",
  "LIQGRWBEES": "1031.02",
  "LIQUID": "999.99",
  "LIQUID1": "1094.85",
  "LIQUIDADD": "1116.98",
  "LIQUIDBEES": "999.99",
  "LIQUIDBETF": "1072.48",
  "LIQUIDCASE": "113.09",
  "LIQUIDETF": "999.99",
  "LIQUIDIETF": "999.99",
  "LIQUIDPLUS": "1076.10",
  "LIQUIDSBI": "1000.00",
  "LIQUIDSHRI": "1095.42",
  "LLOYDSENGG": "43.93",
  "LLOYDSENT": "48.72",
  "LLOYDSME": "1205.00",
  "LMW": "14520.00",
  "LOKESHMACH": "210.50",
  "LORDSCHLO": "119.17",
  "LOTUSDEV": "124.12",
  "LOTUSEYE": "103.51",
  "LOVABLE": "68.38",
  "LOWVOL": "197.75",
  "LOWVOL1": "20.21",
  "LOWVOLIETF": "21.17",
  "LPDC": "5.85",
  "LTF": "265.50",
  "LTFOODS": "390.00",
  "LTGILTBEES": "29.51",
  "LTGILTCASE": "30.04",
  "LTTS": "3129.50",
  "LUMAXIND": "4951.00",
  "LUMAXTECH": "1392.50",
  "LUPIN": "2357.30",
  "LUXIND": "870.15",
  "LXCHEM": "122.46",
  "LYKALABS": "54.93",
  "LYPSAGEMS": "4.73",
  "M&MFIN": "346.30",
  "MACPOWER": "928.40",
  "MADHAV": "35.41",
  "MADHUCON": "4.60",
  "MADRASFERT": "64.03",
  "MAFANG": "162.88",
  "MAGADSUGAR": "447.05",
  "MAGNUM": "19.57",
  "MAHABANK": "67.11",
  "MAHAPEXLTD": "115.39",
  "MAHASTEEL": "1020.90",
  "MAHEPC": "113.53",
  "MAHESHWARI": "40.32",
  "MAHKTECH": "22.99",
  "MAHLIFE": "354.65",
  "MAHLOG": "398.20",
  "MAHSCOOTER": "12816.00",
  "MAHSEAMLES": "561.50",
  "MAITHANALL": "941.70",
  "MAKEINDIA": "153.07",
  "MALLCOM": "1065.50",
  "MALUPAPER": "31.39",
  "MAMATA": "388.65",
  "MANAKCOAT": "112.36",
  "MANAKSIA": "55.96",
  "MANAKSTEEL": "55.05",
  "MANALIPETC": "49.14",
  "MANAPPURAM": "255.55",
  "MANBA": "115.59",
  "MANCREDIT": "168.19",
  "MANGLMCEM": "809.80",
  "MANINDS": "411.00",
  "MANINFRA": "98.21",
  "MANKIND": "2207.90",
  "MANOMAY": "225.01",
  "MANORAMA": "1325.40",
  "MANORG": "416.45",
  "MANUFGBEES": "152.30",
  "MANUGRAPH": "14.29",
  "MANYAVAR": "352.95",
  "MAPMYINDIA": "967.10",
  "MARALOVER": "41.94",
  "MARATHON": "406.55",
  "MARICO": "757.15",
  "MARINE": "182.45",
  "MARKOLINES": "151.35",
  "MARKSANS": "173.18",
  "MASFIN": "304.05",
  "MASKINVEST": "132.00",
  "MASPTOP50": "69.77",
  "MASTEK": "1557.70",
  "MASTERTR": "74.15",
  "MATRIMONY": "383.65",
  "MAWANASUG": "79.98",
  "MAXESTATES": "374.80",
  "MAXIND": "149.28",
  "MAYURUNIQ": "521.00",
  "MAZDA": "188.63",
  "MBAPL": "466.95",
  "MBEL": "293.45",
  "MBLINFRA": "24.44",
  "MCLEODRUSS": "38.60",
  "MCLOUD": "22.87",
  "MCX": "2526.10",
  "MEDANTA": "1103.20",
  "MEDIASSIST": "312.60",
  "MEDICAMEQ": "275.20",
  "MEDICO": "38.94",
  "MEDPLUS": "844.10",
  "MEESHO": "141.37",
  "MEGASTAR": "236.02",
  "MEIL": "235.27",
  "MENONBE": "126.91",
  "METAL": "11.93",
  "METALIETF": "11.89",
  "METROBRAND": "950.80",
  "METROPOLIS": "1823.90",
  "MFML": "22.94",
  "MFSL": "1696.20",
  "MGEL": "10.26",
  "MGL": "1050.20",
  "MHLXMIRU": "166.38",
  "MHRIL": "265.95",
  "MICEL": "35.02",
  "MID150": "21.14",
  "MID150BEES": "215.14",
  "MID150CASE": "10.42",
  "MIDCAP": "16.28",
  "MIDCAPADD": "20.84",
  "MIDCAPBETA": "212.92",
  "MIDCAPETF": "21.22",
  "MIDCAPIETF": "21.50",
  "MIDHANI": "332.30",
  "MIDQ50ADD": "228.32",
  "MIDSELIETF": "16.62",
  "MIDSMALL": "45.57",
  "MIDWESTLTD": "1225.80",
  "MINDACORP": "481.15",
  "MINDTECK": "191.71",
  "MIRCELECTR": "24.96",
  "MIRZAINT": "31.38",
  "MITCON": "54.51",
  "MITTAL": "0.83",
  "MKPL": "5.10",
  "MMFL": "448.65",
  "MMP": "226.46",
  "MMTC": "55.63",
  "MNC": "30.68",
  "MOALPHA50": "47.80",
  "MOBIKWIK": "181.27",
  "MOCAPITAL": "45.48",
  "MODEFENCE": "90.37",
  "MODINATUR": "272.90",
  "MODIRUBBER": "113.83",
  "MODIS": "306.25",
  "MODISONLTD": "125.74",
  "MODTHREAD": "51.76",
  "MOENERGY": "37.10",
  "MOGOLD": "158.35",
  "MOGSEC": "63.78",
  "MOHEALTH": "44.29",
  "MOHITIND": "23.02",
  "MOIL": "271.95",
  "MOINFRA": "58.92",
  "MOIPO": "40.18",
  "MOKSH": "11.50",
  "MOL": "45.17",
  "MOLDTECH": "128.16",
  "MOLDTKPAC": "515.50",
  "MOLOWVOL": "36.30",
  "MOM100": "60.70",
  "MOM30IETF": "29.59",
  "MOM50": "246.19",
  "MOMENTUM": "29.51",
  "MOMENTUM30": "29.44",
  "MOMENTUM50": "48.58",
  "MOMGF": "149.81",
  "MOMIDMTM": "59.35",
  "MOMNC": "29.82",
  "MOMOMENTUM": "58.73",
  "MON100": "223.82",
  "MON50EQUAL": "31.53",
  "MONARCH": "251.45",
  "MONEXT50": "66.24",
  "MONEYBOXX": "66.13",
  "MONIFTY100": "24.48",
  "MONIFTY500": "22.38",
  "MONQ50": "97.48",
  "MONTECARLO": "519.95",
  "MOPSE": "104.80",
  "MOQUALITY": "188.86",
  "MOREALTY": "71.90",
  "MOREPENLAB": "40.26",
  "MOSCHIP": "171.64",
  "MOSERVICE": "30.33",
  "MOSILVER": "261.39",
  "MOSMALL250": "15.33",
  "MOTILALOFS": "697.40",
  "MOTISONS": "13.49",
  "MOTOGENFIN": "19.89",
  "MOTOUR": "71.52",
  "MOVALUE": "117.42",
  "MPHASIS": "2185.20",
  "MPSLTD": "1471.90",
  "MRF": "138005.00",
  "MRPL": "191.44",
  "MSCIADD": "28.29",
  "MSCIINDIA": "28.58",
  "MSPL": "31.71",
  "MSTCLTD": "428.80",
  "MSUMI": "40.06",
  "MTARTECH": "3514.00",
  "MTNL": "26.08",
  "MUFIN": "104.34",
  "MUFTI": "78.08",
  "MUKANDLTD": "120.72",
  "MUKKA": "22.43",
  "MUKTAARTS": "47.32",
  "MULTICAP": "15.26",
  "MUNJALAU": "78.41",
  "MUNJALSHOW": "124.76",
  "MURUDCERA": "30.72",
  "MUTHOOTCAP": "201.42",
  "MUTHOOTFIN": "3244.00",
  "MUTHOOTMF": "153.56",
  "MVGJL": "151.93",
  "MWL": "273.40",
  "NACLIND": "121.06",
  "NAGAFERT": "4.19",
  "NAGREEKCAP": "24.97",
  "NAGREEKEXP": "23.40",
  "NAHARCAP": "227.01",
  "NAHARINDUS": "92.25",
  "NAHARPOLY": "238.38",
  "NAHARSPING": "194.95",
  "NAM-INDIA": "846.35",
  "NARMADA": "32.22",
  "NATCAPSUQ": "151.70",
  "NATCOPHARM": "1016.20",
  "NATHBIOGEN": "144.28",
  "NATIONALUM": "409.15",
  "NAVA": "575.50",
  "NAVINFLUOR": "6220.00",
  "NAVKARCORP": "88.32",
  "NAVKARURB": "1.00",
  "NAVNETEDUL": "135.54",
  "NAZARA": "242.50",
  "NBCC": "86.58",
  "NBIFIN": "1811.30",
  "NCC": "149.50",
  "NCLIND": "183.76",
  "NDGL": "2399.10",
  "NDL": "2.49",
  "NDLVENTURE": "114.63",
  "NDRAUTO": "692.20",
  "NDTV": "77.13",
  "NECCLTD": "13.76",
  "NECLIFE": "11.33",
  "NELCAST": "123.92",
  "NELCO": "594.35",
  "NEOGEN": "1446.40",
  "NEPHROPLUS": "560.00",
  "NESCO": "1066.00",
  "NETF": "256.02",
  "NETWEB": "3226.20",
  "NETWORK18": "32.87",
  "NEULANDLAB": "12574.00",
  "NEWGEN": "451.85",
  "NEXT30ADD": "39.95",
  "NEXT50": "682.90",
  "NEXT50ADD": "66.57",
  "NEXT50BETA": "71.42",
  "NEXT50ETF": "66.84",
  "NEXT50IETF": "69.96",
  "NEXTMEDIA": "5.17",
  "NFL": "72.99",
  "NGIL": "25.09",
  "NGLFINE": "2333.60",
  "NH": "1705.50",
  "NHPC": "74.78",
  "NIACL": "137.89",
  "NIBE": "1073.70",
  "NIBL": "30.65",
  "NIF100BEES": "258.12",
  "NIF100IETF": "27.13",
  "NIFTY1": "261.17",
  "NIFTY100EW": "32.43",
  "NIFTYADD": "247.78",
  "NIFTYBEES": "267.94",
  "NIFTYBETA": "260.79",
  "NIFTYBETF": "241.96",
  "NIFTYCASE": "9.43",
  "NIFTYETF": "255.66",
  "NIFTYIETF": "266.56",
  "NIFTYQLITY": "20.24",
  "NIITLTD": "65.62",
  "NIITMTS": "306.60",
  "NILAINFRA": "7.29",
  "NILASPACES": "13.15",
  "NILKAMAL": "1293.80",
  "NINSYS": "301.50",
  "NIPPOBATRY": "296.90",
  "NIRAJ": "26.69",
  "NITCO": "67.48",
  "NITINSPIN": "360.40",
  "NITIRAJ": "221.72",
  "NIVABUPA": "70.06",
  "NKIND": "63.54",
  "NLCINDIA": "265.25",
  "NMDC": "80.87",
  "NOCIL": "129.93",
  "NOIDATOLL": "3.66",
  "NORTHARC": "233.25",
  "NOVAAGRI": "27.94",
  "NPBET": "269.80",
  "NPST": "984.80",
  "NRAIL": "409.35",
  "NRBBEARING": "264.65",
  "NRL": "51.03",
  "NSIL": "5642.50",
  "NSLNISP": "37.89",
  "NUCLEUS": "756.95",
  "NURECA": "267.90",
  "NUVAMA": "1183.80",
  "NUVOCO": "294.30",
  "NV20": "14.30",
  "NV20BEES": "143.57",
  "NV20IETF": "13.94",
  "NYKAA": "244.95",
  "OAL": "248.00",
  "OBCL": "55.60",
  "OBEROIRLTY": "1470.30",
  "OCCLLTD": "86.27",
  "ODIGMA": "22.89",
  "OFSS": "6694.50",
  "OIL": "479.30",
  "OILCOUNTUB": "44.89",
  "OILIETF": "11.71",
  "OLAELEC": "23.70",
  "OLECTRA": "903.75",
  "OMAXAUTO": "100.60",
  "OMAXE": "72.75",
  "OMFREIGHT": "76.57",
  "OMINFRAL": "87.94",
  "OMNI": "220.35",
  "ONELIFECAP": "15.22",
  "ONEPOINT": "45.56",
  "ONESOURCE": "1469.20",
  "ONMOBILE": "50.60",
  "ONWARDTEC": "252.40",
  "OPTIEMUS": "356.75",
  "ORBTEXP": "162.02",
  "ORCHASP": "2.00",
  "ORCHPHARMA": "540.85",
  "ORICONENT": "65.08",
  "ORIENTALTL": "6.02",
  "ORIENTBELL": "280.45",
  "ORIENTCEM": "139.97",
  "ORIENTCER": "38.05",
  "ORIENTELEC": "170.66",
  "ORIENTHOT": "87.89",
  "ORIENTLTD": "68.77",
  "ORIENTPPR": "16.87",
  "ORIENTTECH": "263.35",
  "ORISSAMINE": "3847.50",
  "ORKLAINDIA": "547.90",
  "OSIAHYPER": "6.69",
  "OSWALAGRO": "43.65",
  "OSWALGREEN": "25.05",
  "OSWALPUMPS": "306.65",
  "OSWALSEEDS": "11.93",
  "PACEDIGITK": "159.22",
  "PAGEIND": "30860.00",
  "PAISALO": "32.17",
  "PAKKA": "81.96",
  "PALASHSECU": "88.04",
  "PALREDTEC": "29.71",
  "PANACEABIO": "341.55",
  "PANAMAPET": "268.85",
  "PAR": "88.88",
  "PARACABLES": "33.14",
  "PARADEEP": "112.62",
  "PARAGMILK": "203.92",
  "PARAS": "668.80",
  "PARKHOSPS": "198.71",
  "PARKHOTELS": "116.20",
  "PARSVNATH": "7.21",
  "PASHUPATI": "996.10",
  "PASUPTAC": "46.37",
  "PATANJALI": "490.60",
  "PATELENG": "25.13",
  "PATELRMART": "172.33",
  "PATINTLOG": "9.64",
  "PAUSHAKLTD": "422.80",
  "PAVNAIND": "18.95",
  "PAYTM": "1009.10",
  "PCBL": "272.00",
  "PCJEWELLER": "8.80",
  "PDMJEPAPER": "75.64",
  "PDSL": "286.80",
  "PEARLPOLY": "17.42",
  "PENIND": "144.27",
  "PENINLAND": "16.06",
  "PERSISTENT": "4714.40",
  "PETRONET": "296.70",
  "PFIZER": "4695.00",
  "PFOCUS": "274.45",
  "PFS": "28.43",
  "PGEL": "532.20",
  "PGHH": "10821.00",
  "PGHL": "4889.30",
  "PGIL": "1515.30",
  "PHARMABEES": "23.91",
  "PHOENIXLTD": "1560.20",
  "PICCADIL": "541.30",
  "PIGL": "101.32",
  "PIIND": "2952.40",
  "PILANIINVS": "4441.00",
  "PILITA": "7.81",
  "PINELABS": "164.81",
  "PIONEEREMB": "25.43",
  "PIRAMALFIN": "1787.30",
  "PITTIENG": "808.55",
  "PIXTRANS": "1446.30",
  "PKTEA": "796.95",
  "PLASTIBLEN": "138.35",
  "PLATIND": "211.32",
  "PLAZACABLE": "35.61",
  "PNBGILTS": "74.01",
  "PNBHOUSING": "780.15",
  "PNC": "22.45",
  "PNCINFRA": "201.86",
  "PNGJL": "568.20",
  "PNGSREVA": "392.80",
  "POCL": "1104.00",
  "PODDARMENT": "221.10",
  "POKARNA": "883.75",
  "POLICYBZR": "1462.70",
  "POLYCAB": "7455.00",
  "POLYMED": "1312.30",
  "POLYPLEX": "821.85",
  "PONNIERODE": "273.70",
  "POONAWALLA": "410.95",
  "POWERINDIA": "24880.00",
  "POWERMECH": "1980.20",
  "PPAP": "202.42",
  "PPL": "199.42",
  "PPLPHARMA": "145.54",
  "PRABHA": "155.16",
  "PRAENG": "20.02",
  "PRAJIND": "314.45",
  "PRAKASH": "128.06",
  "PRAKASHSTL": "4.11",
  "PRAXIS": "6.57",
  "PRECAM": "126.19",
  "PRECWIRE": "319.65",
  "PREMEXPLN": "474.50",
  "PREMIERENE": "789.35",
  "PREMIERPOL": "61.23",
  "PRESTIGE": "1252.70",
  "PRICOLLTD": "541.65",
  "PRIMESECU": "270.05",
  "PRIMO": "17.35",
  "PRINCEPIPE": "255.15",
  "PRITI": "37.02",
  "PRITIKAUTO": "12.30",
  "PRIVISCL": "2869.40",
  "PROSTARM": "129.29",
  "PROTEAN": "551.20",
  "PROZONER": "44.62",
  "PRSMJOHNSN": "125.18",
  "PRUDENT": "2273.00",
  "PRUDMOULI": "15.36",
  "PSB": "24.24",
  "PSPPROJECT": "673.50",
  "PSUBANK": "883.95",
  "PSUBANKADD": "89.30",
  "PSUBNKBEES": "98.24",
  "PSUBNKIETF": "89.40",
  "PTC": "160.87",
  "PTCIL": "17958.00",
  "PTL": "37.45",
  "PUNJABCHEM": "1081.30",
  "PURVA": "187.09",
  "PVP": "24.94",
  "PVRINOX": "996.30",
  "PVSL": "90.42",
  "PVTBANIETF": "26.22",
  "PVTBANKADD": "26.40",
  "PWL": "84.29",
  "PYRAMID": "148.54",
  "QGOLDHALF": "132.97",
  "QNIFTY": "258.63",
  "QPOWER": "820.35",
  "QUADFUTURE": "320.20",
  "QUAL30IETF": "19.99",
  "QUALITY30": "19.72",
  "QUESS": "190.23",
  "QUICKHEAL": "154.81",
  "RACE": "110.48",
  "RACLGEAR": "1286.50",
  "RADAAN": "2.99",
  "RADHIKAJWE": "60.44",
  "RADIANTCMS": "37.56",
  "RADICO": "2857.50",
  "RADIOCITY": "5.76",
  "RAILTEL": "287.10",
  "RAIN": "118.69",
  "RAINBOW": "1174.00",
  "RAJMET": "3.55",
  "RAJOOENG": "60.25",
  "RAJRATAN": "386.45",
  "RAJSREESUG": "28.33",
  "RAJTV": "39.18",
  "RALLIS": "247.35",
  "RAMANEWS": "36.18",
  "RAMAPHO": "115.62",
  "RAMASTEEL": "5.89",
  "RAMCOCEM": "995.70",
  "RAMCOIND": "276.35",
  "RAMCOSYS": "418.05",
  "RAMKY": "458.55",
  "RAMRAT": "316.10",
  "RANASUG": "12.06",
  "RANEHOLDIN": "1172.50",
  "RATEGAIN": "509.85",
  "RATNAMANI": "2360.30",
  "RATNAVEER": "140.90",
  "RAYMOND": "377.95",
  "RAYMONDLSL": "787.65",
  "RAYMONDREL": "389.00",
  "RBA": "61.18",
  "RBLBANK": "299.80",
  "RBZJEWEL": "116.68",
  "RCF": "120.67",
  "REDINGTON": "245.55",
  "REDTAPE": "113.99",
  "REFEX": "208.28",
  "REGAAL": "87.69",
  "REGENCERAM": "43.00",
  "RELAXO": "302.65",
  "RELCHEMQ": "110.65",
  "RELIABLE": "116.37",
  "RELIGARE": "210.58",
  "RELTD": "135.97",
  "REMSONSIND": "105.49",
  "RENUKA": "24.56",
  "REPCOHOME": "369.05",
  "REPL": "73.80",
  "REPRO": "369.05",
  "RESPONIND": "164.12",
  "RETAIL": "20.81",
  "RGL": "104.50",
  "RHETAN": "25.05",
  "RHIM": "380.90",
  "RHL": "183.13",
  "RICOAUTO": "111.81",
  "RIIL": "689.20",
  "RISHABH": "392.35",
  "RITCO": "204.94",
  "RITES": "199.65",
  "RKDL": "18.65",
  "RKEC": "39.99",
  "RKFORGE": "560.10",
  "RKSWAMY": "98.41",
  "RMDRIP": "42.03",
  "RML": "806.15",
  "ROHLTD": "336.85",
  "ROLEXRINGS": "122.06",
  "ROML": "45.00",
  "ROSSARI": "453.25",
  "ROSSELLIND": "45.76",
  "ROSSTECH": "718.20",
  "ROTO": "60.21",
  "ROUTE": "475.95",
  "RPEL": "669.15",
  "RPGLIFE": "1964.90",
  "RPOWER": "23.66",
  "RPPINFRA": "70.33",
  "RPPL": "15.51",
  "RPSGVENT": "612.45",
  "RPTECH": "349.50",
  "RRKABEL": "1433.80",
  "RSSOFTWARE": "27.85",
  "RSWM": "143.44",
  "RSYSTEMS": "288.20",
  "RTNINDIA": "26.73",
  "RTNPOWER": "8.53",
  "RUBFILA": "63.28",
  "RUBICON": "799.15",
  "RUBYMILLS": "199.36",
  "RUCHINFRA": "5.37",
  "RUCHIRA": "105.17",
  "RUDRA": "17.34",
  "RUPA": "128.99",
  "RUSHIL": "16.21",
  "RUSTOMJEE": "395.35",
  "RVHL": "38.31",
  "RVNL": "279.60",
  "RVTH": "558.80",
  "SAATVIKGL": "361.40",
  "SADBHIN": "2.97",
  "SADHNANIQ": "1.61",
  "SAFARI": "1640.00",
  "SAGARDEEP": "22.82",
  "SAGCEM": "180.97",
  "SAGILITY": "39.49",
  "SAHYADRI": "231.00",
  "SAIL": "153.65",
  "SAILIFE": "1008.85",
  "SAKAR": "556.80",
  "SAKHTISUG": "15.17",
  "SAKSOFT": "131.25",
  "SAKUMA": "1.60",
  "SALASAR": "7.21",
  "SALONA": "270.95",
  "SALZERELEC": "599.10",
  "SAMBHAAV": "6.41",
  "SAMBHV": "91.62",
  "SAMHI": "146.48",
  "SAMMAANCAP": "142.42",
  "SAMPANN": "30.97",
  "SANATHAN": "414.30",
  "SANDESH": "945.65",
  "SANDHAR": "491.10",
  "SANDUMA": "199.79",
  "SANGAMIND": "426.55",
  "SANGHIIND": "53.55",
  "SANGHVIMOV": "241.85",
  "SANOFI": "3595.00",
  "SANOFICONR": "4357.00",
  "SANSERA": "2079.60",
  "SANSTAR": "86.60",
  "SAPPHIRE": "169.33",
  "SARDAEN": "550.60",
  "SAREGAMA": "347.55",
  "SARLAPOLY": "79.61",
  "SARVESHWAR": "3.28",
  "SASKEN": "1074.40",
  "SASTASUNDR": "282.00",
  "SATIA": "62.32",
  "SATIN": "147.03",
  "SAURASHCEM": "61.63",
  "SBC": "32.19",
  "SBCL": "423.55",
  "SBFC": "92.53",
  "SBGLP": "26.98",
  "SBIBPB": "51.26",
  "SBICARD": "710.25",
  "SBIETFCON": "110.89",
  "SBIETFIT": "326.55",
  "SBIETFPB": "264.79",
  "SBIETFQLTY": "213.30",
  "SBILIQETF": "1030.10",
  "SBIMIDMOM": "58.47",
  "SBINEQWETF": "31.50",
  "SBISILVER": "259.07",
  "SCHAEFFLER": "3988.60",
  "SCHAND": "153.03",
  "SCI": "250.70",
  "SCILAL": "43.23",
  "SCODATUBES": "123.05",
  "SDBL": "76.72",
  "SDL26BEES": "136.82",
  "SEAMECLTD": "1340.20",
  "SECMARK": "114.69",
  "SECURKLOUD": "22.60",
  "SEDEMAC": "1441.30",
  "SEJALLTD": "538.75",
  "SELECTIPO": "40.15",
  "SELMC": "29.68",
  "SEMAC": "209.77",
  "SENCO": "298.05",
  "SENORES": "736.55",
  "SENSEXADD": "77.99",
  "SENSEXBETA": "837.26",
  "SENSEXETF": "77.99",
  "SENSEXIETF": "869.83",
  "SEPC": "6.23",
  "SERVOTECH": "71.16",
  "SESHAPAPER": "251.00",
  "SETCO": "17.98",
  "SETF10GILT": "261.82",
  "SETFGOLD": "136.61",
  "SETFNIF50": "253.09",
  "SETFNIFBK": "564.73",
  "SETFNN50": "710.13",
  "SETL": "121.86",
  "SFL": "522.30",
  "SGFIN": "389.45",
  "SGIL": "500.15",
  "SGL": "11.29",
  "SGMART": "458.45",
  "SHADOWFAX": "111.97",
  "SHAH": "4.82",
  "SHAHALLOYS": "61.95",
  "SHAILY": "1911.40",
  "SHAKTIPUMP": "526.25",
  "SHALBY": "148.67",
  "SHALPAINTS": "52.01",
  "SHANKARA": "106.26",
  "SHANTI": "6.37",
  "SHANTIGEAR": "478.30",
  "SHANTIGOLD": "203.67",
  "SHARDACROP": "1033.20",
  "SHARDAMOTR": "812.05",
  "SHAREINDIA": "132.92",
  "SHARIABEES": "457.11",
  "SHEKHAWATI": "12.70",
  "SHEMAROO": "104.32",
  "SHILCTECH": "3830.40",
  "SHILPAMED": "332.30",
  "SHIVALIK": "271.65",
  "SHIVAMAUTO": "16.59",
  "SHIVAMILLS": "54.50",
  "SHIVATEX": "147.44",
  "SHK": "129.16",
  "SHOPERSTOP": "309.05",
  "SHRADHA": "33.62",
  "SHREDIGCEM": "63.31",
  "SHREEJISPG": "364.25",
  "SHREEPUSHK": "320.25",
  "SHREERAMA": "48.13",
  "SHREYANIND": "148.89",
  "SHRINGARMS": "200.06",
  "SHRIPISTON": "2976.60",
  "SHRIRAMPPS": "71.95",
  "SHYAMCENT": "4.77",
  "SHYAMMETL": "779.80",
  "SHYAMTEL": "9.96",
  "SIGACHI": "19.25",
  "SIGIND": "46.04",
  "SIGMA": "42.47",
  "SIGMAADV": "152.62",
  "SIGNATURE": "814.70",
  "SIGNPOST": "228.95",
  "SIKKO": "4.73",
  "SIL": "14.10",
  "SILGO": "73.61",
  "SILINV": "411.30",
  "SILLYMONKS": "16.21",
  "SILVER": "264.08",
  "SILVER1": "25.84",
  "SILVER360": "263.08",
  "SILVERADD": "255.68",
  "SILVERAG": "258.46",
  "SILVERBETA": "255.63",
  "SILVERBND": "264.33",
  "SILVERCASE": "26.88",
  "SILVERIETF": "264.34",
  "SILVERTUC": "116.30",
  "SIMPLEXINF": "187.85",
  "SINCLAIR": "71.42",
  "SINDHUTRAD": "25.05",
  "SINTERCOM": "79.78",
  "SIRCA": "424.15",
  "SIS": "288.00",
  "SIYSIL": "497.50",
  "SJS": "1606.50",
  "SJVN": "72.35",
  "SKFINDIA": "1604.00",
  "SKFINDUS": "2170.50",
  "SKIPPER": "351.35",
  "SKMEGGPROD": "156.52",
  "SKYGOLD": "347.10",
  "SMALL250": "15.29",
  "SMALLADD": "15.29",
  "SMALLCAP": "40.30",
  "SMARTLINK": "116.12",
  "SMARTWORKS": "393.05",
  "SMCGLOBAL": "70.92",
  "SML100CASE": "9.23",
  "SMLMAH": "3826.30",
  "SMLT": "67.79",
  "SMSPHARMA": "405.20",
  "SNOWMAN": "35.65",
  "SNXT30BEES": "39.84",
  "SNXT50BETA": "86.63",
  "SOBHA": "1340.30",
  "SOFTTECH": "259.40",
  "SOLARA": "447.95",
  "SOLARWORLD": "163.95",
  "SOLEX": "983.65",
  "SOMANYCERA": "376.70",
  "SOMICONVEY": "102.99",
  "SONACOMS": "510.30",
  "SONAMLTD": "58.48",
  "SONATSOFTW": "242.45",
  "SOTL": "340.75",
  "SOUTHBANK": "38.99",
  "SOUTHWEST": "200.46",
  "SPAL": "700.95",
  "SPANDANA": "227.35",
  "SPARC": "122.39",
  "SPCENET": "3.90",
  "SPECIALITY": "100.05",
  "SPECTRUM": "1437.80",
  "SPENCERS": "31.12",
  "SPIC": "63.10",
  "SPLIL": "26.96",
  "SPLPETRO": "690.35",
  "SPMLINFRA": "175.04",
  "SPORTKING": "114.81",
  "SRD": "51.62",
  "SREEL": "194.08",
  "SRF": "2626.30",
  "SRGHFL": "257.45",
  "SRHHYPOLTD": "452.30",
  "SRM": "384.15",
  "SSDL": "59.14",
  "SSWL": "192.57",
  "STALLION": "114.92",
  "STANLEY": "158.71",
  "STAR": "910.50",
  "STARCEMENT": "202.97",
  "STARHEALTH": "462.30",
  "STARPAPER": "135.78",
  "STARTECK": "250.90",
  "STCINDIA": "109.54",
  "STEELCAS": "230.24",
  "STEELCITY": "82.02",
  "STEELXIND": "7.97",
  "STEL": "484.30",
  "STERTOOLS": "192.04",
  "STLNETWORK": "19.55",
  "STLTECH": "200.84",
  "STOVEKRAFT": "508.00",
  "STUDDS": "514.45",
  "STYL": "254.10",
  "STYLAMIND": "2215.10",
  "STYLEBAAZA": "268.55",
  "STYRENIX": "2073.80",
  "SUBEXLTD": "8.45",
  "SUBROS": "687.55",
  "SUDARCOLOR": "335.25",
  "SUDARSCHEM": "853.30",
  "SUDEEPPHRM": "608.10",
  "SUKHJITS": "173.96",
  "SULA": "161.72",
  "SUMEETINDS": "29.44",
  "SUMICHEM": "388.55",
  "SUMIT": "32.42",
  "SUMMITSEC": "1551.90",
  "SUNCLAY": "1267.80",
  "SUNDARAM": "1.28",
  "SUNDARMFIN": "5347.50",
  "SUNDRMBRAK": "571.75",
  "SUNDRMFAST": "830.20",
  "SUNDROP": "632.85",
  "SUNFLAG": "225.88",
  "SUNTECK": "334.30",
  "SUNTV": "593.30",
  "SUPERHOUSE": "145.72",
  "SUPERSPIN": "5.39",
  "SUPRAJIT": "410.85",
  "SUPREME": "51.35",
  "SUPREMEIND": "4043.70",
  "SUPRIYA": "585.80",
  "SURAJEST": "202.61",
  "SURAJLTD": "229.99",
  "SURAKSHA": "257.25",
  "SURANASOL": "21.43",
  "SURANAT&P": "17.15",
  "SURYALAXMI": "54.65",
  "SURYAROSNI": "222.15",
  "SURYODAY": "126.32",
  "SUTLEJTEX": "32.01",
  "SUVEN": "136.72",
  "SUVIDHAA": "2.75",
  "SUYOG": "691.90",
  "SUZLON": "42.43",
  "SVLL": "538.00",
  "SWANCORP": "361.75",
  "SWARAJENG": "3481.20",
  "SWELECTES": "520.35",
  "SWIGGY": "280.90",
  "SWSOLAR": "179.31",
  "SYMPHONY": "815.50",
  "SYNCOMF": "12.40",
  "SYNGENE": "404.10",
  "SYRMA": "750.20",
  "SYSTMTXC": "67.63",
  "TAINWALCHM": "197.55",
  "TAJGVK": "304.75",
  "TALBROAUTO": "251.70",
  "TANLA": "431.80",
  "TARACHAND": "60.20",
  "TARAPUR": "24.18",
  "TARC": "131.36",
  "TARIL": "292.40",
  "TARSONS": "194.25",
  "TASTYBITE": "7044.00",
  "TATACAP": "318.60",
  "TATACHEM": "683.15",
  "TATACOMM": "1449.30",
  "TATAELXSI": "4330.00",
  "TATAGOLD": "15.52",
  "TATAINVEST": "629.20",
  "TATATECH": "551.85",
  "TATSILV": "25.72",
  "TATVA": "1158.60",
  "TBOTEK": "1212.40",
  "TBZ": "135.59",
  "TCC": "413.25",
  "TCI": "991.40",
  "TCIEXP": "494.50",
  "TCPLPACK": "2519.40",
  "TDPOWERSYS": "812.60",
  "TEAMGTY": "251.75",
  "TEAMLEASE": "1122.00",
  "TECH": "32.03",
  "TECHNOE": "1106.70",
  "TECILCHEM": "12.90",
  "TEGA": "1803.80",
  "TEJASNET": "441.10",
  "TEMBO": "512.55",
  "TENNIND": "535.45",
  "TERASOFT": "343.20",
  "TEXINFRA": "87.15",
  "TEXMOPIPES": "45.49",
  "TEXRAIL": "95.78",
  "TFCILTD": "64.06",
  "TFL": "12.62",
  "TGBHOTELS": "8.91",
  "THANGAMAYL": "3562.80",
  "THEINVEST": "98.63",
  "THEJO": "1651.30",
  "THELEELA": "435.45",
  "THEMISMED": "82.42",
  "THERMAX": "3165.30",
  "THOMASCOOK": "91.59",
  "THOMASCOTT": "257.90",
  "THYROCARE": "367.05",
  "TI": "452.80",
  "TICL": "26.27",
  "TIGERLOGS": "27.74",
  "TIIL": "2045.60",
  "TIINDIA": "2549.70",
  "TIL": "209.43",
  "TIMETECHNO": "168.25",
  "TIMKEN": "3486.50",
  "TINNARUBR": "669.70",
  "TIPSFILMS": "338.40",
  "TIPSMUSIC": "504.30",
  "TIRUMALCHM": "176.83",
  "TIRUPATIFL": "44.07",
  "TITAGARH": "655.85",
  "TMB": "627.35",
  "TMCV": "443.55",
  "TNIDETF": "77.97",
  "TNPETRO": "83.55",
  "TNPL": "137.11",
  "TNTELE": "8.70",
  "TOKYOPLAST": "74.98",
  "TOLINS": "103.47",
  "TOP100CASE": "10.17",
  "TOP10ADD": "87.72",
  "TOP15IETF": "9.69",
  "TOP20": "8.58",
  "TORNTPOWER": "1506.00",
  "TOTAL": "59.70",
  "TOUCHWOOD": "70.90",
  "TPHQ": "0.53",
  "TPLPLASTEH": "62.15",
  "TRACXN": "32.16",
  "TRANSRAILL": "514.40",
  "TRANSWORLD": "134.27",
  "TRAVELFOOD": "1192.50",
  "TREJHARA": "160.09",
  "TREL": "23.68",
  "TRF": "233.20",
  "TRIDENT": "23.30",
  "TRIGYN": "48.65",
  "TRITURBINE": "470.30",
  "TRIVENI": "359.95",
  "TRU": "6.69",
  "TRUALT": "402.60",
  "TSFINV": "377.55",
  "TTKHLTCARE": "847.40",
  "TTKPRESTIG": "578.30",
  "TTML": "39.33",
  "TVSELECT": "376.70",
  "TVSHLTD": "14048.00",
  "TVSSRICHAK": "3549.80",
  "TVTODAY": "112.79",
  "TWCGOLDETF": "158.71",
  "UBL": "1645.50",
  "UCAL": "102.37",
  "UCOBANK": "26.56",
  "UDS": "149.73",
  "UEL": "157.80",
  "UFBL": "207.44",
  "UFLEX": "450.60",
  "UFO": "65.01",
  "UGARSUGAR": "37.46",
  "UGROCAP": "96.39",
  "UJJIVANSFB": "53.19",
  "UMAEXPORTS": "25.55",
  "UMESLTD": "5.98",
  "UMIYA-MRO": "79.90",
  "UNICHEMLAB": "335.80",
  "UNIDT": "180.02",
  "UNIECOM": "99.34",
  "UNIENTER": "99.99",
  "UNIINFO": "12.05",
  "UNIMECH": "852.45",
  "UNIONBANK": "182.10",
  "UNIONGOLD": "156.80",
  "UNIPARTS": "444.15",
  "UNITECH": "4.49",
  "UNITEDPOLY": "27.00",
  "UNITEDTEA": "505.80",
  "UNIVASTU": "65.23",
  "UNIVCABLES": "634.40",
  "UNOMINDA": "1068.50",
  "UPL": "629.05",
  "URAVIDEF": "130.07",
  "URBANCO": "114.40",
  "URJA": "9.14",
  "USHAMART": "421.15",
  "UTIAMC": "980.05",
  "UTKARSHBNK": "12.53",
  "UTLSOLAR": "189.80",
  "UTTAMSUGAR": "197.02",
  "UYFINCORP": "13.59",
  "V2RETAIL": "1989.10",
  "VADILALIND": "4913.70",
  "VAIBHAVGBL": "214.65",
  "VAISHALI": "6.33",
  "VAKRANGEE": "6.02",
  "VAL30IETF": "15.54",
  "VALIANTLAB": "54.08",
  "VALIANTORG": "210.98",
  "VARDHACRLC": "33.87",
  "VARROC": "495.35",
  "VASCONEQ": "34.66",
  "VASWANI": "55.33",
  "VCL": "1.60",
  "VEEDOL": "1358.70",
  "VENKEYS": "1256.80",
  "VENTIVE": "665.70",
  "VENUSPIPES": "1015.60",
  "VENUSREM": "927.50",
  "VERANDA": "151.27",
  "VERTOZ": "39.26",
  "VESUVIUS": "496.80",
  "VETO": "100.31",
  "VGL": "60.28",
  "VGUARD": "318.70",
  "VHL": "3112.30",
  "VIDHIING": "299.75",
  "VIDYAWIRES": "55.90",
  "VIJAYA": "955.50",
  "VIJIFIN": "2.63",
  "VIKASECO": "1.30",
  "VIKASLIFE": "1.30",
  "VIKRAMSOLR": "184.78",
  "VIKRAN": "62.25",
  "VIMTALABS": "439.45",
  "VINATIORGA": "1385.60",
  "VINCOFE": "125.75",
  "VINDHYATEL": "1185.40",
  "VINEETLAB": "30.04",
  "VINNY": "1.20",
  "VINYLINDIA": "199.46",
  "VIPCLOTHNG": "18.89",
  "VIPIND": "347.55",
  "VIRINCHI": "19.00",
  "VISAKAIND": "58.70",
  "VISASTEEL": "34.75",
  "VISHNU": "503.75",
  "VISHWARAJ": "5.56",
  "VITAL": "39.90",
  "VIVIDHA": "0.60",
  "VIVIMEDLAB": "6.96",
  "VIYASH": "196.06",
  "VLEGOV": "13.21",
  "VLSFINANCE": "231.50",
  "VMART": "526.85",
  "VMM": "106.07",
  "VMSTMT": "41.41",
  "VOLTAMP": "8736.00",
  "VOLTAS": "1449.40",
  "VPRPL": "40.29",
  "VRAJ": "113.09",
  "VRLLOG": "258.45",
  "VSSL": "243.15",
  "VSTIND": "221.74",
  "VSTL": "113.88",
  "VSTTILLERS": "5274.00",
  "VTL": "541.35",
  "WAAREEENER": "2739.40",
  "WAAREERTL": "840.00",
  "WABAG": "1279.50",
  "WAKEFIT": "168.64",
  "WALCHANNAG": "160.59",
  "WCIL": "94.49",
  "WEALTH": "958.95",
  "WEBELSOLAR": "55.96",
  "WEIZMANIND": "80.02",
  "WEL": "138.79",
  "WELCORP": "844.25",
  "WELENT": "471.05",
  "WELINV": "1325.60",
  "WELSPUNLIV": "115.86",
  "WENDT": "6650.50",
  "WESTLIFE": "461.05",
  "WEWIN": "41.38",
  "WEWORK": "468.00",
  "WHEELS": "930.70",
  "WHIRLPOOL": "860.85",
  "WILLAMAGOR": "26.34",
  "WINDLAS": "737.00",
  "WINDMACHIN": "237.00",
  "WIPL": "152.58",
  "WOCKPHARMA": "1298.60",
  "WONDERLA": "523.90",
  "WORTHPERI": "132.87",
  "WSI": "66.90",
  "WSTCSTPAPR": "397.60",
  "XCHANGING": "59.30",
  "XELPMOC": "107.58",
  "XPROINDIA": "858.45",
  "XTGLOBAL": "34.02",
  "YASHO": "1373.40",
  "YATHARTH": "677.80",
  "YATRA": "104.71",
  "YESBANK": "19.31",
  "YUKEN": "714.50",
  "ZAGGLE": "224.61",
  "ZEEL": "82.02",
  "ZEELEARN": "5.47",
  "ZENITHEXPO": "193.20",
  "ZENITHSTL": "5.51",
  "ZENSARTECH": "564.40",
  "ZENTEC": "1418.60",
  "ZFCVINDIA": "13971.00",
  "ZIMLAB": "64.67",
  "ZODIAC": "242.41",
  "ZODIACLOTH": "72.18",
  "ZOTA": "1170.50",
  "ZUARI": "209.81",
  "ZUARIIND": "247.50",
  "ZYDUSWELL": "388.90",
  "ABB": "6412.50",
  "BEL": "453.75",
  "DISAQ": "11869.85",
  "CIPLA": "1325.25",
  "CGPOWER": "737.45",
  "TITAN": "4126.95",
  "ELANTAS": "8125.10",
  "DRREDDY": "1318.75",
  "COCKERILL": "4825.70",
  "GOODYEAR": "763.10",
  "HINDZINC": "582.95",
  "JSWSTEEL": "1172.70",
  "KIRLFER": "380.65",
  "TRENT": "3532.15",
  "SPICEJET": "14.72",
  "VEDL": "719.55",
  "GRASIM": "2676.55",
  "NIRLON": "489.20",
  "ONGC": "270.45",
  "PIDILITIND": "1386.05",
  "PUNJCOMMU": "52.99",
  "WELSPLSOL": "35.82",
  "SHREECEM": "23504.40",
  "TIMEX": "283.25",
  "TORNTPHARM": "4444.75",
  "AMBUJACEM": "446.70",
  "HINDALCO": "969.85",
  "HOCL": "29.02",
  "TATASTEEL": "193.45",
  "BAJAJHLDNG": "9796.40",
  "HINDMOTORS": "14.68",
  "BOSCHLTD": "31280.70",
  "BPCL": "326.25",
  "SIEMENS": "3324.25",
  "TMPV": "324.45",
  "NOVARTIND": "957.95",
  "HINDUNILVR": "2135.45",
  "NESTLEIND": "1219.85",
  "TATACONSUM": "1057.45",
  "ASIANPAINT": "2221.50",
  "BRITANNIA": "5785.60",
  "INDHOTEL": "624.80",
  "ITC": "303.90",
  "INDPRUD": "5200.00",
  "ELCIDIN": "98500.00",
  "ELPROINTL": "85.62",
  "NATIONSTD": "1350.05",
  "ACGL": "1639.15",
  "ZFSTEERING": "681.75",
  "GRAUWEIL": "62.16",
  "HERCULES": "116.75",
  "WPIL": "390.00",
  "KENNAMET": "2222.10",
  "CITURGIA": "137.85",
  "AGVENTURES": "105.00",
  "ULTRAMAR": "429.70",
  "TANFACIND": "1830.60",
  "WIPRO": "202.40",
  "TGVSL": "82.09",
  "BAJAJST": "393.05",
  "HAWKINCOOK": "7472.85",
  "ISTLTD": "659.45",
  "APOLLOHOSP": "7574.30",
  "BENARAS": "9511.60",
  "KOTIC": "177.45",
  "SHRIRAMFIN": "1031.40",
  "CHOLAFIN": "1523.85",
  "ZSARACOM": "9852.00",
  "DECNGOLD": "99.95",
  "MMWL": "9.97",
  "GUJTLRM": "0.55",
  "BPAGRI": "41.06",
  "JYOTIRES": "824.70",
  "WINSOMTX": "72.09",
  "SEKURITIND": "94.03",
  "RIR": "159.85",
  "MOTHERSON": "120.15",
  "HAVELLS": "1353.50",
  "MARSONS": "136.05",
  "BGDL": "91.88",
  "KLBRENG-B": "490.95",
  "FRONTSP": "4594.85",
  "GVTD": "3749.40",
  "CROPSTER": "7.22",
  "KOVAI": "5202.25",
  "INDBNK": "43.65",
  "LOTUSCHO": "748.65",
  "SIKA": "979.85",
  "GRANDOAK": "31.00",
  "KMCSHIL": "83.98",
  "BIBCL": "16.70",
  "SUNPHARMA": "1825.00",
  "BNAGROCHEM": "229.20",
  "ANDREWYU": "19.14",
  "ASMTEC": "2224.55",
  "DRAGARWQ": "4900.70",
  "ECORECO": "324.90",
  "IOC": "160.15",
  "MERCURYEV": "31.98",
  "ARIHANT": "1042.10",
  "PRAVEG": "228.90",
  "ASTAR": "589.00",
  "ORIRAIL": "116.15",
  "3BBLACKBIO": "1215.15",
  "BANKBARODA": "289.15",
  "GAIL": "152.40",
  "GUJSTATFIN": "10.87",
  "HCLTECH": "1358.45",
  "JINDALSTEL": "1225.15",
  "ZYDUSLIFE": "916.55",
  "GODREJCP": "1050.55",
  "UNITDSPR": "1363.95",
  "PNB": "116.60",
  "HAZOOR": "28.80",
  "KAMAHOLD": "2575.25",
  "CANBK": "140.30",
  "BLIL": "72.67",
  "DIVISLAB": "6276.45",
  "TCS": "2442.85",
  "SOLARINDS": "14524.30",
  "TECHM": "1350.15",
  "NAUKRI": "955.50",
  "PFC": "416.00",
  "DLF": "558.90",
  "ADANIPORTS": "1391.30",
  "RECLTD": "343.45",
  "BAJAJ-AUTO": "9165.15",
  "BAJAJFINSV": "1770.90",
  "SENSEX1": "83.68",
  "BENGALASM": "5850.15",
  "SBISENSEX": "842.43",
  "GCMSECU": "0.64",
  "MMLF": "0.72",
  "ALSL": "56.70",
  "BRPL": "111.75",
  "VISHAL": "18.82",
  "MIIL": "535.05",
  "SENSEXBEES": "870.24",
  "CAPPIPES": "9.42",
  "SETFBSE100": "274.11",
  "URSUGAR": "2.37",
  "GROWINGTON": "0.97",
  "ADANIENSOL": "1003.40",
  "UNIAUTO": "55.00",
  "VISHALBL": "52.90",
  "NAKSH": "4.60",
  "INDIGO": "4253.45",
  "PANORAMA": "42.83",
  "ELITECON": "54.53",
  "BLUECLOUDS": "19.56",
  "KAMATS": "48.00",
  "RELICAB": "32.51",
  "KPL": "1660.25",
  "LTM": "4322.45",
  "SPRAYKING": "1.47",
  "IDFSENSEXE": "826.18",
  "VBL": "410.70",
  "VSL": "9.87",
  "DMART": "3950.45",
  "IFL": "0.38",
  "CHEMCRUX": "86.02",
  "PRIMEFRESH": "238.05",
  "ESCORP": "109.80",
  "MEERA": "32.79",
  "ANG": "23.30",
  "ICICIGI": "1856.55",
  "PQIF": "16.95",
  "SBILIFE": "1941.10",
  "TTFL": "49.82",
  "POOJA": "24.35",
  "STL": "7.23",
  "HDFCLIFE": "645.65",
  "SHARIKA": "10.54",
  "RATNABHUMI": "203.60",
  "MRCAGRO": "38.73",
  "GGL": "3.06",
  "KENVI": "2.32",
  "ACTIVE": "105.90",
  "HAL": "4011.50",
  "TRL": "96.25",
  "UHZAVERI": "13.03",
  "PALMJEWELS": "16.18",
  "ADANIGREEN": "865.95",
  "RAJNISH": "0.52",
  "RAWEDGE": "14.66",
  "DEEP": "31.53",
  "ASRL": "7.09",
  "SETFSN50": "866.79",
  "A1L": "20.17",
  "DOLFIN": "173.15",
  "SHUBHAM": "55.47",
  "SMGOLD": "11.94",
  "BCPL": "61.64",
  "DECCAN": "12.60",
  "KRANTI": "57.08",
  "AGOL": "4.25",
  "NSL": "115.15",
  "VRFILMS": "12.70",
  "GKP": "5.99",
  "BMW": "33.22",
  "ARL": "75.00",
  "SNXT50BEES": "84.71",
  "ALPHALOGIC": "35.01",
  "GALACTICO": "1.81",
  "ANUROOP": "11.75",
  "08MPD": "5.98",
  "08GPG": "2.61",
  "08AGG": "34.07",
  "ROJL": "1.42",
  "11DPR": "13.58",
  "11GPG": "2.29",
  "11MPD": "3.90",
  "11MPR": "53.16",
  "11QPD": "6.99",
  "11QPR": "31.70",
  "11AGG": "31.61",
  "11AMD": "39.25",
  "11AQD": "35.49",
  "11DPD": "5.21",
  "MAXHEALTH": "1020.30",
  "MAZDOCK": "2447.90",
  "IRFC": "99.90",
  "EKI": "82.69",
  "LODHA": "869.25",
  "SAMOR": "70.87",
  "ACHYUT": "5.42",
  "LICI": "796.50",
  "ASHIKA": "356.95",
  "BAJAJHFL": "83.72",
  "HYUNDAI": "1991.95",
  "ENRIN": "2866.25",
  "NSDL": "870.15",
  "SOLARAPP1": "291.50",
  "SSFLPP": "112.80",
  "ATLPP": "9.75"
}