{
  "Bhavdate": "11-Mar-2026",
  "HDFCBANK": "849.45",
  "RELIANCE": "1408.80",
  "HAPPSTMNDS": "411.70",
  "FACT": "884.90",
  "JINDALSAW": "198.04",
  "BHARTIARTL": "1850.40",
  "ICICIBANK": "1311.90",
  "M&M": "3168.20",
  "APOLLOPIPE": "424.35",
  "DIXON": "10618.00",
  "INDIGO": "4380.40",
  "VEDL": "722.00",
  "TEJASNET": "470.40",
  "KOTAKBANK": "391.85",
  "SHRIRAMFIN": "1062.90",
  "SILVERBEES": "251.69",
  "ATGL": "566.90",
  "BAJFINANCE": "893.65",
  "INFY": "1295.60",
  "SHAKTIPUMP": "528.20",
  "SBIN": "1112.20",
  "AXISBANK": "1255.80",
  "POLYCAB": "7429.50",
  "BSE": "2837.40",
  "LT": "3876.00",
  "JIOFIN": "238.70",
  "DRREDDY": "1325.50",
  "SUNPHARMA": "1825.90",
  "COALINDIA": "446.75",
  "NTPC": "379.90",
  "BAJAJFINSV": "1795.30",
  "EICHERMOT": "7253.50",
  "20MICRONS": "166.61",
  "21STCENMGM": "33.94",
  "360ONE": "1048.10",
  "3IINFOLTD": "13.24",
  "3MINDIA": "33720.00",
  "3PLAND": "31.36",
  "5PAISA": "304.00",
  "63MOONS": "595.75",
  "AAATECH": "94.76",
  "AADHARHFC": "482.35",
  "AAREYDRUGS": "67.65",
  "AARNAV": "26.29",
  "AARON": "145.90",
  "AARTECH": "40.34",
  "AARTIDRUGS": "352.75",
  "AARTIIND": "430.15",
  "AARTIPHARM": "681.05",
  "AARTISURF": "367.15",
  "AARVI": "129.82",
  "AAVAS": "1211.80",
  "ABBOTINDIA": "27200.00",
  "ABCAPITAL": "323.80",
  "ABCOTS": "401.95",
  "ABDL": "473.45",
  "ABFRL": "61.74",
  "ABGSEC": "112.26",
  "ABINFRA": "17.61",
  "ABLBL": "102.75",
  "ABREL": "1183.00",
  "ABSL10BANK": "167.59",
  "ABSLAMC": "1010.00",
  "ABSLBANETF": "57.00",
  "ABSLLIQUID": "999.99",
  "ABSLMSCIN": "28.54",
  "ABSLNN50ET": "70.17",
  "ABSLPSE": "10.48",
  "ACC": "1456.40",
  "ACCELYA": "1226.70",
  "ACCURACY": "4.00",
  "ACE": "853.40",
  "ACEINTEG": "16.63",
  "ACI": "537.20",
  "ACL": "52.57",
  "ACMESOLAR": "230.24",
  "ACUTAAS": "2193.00",
  "ADFFOODS": "187.44",
  "ADL": "72.99",
  "ADOR": "999.80",
  "ADROITINFO": "9.67",
  "ADSL": "105.09",
  "ADVAIT": "1614.00",
  "ADVANCE": "105.02",
  "ADVANIHOTR": "52.31",
  "ADVENTHTL": "178.16",
  "ADVENZYMES": "294.90",
  "AEGISLOG": "616.55",
  "AEGISVOPAK": "193.27",
  "AEQUS": "126.08",
  "AEROENTER": "72.68",
  "AEROFLEX": "234.17",
  "AERONEU": "67.09",
  "AETHER": "1015.50",
  "AFCONS": "280.30",
  "AFFLE": "1411.40",
  "AFFORDABLE": "168.49",
  "AFSL": "204.72",
  "AGARIND": "441.50",
  "AGARWALEYE": "444.80",
  "AGI": "533.05",
  "AGIIL": "311.05",
  "AGROPHOS": "33.99",
  "AHCL": "126.99",
  "AHLADA": "42.13",
  "AHLEAST": "160.31",
  "AHLUCONT": "771.80",
  "AIAENG": "3743.10",
  "AIIL": "453.15",
  "AIRAN": "15.92",
  "AIROLAM": "86.18",
  "AJANTPHARM": "3048.20",
  "AJAXENGG": "480.45",
  "AJMERA": "125.49",
  "AJOONI": "4.45",
  "AKASH": "24.56",
  "AKG": "10.96",
  "AKI": "5.05",
  "AKSHAR": "0.40",
  "AKSHARCHEM": "171.07",
  "AKSHOPTFBR": "4.37",
  "AKUMS": "507.25",
  "AKZOINDIA": "2880.80",
  "ALANKIT": "7.85",
  "ALBERTDAVD": "690.80",
  "ALEMBICLTD": "84.79",
  "ALGOQUANT": "56.36",
  "ALICON": "699.45",
  "ALIVUS": "949.75",
  "ALKALI": "59.42",
  "ALKEM": "5544.50",
  "ALKYLAMINE": "1321.40",
  "ALLCARGO": "7.85",
  "ALLDIGI": "797.65",
  "ALLTIME": "213.42",
  "ALMONDZ": "14.22",
  "ALOKINDS": "13.26",
  "ALPA": "61.70",
  "ALPHA": "46.23",
  "ALPHAETF": "24.02",
  "ALPHAGEO": "199.31",
  "ALPL30IETF": "26.59",
  "AMAGI": "384.20",
  "AMANTA": "99.65",
  "AMBER": "7308.00",
  "AMBICAAGAR": "23.84",
  "AMBIKCO": "1370.90",
  "AMDIND": "38.60",
  "AMJLAND": "39.01",
  "AMNPLST": "149.96",
  "AMRUTANJAN": "557.10",
  "ANANDRATHI": "3125.20",
  "ANANTRAJ": "472.55",
  "ANDHRAPAP": "63.22",
  "ANDHRSUGAR": "73.79",
  "ANGELONE": "218.53",
  "ANIKINDS": "40.73",
  "ANMOL": "11.13",
  "ANTELOPUS": "569.20",
  "ANTGRAPHIC": "0.80",
  "ANTHEM": "648.75",
  "ANUHPHR": "78.25",
  "ANUP": "1527.30",
  "ANURAS": "1299.00",
  "AONEGOLD": "14.95",
  "AONELIQUID": "1050.21",
  "AONENIFTY": "9.79",
  "AONESILVER": "10.08",
  "AONETMMQ50": "9.38",
  "AONETOTAL": "11.13",
  "APARINDS": "9260.00",
  "APCL": "116.94",
  "APCOTEXIND": "365.80",
  "APEX": "339.95",
  "APLAPOLLO": "2016.30",
  "APLLTD": "706.10",
  "APOLLO": "212.66",
  "APOLLOTYRE": "434.25",
  "APOLSINHOT": "1158.70",
  "APTECHT": "81.51",
  "APTUS": "229.57",
  "AQYLON": "93.30",
  "ARCHIDPLY": "76.36",
  "ARCHIES": "13.94",
  "ARE&M": "790.95",
  "ARENTERP": "39.90",
  "ARFIN": "80.28",
  "ARIES": "345.75",
  "ARIHANTCAP": "72.43",
  "ARIHANTSUP": "231.40",
  "ARIS": "107.86",
  "ARKADE": "105.75",
  "ARMANFIN": "1359.80",
  "AROGRANITE": "24.45",
  "ARROWGREEN": "369.55",
  "ARSSBL": "484.65",
  "ARTEMISMED": "231.68",
  "ARTNIRMAN": "36.95",
  "ARVIND": "333.45",
  "ARVINDFASN": "400.30",
  "ARVSMART": "518.60",
  "ASAHIINDIA": "864.55",
  "ASAHISONG": "196.05",
  "ASAL": "429.00",
  "ASALCBR": "747.65",
  "ASHAPURMIN": "529.50",
  "ASHIANA": "310.45",
  "ASHIMASYN": "13.62",
  "ASHOKA": "120.79",
  "ASHOKAMET": "14.18",
  "ASHOKLEY": "184.66",
  "ASIANENE": "280.65",
  "ASIANHOTNR": "293.40",
  "ASIANTILES": "66.16",
  "ASKAUTOLTD": "404.65",
  "ASMS": "8.82",
  "ASPINWALL": "214.20",
  "ASTEC": "625.75",
  "ASTERDM": "685.90",
  "ASTRAL": "1746.30",
  "ASTRAMICRO": "1029.25",
  "ASTRAZEN": "8760.00",
  "ASTRON": "4.18",
  "ATALREAL": "23.42",
  "ATAM": "62.82",
  "ATHERENERG": "702.00",
  "ATL": "23.25",
  "ATLANTAA": "37.33",
  "ATLANTAELE": "986.70",
  "ATLASCYCLE": "85.81",
  "ATUL": "6203.00",
  "ATULAUTO": "431.25",
  "AUBANK": "918.40",
  "AURIONPRO": "887.50",
  "AUROPHARMA": "1304.80",
  "AURUM": "165.07",
  "AUTOAXLES": "1897.40",
  "AUTOBEES": "266.79",
  "AUTOIETF": "26.62",
  "AUTOIND": "67.42",
  "AVADHSUGAR": "438.60",
  "AVALON": "942.90",
  "AVANTEL": "142.78",
  "AVANTIFEED": "1210.00",
  "AVG": "132.69",
  "AVL": "453.35",
  "AVONMORE": "13.72",
  "AVROIND": "139.52",
  "AVTNPL": "60.17",
  "AWFIS": "278.80",
  "AWHCL": "476.45",
  "AWL": "179.40",
  "AXISBNKETF": "571.68",
  "AXISBPSETF": "13.24",
  "AXISCADES": "1457.70",
  "AXISCETF": "111.88",
  "AXISGOLD": "133.79",
  "AXISHCETF": "151.99",
  "AXISILVER": "261.65",
  "AXISNIFTY": "262.87",
  "AXISTECETF": "324.75",
  "AXISVALUE": "32.65",
  "AXSENSEX": "79.44",
  "AYE": "108.86",
  "AYMSYNTEX": "187.70",
  "AZAD": "1611.60",
  "BAFNAPH": "105.11",
  "BAGFILMS": "5.00",
  "BAIDFIN": "10.97",
  "BAJAJCON": "357.45",
  "BAJAJELEC": "380.15",
  "BAJAJHCARE": "309.30",
  "BAJAJHIND": "16.57",
  "BAJAJINDEF": "238.66",
  "BAJEL": "149.28",
  "BALAJEE": "27.65",
  "BALAJITELE": "98.53",
  "BALAMINES": "1047.90",
  "BALAXI": "20.18",
  "BALKRISHNA": "12.94",
  "BALKRISIND": "2175.60",
  "BALMLAWRIE": "171.17",
  "BALPHARMA": "70.64",
  "BALRAMCHIN": "519.05",
  "BALUFORGE": "461.75",
  "BANARBEADS": "114.67",
  "BANARISUG": "3607.70",
  "BANCOINDIA": "576.00",
  "BANDHANBNK": "182.47",
  "BANG": "37.10",
  "BANKA": "51.77",
  "BANKADD": "56.91",
  "BANKBEES": "576.13",
  "BANKBETA": "57.54",
  "BANKBETF": "56.52",
  "BANKETF": "566.15",
  "BANKIETF": "57.09",
  "BANKINDIA": "154.30",
  "BANKNIFTY1": "57.70",
  "BANKPSU": "88.91",
  "BANSALWIRE": "247.45",
  "BANSWRAS": "114.48",
  "BASF": "3453.40",
  "BASML": "20.70",
  "BATAINDIA": "718.70",
  "BAYERCROP": "4520.60",
  "BBETF0432": "1311.00",
  "BBL": "2375.20",
  "BBNPNBETF": "56.19",
  "BBNPPGOLD": "155.55",
  "BBOX": "514.10",
  "BBTC": "1570.40",
  "BBTCL": "167.97",
  "BCLIND": "28.54",
  "BCONCEPTS": "249.05",
  "BDL": "1360.00",
  "BEARDSELL": "23.47",
  "BECTORFOOD": "187.70",
  "BELLACASA": "252.70",
  "BELRISE": "192.35",
  "BEML": "1610.10",
  "BEPL": "81.30",
  "BERGEPAINT": "430.65",
  "BETA": "1130.80",
  "BFINVEST": "378.60",
  "BFSI": "26.83",
  "BHAGCHEM": "203.35",
  "BHAGERIA": "151.92",
  "BHAGYANGR": "161.11",
  "BHANDARI": "2.58",
  "BHARATCOAL": "33.35",
  "BHARATFORG": "1797.10",
  "BHARATGEAR": "100.86",
  "BHARATRAS": "1361.20",
  "BHARATSE": "172.31",
  "BHARATWIRE": "164.03",
  "BHARTIHEXA": "1536.20",
  "BHEL": "255.75",
  "BIGBLOC": "51.22",
  "BIKAJI": "619.90",
  "BIL": "707.40",
  "BIOCON": "395.35",
  "BIOFILCHEM": "30.56",
  "BIRLACABLE": "136.06",
  "BIRLACORPN": "843.60",
  "BIRLAMONEY": "121.20",
  "BIRLANU": "1388.00",
  "BLACKBUCK": "574.80",
  "BLAL": "176.75",
  "BLISSGVS": "216.26",
  "BLKASHYAP": "52.08",
  "BLS": "249.15",
  "BLSE": "141.64",
  "BLUECOAST": "20.72",
  "BLUEDART": "5398.50",
  "BLUEJET": "374.70",
  "BLUESTARCO": "1941.10",
  "BLUESTONE": "513.65",
  "BLUSPRING": "47.82",
  "BMWVENTLTD": "56.77",
  "BODALCHEM": "44.56",
  "BOMDYEING": "108.90",
  "BOROLTD": "259.50",
  "BORORENEW": "415.80",
  "BOROSCI": "106.28",
  "BOSCH-HCIL": "1316.90",
  "BPL": "51.55",
  "BRIGADE": "672.00",
  "BRIGHOTEL": "58.62",
  "BRNL": "18.49",
  "BROOKS": "60.91",
  "BSE500IETF": "37.24",
  "BSHSL": "83.36",
  "BSL": "126.60",
  "BSLGOLDETF": "140.81",
  "BSLNIFTY": "27.84",
  "BSLSENETFG": "77.13",
  "BSOFT": "381.90",
  "BTML": "7.06",
  "BUILDPRO": "954.30",
  "BUTTERFLY": "694.50",
  "BVCL": "39.72",
  "BYKE": "39.92",
  "CALSOFT": "12.51",
  "CAMLINFINE": "142.63",
  "CAMPUS": "238.25",
  "CAMS": "676.20",
  "CANFINHOME": "865.95",
  "CANHLIFE": "148.63",
  "CANTABIL": "257.35",
  "CAPACITE": "214.56",
  "CAPILLARY": "514.90",
  "CAPITALSFB": "249.25",
  "CAPLIPOINT": "1690.10",
  "CARBORUNIV": "787.10",
  "CARERATING": "1607.90",
  "CARRARO": "481.75",
  "CARTRADE": "1689.20",
  "CARYSIL": "846.65",
  "CASHIETF": "1052.89",
  "CASTROLIND": "185.79",
  "CCAVENUE": "14.89",
  "CCCL": "15.87",
  "CCHHL": "12.70",
  "CCL": "1042.60",
  "CDSL": "1219.40",
  "CEATLTD": "3553.30",
  "CEIGALL": "277.30",
  "CEINSYS": "972.60",
  "CELEBRITY": "8.11",
  "CELLO": "396.85",
  "CEMPRO": "555.30",
  "CENTENKA": "409.80",
  "CENTEXT": "19.85",
  "CENTRALBK": "36.61",
  "CENTRUM": "20.77",
  "CENTUM": "2856.90",
  "CENTURYPLY": "690.25",
  "CERA": "4652.10",
  "CESC": "154.29",
  "CEWATER": "248.80",
  "CGCL": "169.24",
  "CHALET": "774.95",
  "CHAMBLFERT": "431.75",
  "CHEMBOND": "142.17",
  "CHEMBONDCH": "140.36",
  "CHEMCON": "156.76",
  "CHEMFAB": "389.55",
  "CHEMICAL": "27.04",
  "CHEMPLASTS": "267.52",
  "CHENNPETRO": "906.70",
  "CHEVIOT": "990.10",
  "CHOICEGOLD": "159.03",
  "CHOICEIN": "649.90",
  "CHOLAHLDNG": "1569.90",
  "CIEINDIA": "471.05",
  "CIFL": "28.14",
  "CIGNITITEC": "1095.60",
  "CINELINE": "85.59",
  "CINEVISTA": "15.57",
  "CLEAN": "742.60",
  "CLEANMAX": "862.70",
  "CLEDUCATE": "50.90",
  "CLSEL": "248.85",
  "CMSINFO": "299.05",
  "CNL": "655.95",
  "COASTCORP": "44.71",
  "COCHINSHIP": "1460.70",
  "COFFEEDAY": "25.87",
  "COFORGE": "1108.80",
  "COHANCE": "291.70",
  "COLPAL": "2055.60",
  "COMMOIETF": "97.22",
  "COMPUSOFT": "12.30",
  "COMSYN": "153.78",
  "CONCOR": "470.45",
  "CONCORDBIO": "1158.40",
  "CONFIPET": "29.58",
  "CONS": "11.21",
  "CONSUMBEES": "121.56",
  "CONSUMER": "10.45",
  "CONSUMIETF": "113.03",
  "CONTROLPR": "630.50",
  "CORALFINAC": "32.07",
  "CORDSCABLE": "157.67",
  "COROMANDEL": "2020.70",
  "CORONA": "1616.50",
  "COSMOFIRST": "664.70",
  "COUNCODOS": "4.98",
  "CPCAP": "87.55",
  "CPEDU": "185.01",
  "CPPLUS": "1582.90",
  "CPSEETF": "102.87",
  "CRAFTSMAN": "7325.50",
  "CRAMC": "239.85",
  "CREATIVEYE": "7.50",
  "CREDITACC": "1195.30",
  "CREST": "344.05",
  "CRISIL": "4311.30",
  "CRIZAC": "211.71",
  "CROMPTON": "247.50",
  "CROWN": "120.96",
  "CSBBANK": "358.40",
  "CSLFINANCE": "255.15",
  "CTE": "27.03",
  "CUB": "247.05",
  "CUBEXTUB": "93.63",
  "CUMMINSIND": "4630.70",
  "CUPID": "86.90",
  "CYBERMEDIA": "13.94",
  "CYBERTECH": "106.70",
  "CYIENT": "924.60",
  "CYIENTDLM": "312.45",
  "DABUR": "471.85",
  "DALBHARAT": "1855.90",
  "DALMIASUG": "318.60",
  "DAMCAPITAL": "132.86",
  "DAMODARIND": "23.36",
  "DANGEE": "2.85",
  "DATAMATICS": "697.10",
  "DATAPATTNS": "3383.20",
  "DAVANGERE": "3.93",
  "DBCORP": "210.69",
  "DBEIL": "72.78",
  "DBL": "452.90",
  "DBOL": "105.85",
  "DBREALTY": "101.29",
  "DBSTOCKBRO": "25.36",
  "DCAL": "172.41",
  "DCBBANK": "172.32",
  "DCI": "253.40",
  "DCM": "60.98",
  "DCMFINSERV": "5.62",
  "DCMNVL": "118.12",
  "DCMSHRIRAM": "989.80",
  "DCMSIL": "63.31",
  "DCMSRIND": "35.56",
  "DCW": "43.79",
  "DCXINDIA": "188.28",
  "DDEVPLSTIK": "260.30",
  "DECCANCE": "685.65",
  "DEEDEV": "310.85",
  "DEEPAKFERT": "996.85",
  "DEEPAKNTR": "1489.60",
  "DEEPINDS": "343.25",
  "DEFENCE": "67.88",
  "DELHIVERY": "417.95",
  "DELPHIFX": "11.46",
  "DELTACORP": "56.93",
  "DELTAMAGNT": "58.69",
  "DEN": "26.77",
  "DENORA": "710.30",
  "DENTA": "259.60",
  "DEVIT": "26.64",
  "DEVX": "37.73",
  "DEVYANI": "111.98",
  "DGCONTENT": "25.69",
  "DHAMPURSUG": "127.47",
  "DHANBANK": "23.43",
  "DHANUKA": "977.00",
  "DHARMAJ": "241.34",
  "DHRUV": "31.04",
  "DHUNINV": "861.35",
  "DIACABS": "137.31",
  "DIAMINESQ": "222.55",
  "DIAMONDYD": "979.60",
  "DICIND": "524.10",
  "DIFFNKG": "260.15",
  "DIGIDRIVE": "21.43",
  "DIGISPICE": "17.83",
  "DIGITIDE": "88.06",
  "DIGJAMLMTD": "40.28",
  "DISHTV": "2.58",
  "DIVGIITTS": "723.05",
  "DIVIDEND": "35.30",
  "DIVOPPBEES": "78.94",
  "DLINKINDIA": "399.60",
  "DMCC": "220.33",
  "DNAMEDIA": "3.36",
  "DODLA": "1018.10",
  "DOLATALGO": "75.51",
  "DOLLAR": "259.40",
  "DOLPHIN": "403.85",
  "DOMS": "2097.70",
  "DONEAR": "88.92",
  "DPABHUSHAN": "1037.50",
  "DPSCLTD": "8.54",
  "DPWIRES": "148.13",
  "DRCSYSTEMS": "13.27",
  "DREAMFOLKS": "75.06",
  "DREDGECORP": "962.20",
  "DSFCL": "25.92",
  "DSSL": "911.50",
  "DTIL": "131.14",
  "DUCON": "3.14",
  "DVL": "218.75",
  "DWARKESH": "39.53",
  "DYCL": "285.55",
  "DYNAMATECH": "9919.00",
  "DYNPRO": "212.12",
  "EASEMYTRIP": "7.35",
  "EBANKNIFTY": "56.20",
  "EBBETF0430": "1565.65",
  "EBBETF0431": "1402.63",
  "EBBETF0433": "1272.73",
  "EBGNG": "374.25",
  "ECAPINSURE": "23.11",
  "ECLERX": "3114.40",
  "ECOSMOBLTY": "137.56",
  "EDELWEISS": "108.65",
  "EFCIL": "216.41",
  "EGOLD": "159.95",
  "EIDPARRY": "810.10",
  "EIEL": "153.08",
  "EIFFL": "230.57",
  "EIHAHOTELS": "313.10",
  "EIHOTEL": "320.05",
  "EIMCOELECO": "1553.80",
  "EKC": "110.89",
  "ELDEHSG": "828.40",
  "ELECON": "401.30",
  "ELECTCAST": "75.62",
  "ELECTHERM": "613.50",
  "ELGIEQUIP": "501.10",
  "ELGIRUBCO": "41.16",
  "ELIN": "119.92",
  "ELIQUID": "1021.75",
  "ELLEN": "228.53",
  "ELM250": "15.61",
  "EMAMILTD": "433.25",
  "EMAMIPAP": "75.77",
  "EMAMIREAL": "59.45",
  "EMCURE": "1560.10",
  "EMIL": "93.45",
  "EMKAY": "219.79",
  "EMMBI": "82.99",
  "EMMVEE": "206.37",
  "EMSLIMITED": "311.40",
  "EMUDHRA": "418.50",
  "EMULTIMQ": "39.39",
  "ENDURANCE": "2485.20",
  "ENERGY": "36.24",
  "ENERGYDEV": "15.30",
  "ENGINERSIN": "199.02",
  "ENIFTY": "23.92",
  "ENIL": "105.79",
  "ENTERO": "1024.00",
  "EPACK": "265.37",
  "EPACKPEB": "160.03",
  "EPIGRAL": "875.90",
  "EPL": "195.12",
  "EQUAL200": "12.75",
  "EQUAL50": "317.18",
  "EQUAL50ADD": "326.69",
  "EQUITASBNK": "58.16",
  "ERIS": "1349.30",
  "ESABINDIA": "5335.50",
  "ESAFSFB": "24.98",
  "ESCORTS": "3396.60",
  "ESENSEX": "77.13",
  "ESG": "40.27",
  "ESILVER": "262.30",
  "ESSARSHPNG": "25.26",
  "ESSENTIA": "1.29",
  "ESTER": "96.93",
  "ETHOSLTD": "2172.80",
  "EUREKAFORB": "443.50",
  "EUROBOND": "160.35",
  "EUROPRATIK": "243.55",
  "EVEREADY": "315.25",
  "EVERESTIND": "375.35",
  "EVIETF": "28.69",
  "EVINDIA": "28.72",
  "EXCEL": "1.17",
  "EXCELINDUS": "902.35",
  "EXCELSOFT": "79.91",
  "EXICOM": "85.46",
  "EXIDEIND": "311.50",
  "EXPLEOSOL": "757.45",
  "EXXARO": "7.04",
  "FABTECH": "150.44",
  "FAIRCHEMOR": "549.95",
  "FCL": "22.53",
  "FCSSOFT": "1.49",
  "FDC": "369.05",
  "FEDERALBNK": "269.45",
  "FEDFINA": "128.30",
  "FIEMIND": "2111.10",
  "FILATEX": "42.51",
  "FILATFASH": "0.19",
  "FINCABLES": "887.85",
  "FINEORG": "4277.10",
  "FINIETF": "30.28",
  "FINKURVE": "59.29",
  "FINOPB": "179.93",
  "FINPIPE": "185.41",
  "FIRSTCRY": "224.86",
  "FISCHER": "36.58",
  "FIVESTAR": "380.60",
  "FLAIR": "302.10",
  "FLEXIADD": "9.48",
  "FLEXITUFF": "7.01",
  "FLUOROCHEM": "3245.60",
  "FMCGIETF": "52.47",
  "FMGOETZE": "386.35",
  "FMNL": "8.42",
  "FOCUS": "66.78",
  "FOODSIN": "56.77",
  "FORCEMOT": "21665.00",
  "FORTIS": "881.20",
  "FOSECOIND": "5114.50",
  "FRACTAL": "842.65",
  "FSL": "218.00",
  "FUSION": "170.68",
  "GABRIEL": "884.10",
  "GAEL": "132.42",
  "GALAPREC": "733.95",
  "GALAXYSURF": "1872.60",
  "GALLANTT": "522.85",
  "GANDHAR": "130.16",
  "GANDHITUBE": "783.10",
  "GANECOS": "759.35",
  "GANESHBE": "78.02",
  "GANESHCP": "170.10",
  "GANESHHOU": "625.80",
  "GANGAFORGE": "2.85",
  "GANGESSECU": "119.34",
  "GARFIBRES": "624.45",
  "GARUDA": "168.80",
  "GATECH": "0.48",
  "GATECHDVR": "0.44",
  "GATEWAY": "55.94",
  "GAYAHWS": "2.39",
  "GEECEE": "269.30",
  "GEEKAYWIRE": "21.42",
  "GEMAROMA": "186.12",
  "GENCON": "43.50",
  "GENESYS": "279.85",
  "GENUSPAPER": "11.71",
  "GENUSPOWER": "253.15",
  "GEOJITFSL": "59.87",
  "GESHIP": "1427.00",
  "GFLLIMITED": "44.59",
  "GHCL": "456.65",
  "GHCLTEXTIL": "73.43",
  "GICHSGFIN": "146.42",
  "GICRE": "366.15",
  "GILLANDERS": "82.74",
  "GILLETTE": "7979.00",
  "GILT10BETA": "26.06",
  "GILT5BETA": "65.11",
  "GILT5YBEES": "64.32",
  "GINNIFILA": "35.83",
  "GIPCL": "131.86",
  "GKENERGY": "110.58",
  "GKSL": "106.80",
  "GKWLIMITED": "1650.40",
  "GLAND": "1667.00",
  "GLAXO": "2486.00",
  "GLENMARK": "2272.70",
  "GLOBAL": "105.06",
  "GLOBALE": "10.77",
  "GLOBALVECT": "164.45",
  "GLOBE": "2.59",
  "GLOBECIVIL": "46.50",
  "GLOBUSSPR": "853.45",
  "GLOSTERLTD": "547.85",
  "GLOTTIS": "44.06",
  "GMBREW": "1009.90",
  "GMDCLTD": "542.35",
  "GMMPFAUDLR": "869.70",
  "GMRAIRPORT": "93.79",
  "GMRP&UI": "106.71",
  "GNA": "421.10",
  "GNFC": "425.15",
  "GOACARBON": "329.95",
  "GOCLCORP": "252.20",
  "GOCOLORS": "280.65",
  "GODAVARIB": "295.05",
  "GODFRYPHLP": "2122.80",
  "GODIGIT": "334.25",
  "GODREJAGRO": "600.35",
  "GODREJIND": "888.60",
  "GODREJPROP": "1651.10",
  "GOKEX": "611.75",
  "GOKUL": "41.78",
  "GOKULAGRO": "162.60",
  "GOLD1": "134.05",
  "GOLD360": "156.00",
  "GOLDADD": "155.94",
  "GOLDBEES": "132.71",
  "GOLDBETA": "134.95",
  "GOLDBND": "160.49",
  "GOLDCASE": "25.27",
  "GOLDETF": "155.48",
  "GOLDIAM": "313.10",
  "GOLDIETF": "137.45",
  "GOLDTECH": "38.45",
  "GOODLUCK": "1038.70",
  "GOPAL": "281.25",
  "GPIL": "253.75",
  "GPPL": "159.68",
  "GPTHEALTH": "124.60",
  "GPTINFRA": "108.15",
  "GRANULES": "586.20",
  "GRAPHITE": "648.95",
  "GRAVITA": "1505.30",
  "GREAVESCOT": "144.38",
  "GREENLAM": "227.21",
  "GREENPANEL": "194.88",
  "GREENPLY": "201.99",
  "GREENPOWER": "9.26",
  "GRINDWELL": "1514.60",
  "GRINFRA": "925.35",
  "GRMOVER": "157.29",
  "GROBTEA": "868.35",
  "GROWW": "155.06",
  "GROWWCAPM": "9.61",
  "GROWWCHEM": "26.97",
  "GROWWDEFNC": "82.61",
  "GROWWEV": "28.66",
  "GROWWGOLD": "15.67",
  "GROWWHOSPI": "47.78",
  "GROWWLIQID": "108.16",
  "GROWWLOVOL": "10.20",
  "GROWWMC150": "209.64",
  "GROWWMETAL": "11.22",
  "GROWWMOM50": "9.96",
  "GROWWN200": "10.85",
  "GROWWNET": "8.28",
  "GROWWNIFTY": "9.61",
  "GROWWNXT50": "66.68",
  "GROWWPOWER": "10.39",
  "GROWWPSE": "101.87",
  "GROWWRAIL": "30.70",
  "GROWWRLTY": "8.21",
  "GROWWSC250": "8.86",
  "GROWWSLVR": "25.77",
  "GRPLTD": "1713.60",
  "GRSE": "2449.10",
  "GRWRHITECH": "3986.70",
  "GSEC10ABSL": "111.29",
  "GSEC10IETF": "260.89",
  "GSEC10YEAR": "29.91",
  "GSEC5IETF": "64.61",
  "GSFC": "160.89",
  "GSLSU": "73.31",
  "GSPL": "285.15",
  "GSS": "12.31",
  "GTECJAINX": "21.05",
  "GTL": "6.85",
  "GTLINFRA": "1.09",
  "GTPL": "63.55",
  "GUFICBIO": "289.30",
  "GUJALKALI": "445.20",
  "GUJAPOLLO": "399.95",
  "GUJGASLTD": "391.00",
  "GUJRAFFIA": "37.72",
  "GUJTHEM": "290.60",
  "GULFOILLUB": "1017.20",
  "GULFPETRO": "30.42",
  "GULPOLY": "160.21",
  "GVPTECH": "6.23",
  "GVT&D": "3784.10",
  "HALDER": "263.15",
  "HALEOSLABS": "1287.90",
  "HAPPYFORGE": "1290.60",
  "HARIOMPIPE": "330.00",
  "HARRMALAYA": "180.02",
  "HARSHA": "355.45",
  "HATHWAY": "10.06",
  "HATSUN": "918.30",
  "HAVISHA": "1.46",
  "HBLENGINE": "670.60",
  "HBSL": "50.02",
  "HCC": "15.97",
  "HCG": "577.15",
  "HCL-INSYS": "12.17",
  "HDBFS": "656.55",
  "HDFCAMC": "2448.20",
  "HDFCBSE500": "35.38",
  "HDFCGOLD": "137.14",
  "HDFCGROWTH": "114.75",
  "HDFCLIQUID": "1051.40",
  "HDFCLOWVOL": "20.01",
  "HDFCMID150": "21.01",
  "HDFCMOMENT": "29.80",
  "HDFCNEXT50": "67.79",
  "HDFCNIF100": "25.33",
  "HDFCNIFBAN": "57.27",
  "HDFCNIFIT": "31.50",
  "HDFCNIFTY": "267.47",
  "HDFCPSUBK": "89.19",
  "HDFCPVTBAN": "26.93",
  "HDFCQUAL": "56.10",
  "HDFCSENSEX": "86.81",
  "HDFCSILVER": "251.78",
  "HDFCSML250": "154.28",
  "HDFCVALUE": "129.76",
  "HEADSUP": "7.11",
  "HEALTHADD": "150.97",
  "HEALTHCARE": "18.84",
  "HEALTHIETF": "153.42",
  "HEALTHY": "15.35",
  "HECPROJECT": "113.14",
  "HEG": "524.75",
  "HEIDELBERG": "157.13",
  "HEMIPROP": "140.00",
  "HERANBA": "187.19",
  "HERITGFOOD": "309.25",
  "HEROMOTOCO": "5575.00",
  "HESTERBIO": "1450.70",
  "HEXATRADEX": "159.63",
  "HEXT": "428.90",
  "HFCL": "72.06",
  "HGINFRA": "520.15",
  "HGM": "53.40",
  "HGS": "379.80",
  "HIKAL": "179.73",
  "HILINFRA": "50.79",
  "HILTON": "16.87",
  "HIMATSEIDE": "88.06",
  "HINDCOMPOS": "410.10",
  "HINDCON": "19.28",
  "HINDCOPPER": "542.90",
  "HINDOILEXP": "147.32",
  "HINDPETRO": "384.25",
  "HINDWAREAP": "207.09",
  "HIRECT": "1433.30",
  "HISARMETAL": "159.34",
  "HITECH": "81.49",
  "HITECHCORP": "129.93",
  "HLEGLAS": "308.15",
  "HLVLTD": "7.62",
  "HMAAGRO": "24.74",
  "HMVL": "61.91",
  "HNDFDS": "474.10",
  "HNGSNGBEES": "512.72",
  "HOMEFIRST": "1053.20",
  "HONASA": "289.35",
  "HONAUT": "30650.00",
  "HONDAPOWER": "2075.90",
  "HPAL": "33.28",
  "HPIL": "123.15",
  "HPL": "322.40",
  "HSCL": "447.00",
  "HTMEDIA": "20.77",
  "HUBTOWN": "212.97",
  "HUDCO": "177.56",
  "HUHTAMAKI": "169.88",
  "HYBRIDFIN": "16.98",
  "IBULLSLTD": "10.55",
  "ICDSLTD": "37.81",
  "ICEMAKE": "823.95",
  "ICICIAMC": "3000.20",
  "ICICIB22": "121.78",
  "ICICIPRULI": "598.50",
  "ICIL": "248.10",
  "ICRA": "5432.50",
  "IDBI": "99.14",
  "IDEA": "9.71",
  "IDEAFORGE": "433.10",
  "IDFCFIRSTB": "66.16",
  "IDFNIFTYET": "262.48",
  "IEX": "122.85",
  "IFBAGRO": "759.90",
  "IFBIND": "1044.10",
  "IFCI": "53.61",
  "IFGLEXPOR": "151.63",
  "IGARASHI": "319.05",
  "IGCL": "63.18",
  "IGIL": "327.60",
  "IGL": "162.67",
  "IGPL": "360.75",
  "IIFL": "480.85",
  "IIFLCAPS": "297.00",
  "IITL": "133.04",
  "IKIO": "133.65",
  "IKS": "1376.40",
  "IMAGICAA": "43.29",
  "IMFA": "1230.30",
  "IMPAL": "1023.10",
  "INA": "100.21",
  "INCREDIBLE": "33.94",
  "INDBANK": "32.22",
  "INDGN": "449.60",
  "INDIACEM": "367.65",
  "INDIAGLYCO": "867.80",
  "INDIAMART": "2130.40",
  "INDIANB": "917.80",
  "INDIANCARD": "194.89",
  "INDIANHUME": "351.35",
  "INDIASHLTR": "712.85",
  "INDIGOPNTS": "823.45",
  "INDIQUBE": "160.05",
  "INDNIPPON": "793.75",
  "INDOAMIN": "100.75",
  "INDOBORAX": "245.65",
  "INDOCO": "194.43",
  "INDOFARM": "126.07",
  "INDORAMA": "34.81",
  "INDOSTAR": "211.81",
  "INDOTECH": "1378.30",
  "INDOTHAI": "261.60",
  "INDOUS": "99.85",
  "INDOWIND": "8.52",
  "INDRAMEDCO": "408.30",
  "INDSWFTLAB": "142.82",
  "INDTERRAIN": "29.53",
  "INDUSINDBK": "877.15",
  "INDUSTOWER": "438.75",
  "INFOBEAN": "134.94",
  "INFOMEDIA": "5.04",
  "INFRA": "10.95",
  "INFRABEES": "933.39",
  "INFRAIETF": "92.88",
  "INGERRAND": "3866.40",
  "INNOVACAP": "695.70",
  "INNOVANA": "384.20",
  "INOXGREEN": "150.11",
  "INOXINDIA": "1193.40",
  "INOXWIND": "82.26",
  "INSECTICID": "576.55",
  "INTELLECT": "662.25",
  "INTENTECH": "91.41",
  "INTERARCH": "1832.40",
  "INTERNET": "11.17",
  "INTLCONV": "74.95",
  "INVENTURE": "1.04",
  "IOB": "33.56",
  "IOLCP": "71.62",
  "IONEXCHANG": "369.55",
  "IPCALAB": "1533.90",
  "IPL": "146.69",
  "IRB": "42.10",
  "IRCON": "137.16",
  "IRCTC": "534.15",
  "IREDA": "114.80",
  "IRIS": "243.36",
  "IRISDOREME": "30.09",
  "IRMENERGY": "213.12",
  "ISFT": "70.20",
  "ISGEC": "949.75",
  "ISHANCH": "55.57",
  "IT": "32.69",
  "ITADD": "31.24",
  "ITBEES": "32.77",
  "ITBETA": "310.14",
  "ITCHOTELS": "162.12",
  "ITDC": "465.10",
  "ITETF": "31.14",
  "ITI": "253.40",
  "ITIETF": "32.76",
  "IVALUE": "228.61",
  "IVC": "7.00",
  "IVP": "127.37",
  "IVZINGOLD": "13935.60",
  "IVZINNIFTY": "2770.00",
  "IXIGO": "167.53",
  "J&KBANK": "125.41",
  "JAGRAN": "63.51",
  "JAGSNPHARM": "179.24",
  "JAIBALAJI": "67.46",
  "JAICORPLTD": "103.00",
  "JAINREC": "434.00",
  "JAIPURKURT": "29.77",
  "JAMNAAUTO": "123.89",
  "JARO": "411.80",
  "JASH": "376.00",
  "JAYAGROGN": "188.45",
  "JAYBARMARU": "90.94",
  "JAYKAY": "138.47",
  "JAYNECOIND": "73.53",
  "JAYSREETEA": "82.43",
  "JBCHEPHARM": "2126.10",
  "JBMA": "511.85",
  "JETFREIGHT": "19.14",
  "JGCHEM": "353.35",
  "JHS": "9.36",
  "JINDALPHOT": "1228.90",
  "JINDALPOLY": "903.10",
  "JINDRILL": "531.25",
  "JINDWORLD": "21.88",
  "JISLDVREQS": "22.64",
  "JISLJALEQS": "35.61",
  "JKCEMENT": "5151.00",
  "JKIL": "504.40",
  "JKIPL": "53.45",
  "JKLAKSHMI": "604.60",
  "JKPAPER": "339.05",
  "JKTYRE": "434.75",
  "JLHL": "1252.90",
  "JMA": "84.48",
  "JMFINANCIL": "121.69",
  "JNKINDIA": "241.33",
  "JOCIL": "126.82",
  "JPOLYINVST": "1340.60",
  "JPPOWER": "13.66",
  "JSFB": "360.40",
  "JSL": "736.55",
  "JSLL": "616.50",
  "JSWCEMENT": "120.61",
  "JSWHL": "16080.00",
  "JSWINFRA": "259.55",
  "JTEKTINDIA": "136.02",
  "JTLIND": "54.56",
  "JUBLCPL": "1776.70",
  "JUBLFOOD": "473.25",
  "JUBLINGREA": "570.50",
  "JUBLPHARMA": "807.65",
  "JUNIORBEES": "716.62",
  "JUNIPER": "199.63",
  "JUSTDIAL": "535.35",
  "JWL": "274.85",
  "JYOTHYLAB": "236.65",
  "JYOTICNC": "770.95",
  "JYOTISTRUC": "11.35",
  "KABRAEXTRU": "238.10",
  "KAJARIACER": "957.95",
  "KAKATCEM": "107.69",
  "KALAMANDIR": "102.63",
  "KALPATARU": "302.45",
  "KALYANIFRG": "593.55",
  "KALYANKJIL": "390.50",
  "KAMATHOTEL": "195.96",
  "KAMDHENU": "22.50",
  "KAMOPAINTS": "4.62",
  "KANANIIND": "1.38",
  "KANORICHEM": "64.04",
  "KANPRPLA": "182.02",
  "KANSAINER": "187.02",
  "KARMAENG": "38.71",
  "KARURVYSYA": "304.95",
  "KAUSHALYA": "825.95",
  "KAYA": "322.90",
  "KAYNES": "3726.10",
  "KCP": "148.74",
  "KCPSUGIND": "23.56",
  "KDDL": "2328.50",
  "KEC": "547.75",
  "KECL": "82.76",
  "KEEPLEARN": "1.88",
  "KEI": "4321.00",
  "KELLTONTEC": "17.17",
  "KERNEX": "996.70",
  "KEYFINSERV": "266.00",
  "KFINTECH": "926.85",
  "KHADIM": "111.17",
  "KHAICHEM": "54.95",
  "KHAITANLTD": "93.14",
  "KHANDSE": "18.11",
  "KICL": "4760.50",
  "KILITCH": "317.90",
  "KIMS": "675.90",
  "KINGFA": "4197.00",
  "KIOCL": "314.40",
  "KIRIINDUS": "394.95",
  "KIRLOSBROS": "1592.60",
  "KIRLOSENG": "1450.40",
  "KIRLOSIND": "2818.80",
  "KIRLPNU": "1117.10",
  "KITEX": "167.80",
  "KKCL": "484.65",
  "KMEW": "1601.00",
  "KMSUGAR": "25.73",
  "KNAGRI": "179.95",
  "KNRCON": "125.70",
  "KOHINOOR": "24.46",
  "KOKUYOCMLN": "76.99",
  "KOLTEPATIL": "335.25",
  "KOPRAN": "124.07",
  "KOTARISUG": "24.53",
  "KOTHARIPET": "111.67",
  "KOTHARIPRO": "63.89",
  "KPEL": "281.10",
  "KPIGREEN": "363.70",
  "KPIL": "1141.30",
  "KPITTECH": "682.75",
  "KPRMILL": "810.90",
  "KRBL": "310.30",
  "KREBSBIO": "54.91",
  "KRIDHANINF": "2.77",
  "KRISHANA": "495.85",
  "KRISHIVAL": "315.50",
  "KRISHNADEF": "1100.30",
  "KRITI": "82.53",
  "KRITIKA": "5.89",
  "KRITINUT": "65.35",
  "KRN": "926.90",
  "KRONOX": "111.82",
  "KROSS": "193.18",
  "KRSNAA": "619.40",
  "KRYSTAL": "591.20",
  "KSB": "764.00",
  "KSCL": "800.45",
  "KSHINTL": "414.85",
  "KSL": "701.75",
  "KSOLVES": "288.55",
  "KTKBANK": "228.73",
  "KUANTUM": "82.51",
  "KWIL": "26.59",
  "LAGNAM": "68.86",
  "LAL": "7.00",
  "LALPATHLAB": "1404.70",
  "LAMBODHARA": "98.88",
  "LANDMARK": "363.15",
  "LAOPALA": "193.94",
  "LASA": "7.81",
  "LATENTVIEW": "299.15",
  "LATTEYS": "20.17",
  "LAURUSLABS": "1041.00",
  "LAXMIDENTL": "184.03",
  "LAXMIINDIA": "84.99",
  "LCCINFOTEC": "5.17",
  "LEMERITE": "442.75",
  "LEMONTREE": "106.37",
  "LENSKART": "499.10",
  "LFIC": "130.86",
  "LGBBROSLTD": "1913.60",
  "LGEINDIA": "1594.60",
  "LGHL": "271.70",
  "LIBAS": "9.88",
  "LIBERTSHOE": "225.37",
  "LICHSGFIN": "505.40",
  "LICMFGOLD": "144.40",
  "LICNETFGSC": "29.03",
  "LICNETFN50": "266.77",
  "LICNFNHGP": "268.62",
  "LICNMID100": "56.68",
  "LIKHITHA": "149.27",
  "LINC": "102.46",
  "LINCOLN": "621.85",
  "LINDEINDIA": "6776.00",
  "LIQGRWBEES": "1030.89",
  "LIQUID": "999.99",
  "LIQUID1": "1094.72",
  "LIQUIDADD": "1116.83",
  "LIQUIDBEES": "1000.00",
  "LIQUIDBETF": "1072.35",
  "LIQUIDCASE": "113.08",
  "LIQUIDETF": "999.99",
  "LIQUIDIETF": "1000.00",
  "LIQUIDPLUS": "1075.98",
  "LIQUIDSBI": "1000.00",
  "LIQUIDSHRI": "1095.29",
  "LLOYDSENGG": "44.00",
  "LLOYDSENT": "48.81",
  "LLOYDSME": "1185.60",
  "LMW": "14502.00",
  "LOKESHMACH": "209.76",
  "LORDSCHLO": "122.00",
  "LOTUSDEV": "134.15",
  "LOTUSEYE": "107.85",
  "LOVABLE": "68.70",
  "LOWVOL": "199.95",
  "LOWVOL1": "20.51",
  "LOWVOLIETF": "21.47",
  "LPDC": "5.86",
  "LTF": "266.65",
  "LTFOODS": "382.75",
  "LTGILTBEES": "29.42",
  "LTGILTCASE": "30.03",
  "LTTS": "3097.40",
  "LUMAXIND": "5237.00",
  "LUMAXTECH": "1470.40",
  "LUPIN": "2344.60",
  "LUXIND": "890.05",
  "LXCHEM": "120.65",
  "LYKALABS": "57.01",
  "LYPSAGEMS": "4.99",
  "M&MFIN": "353.05",
  "MACPOWER": "947.50",
  "MADHAV": "35.95",
  "MADHUCON": "4.59",
  "MADRASFERT": "66.30",
  "MAFANG": "163.74",
  "MAGADSUGAR": "452.30",
  "MAGNUM": "19.62",
  "MAHABANK": "67.04",
  "MAHAPEXLTD": "107.57",
  "MAHASTEEL": "1014.70",
  "MAHEPC": "114.12",
  "MAHESHWARI": "40.95",
  "MAHKTECH": "23.25",
  "MAHLIFE": "357.50",
  "MAHLOG": "394.95",
  "MAHSCOOTER": "12755.00",
  "MAHSEAMLES": "556.90",
  "MAITHANALL": "947.00",
  "MAKEINDIA": "154.08",
  "MALLCOM": "1052.40",
  "MALUPAPER": "31.99",
  "MAMATA": "385.45",
  "MANAKCOAT": "115.23",
  "MANAKSIA": "55.51",
  "MANAKSTEEL": "55.56",
  "MANALIPETC": "49.99",
  "MANAPPURAM": "258.00",
  "MANBA": "113.19",
  "MANCREDIT": "170.93",
  "MANGLMCEM": "834.05",
  "MANINDS": "417.95",
  "MANINFRA": "98.49",
  "MANKIND": "2243.80",
  "MANOMAY": "224.29",
  "MANORAMA": "1337.20",
  "MANORG": "422.10",
  "MANUFGBEES": "153.37",
  "MANUGRAPH": "14.06",
  "MANYAVAR": "364.40",
  "MAPMYINDIA": "990.00",
  "MARALOVER": "41.35",
  "MARATHON": "413.50",
  "MARICO": "761.60",
  "MARINE": "185.20",
  "MARKOLINES": "154.09",
  "MARKSANS": "172.95",
  "MASFIN": "303.40",
  "MASKINVEST": "132.09",
  "MASPTOP50": "69.38",
  "MASTEK": "1579.20",
  "MASTERTR": "75.37",
  "MATRIMONY": "396.50",
  "MAWANASUG": "80.82",
  "MAXESTATES": "375.45",
  "MAXIND": "152.39",
  "MAYURUNIQ": "510.85",
  "MAZDA": "193.02",
  "MBAPL": "463.95",
  "MBEL": "298.70",
  "MBLINFRA": "25.32",
  "MCLEODRUSS": "39.78",
  "MCLOUD": "23.36",
  "MCX": "2531.60",
  "MEDANTA": "1101.20",
  "MEDIASSIST": "324.75",
  "MEDICAMEQ": "283.00",
  "MEDICO": "40.84",
  "MEDPLUS": "830.35",
  "MEESHO": "139.40",
  "MEGASTAR": "236.46",
  "MEIL": "239.15",
  "MENONBE": "126.79",
  "METAL": "11.89",
  "METALIETF": "11.86",
  "METROBRAND": "947.00",
  "METROPOLIS": "1837.00",
  "MFML": "24.28",
  "MFSL": "1725.50",
  "MGEL": "10.08",
  "MGL": "1049.30",
  "MHLXMIRU": "166.21",
  "MHRIL": "268.35",
  "MICEL": "34.93",
  "MID150": "21.36",
  "MID150BEES": "215.62",
  "MID150CASE": "10.44",
  "MIDCAP": "16.35",
  "MIDCAPADD": "20.90",
  "MIDCAPBETA": "212.45",
  "MIDCAPETF": "21.28",
  "MIDCAPIETF": "21.54",
  "MIDHANI": "336.05",
  "MIDQ50ADD": "228.74",
  "MIDSELIETF": "16.73",
  "MIDSMALL": "45.60",
  "MIDWESTLTD": "1221.40",
  "MINDACORP": "494.25",
  "MINDTECK": "192.51",
  "MIRCELECTR": "25.17",
  "MIRZAINT": "31.78",
  "MITCON": "53.28",
  "MITTAL": "0.85",
  "MKPL": "4.90",
  "MMFL": "455.65",
  "MMP": "229.86",
  "MMTC": "55.45",
  "MNC": "30.98",
  "MOALPHA50": "48.18",
  "MOBIKWIK": "180.03",
  "MOCAPITAL": "45.62",
  "MODEFENCE": "90.72",
  "MODINATUR": "278.50",
  "MODIRUBBER": "113.63",
  "MODIS": "310.05",
  "MODISONLTD": "128.75",
  "MODTHREAD": "54.27",
  "MOENERGY": "36.93",
  "MOGOLD": "158.35",
  "MOGSEC": "63.59",
  "MOHEALTH": "44.30",
  "MOHITIND": "23.32",
  "MOIL": "277.80",
  "MOINFRA": "58.22",
  "MOIPO": "40.66",
  "MOKSH": "11.73",
  "MOL": "44.81",
  "MOLDTECH": "130.77",
  "MOLDTKPAC": "526.35",
  "MOLOWVOL": "36.59",
  "MOM100": "60.95",
  "MOM30IETF": "30.05",
  "MOM50": "249.96",
  "MOMENTUM": "29.86",
  "MOMENTUM30": "29.72",
  "MOMENTUM50": "49.23",
  "MOMGF": "151.00",
  "MOMIDMTM": "59.63",
  "MOMNC": "30.02",
  "MOMOMENTUM": "59.85",
  "MON100": "222.27",
  "MON50EQUAL": "31.74",
  "MONARCH": "250.20",
  "MONEXT50": "66.37",
  "MONEYBOXX": "67.14",
  "MONIFTY100": "24.67",
  "MONIFTY500": "22.50",
  "MONQ50": "95.85",
  "MONTECARLO": "523.10",
  "MOPSE": "103.10",
  "MOQUALITY": "189.65",
  "MOREALTY": "73.15",
  "MOREPENLAB": "40.11",
  "MOSCHIP": "169.91",
  "MOSERVICE": "30.55",
  "MOSILVER": "267.23",
  "MOSMALL250": "15.36",
  "MOTILALOFS": "699.05",
  "MOTISONS": "13.77",
  "MOTOGENFIN": "20.10",
  "MOTOUR": "71.91",
  "MOVALUE": "116.93",
  "MPHASIS": "2184.90",
  "MPSLTD": "1482.50",
  "MRF": "136255.00",
  "MRPL": "186.92",
  "MSCIADD": "28.54",
  "MSCIINDIA": "28.81",
  "MSPL": "31.79",
  "MSTCLTD": "423.00",
  "MSUMI": "40.18",
  "MTARTECH": "3575.30",
  "MTNL": "26.06",
  "MUFIN": "105.66",
  "MUFTI": "78.29",
  "MUKANDLTD": "123.61",
  "MUKKA": "22.93",
  "MUKTAARTS": "48.13",
  "MULTICAP": "15.35",
  "MUNJALAU": "80.91",
  "MUNJALSHOW": "127.12",
  "MURUDCERA": "30.77",
  "MUTHOOTCAP": "208.34",
  "MUTHOOTFIN": "3163.90",
  "MUTHOOTMF": "155.79",
  "MVGJL": "154.02",
  "MWL": "273.05",
  "NACLIND": "122.44",
  "NAGAFERT": "4.18",
  "NAGREEKCAP": "24.94",
  "NAGREEKEXP": "23.51",
  "NAHARCAP": "222.61",
  "NAHARINDUS": "92.85",
  "NAHARPOLY": "234.33",
  "NAHARSPING": "194.87",
  "NAM-INDIA": "857.30",
  "NARMADA": "32.11",
  "NATCAPSUQ": "151.00",
  "NATCOPHARM": "1016.15",
  "NATHBIOGEN": "146.78",
  "NATIONALUM": "397.75",
  "NAVA": "567.30",
  "NAVINFLUOR": "6315.00",
  "NAVKARCORP": "90.03",
  "NAVKARURB": "1.03",
  "NAVNETEDUL": "136.88",
  "NAZARA": "243.80",
  "NBCC": "86.16",
  "NBIFIN": "1842.90",
  "NCC": "149.01",
  "NCLIND": "183.83",
  "NDGL": "2450.60",
  "NDL": "2.52",
  "NDLVENTURE": "119.06",
  "NDRAUTO": "709.15",
  "NDTV": "76.90",
  "NECCLTD": "13.85",
  "NECLIFE": "11.42",
  "NELCAST": "120.07",
  "NELCO": "590.50",
  "NEOGEN": "1435.40",
  "NEPHROPLUS": "580.45",
  "NESCO": "1067.40",
  "NETF": "258.17",
  "NETWEB": "3278.60",
  "NETWORK18": "32.47",
  "NEULANDLAB": "12828.00",
  "NEWGEN": "457.60",
  "NEXT30ADD": "40.08",
  "NEXT50": "683.42",
  "NEXT50ADD": "66.41",
  "NEXT50BETA": "71.54",
  "NEXT50ETF": "66.80",
  "NEXT50IETF": "70.02",
  "NEXTMEDIA": "5.04",
  "NFL": "75.28",
  "NGIL": "24.02",
  "NGLFINE": "2431.00",
  "NH": "1736.20",
  "NHPC": "73.46",
  "NIACL": "136.74",
  "NIBE": "1105.20",
  "NIBL": "32.02",
  "NIF100BEES": "259.85",
  "NIF100IETF": "27.37",
  "NIFTY1": "263.71",
  "NIFTY100EW": "32.53",
  "NIFTYADD": "250.21",
  "NIFTYBEES": "270.56",
  "NIFTYBETA": "263.21",
  "NIFTYBETF": "244.32",
  "NIFTYCASE": "9.53",
  "NIFTYETF": "258.13",
  "NIFTYIETF": "269.26",
  "NIFTYQLITY": "20.36",
  "NIITLTD": "65.29",
  "NIITMTS": "313.35",
  "NILAINFRA": "7.39",
  "NILASPACES": "13.39",
  "NILKAMAL": "1311.00",
  "NINSYS": "303.75",
  "NIPPOBATRY": "305.50",
  "NIRAJ": "26.80",
  "NITCO": "68.89",
  "NITINSPIN": "360.25",
  "NITIRAJ": "221.75",
  "NIVABUPA": "71.52",
  "NKIND": "64.98",
  "NLCINDIA": "248.45",
  "NMDC": "79.73",
  "NOCIL": "131.27",
  "NOIDATOLL": "3.64",
  "NORTHARC": "242.40",
  "NOVAAGRI": "27.66",
  "NPBET": "274.66",
  "NPST": "1008.20",
  "NRAIL": "429.80",
  "NRBBEARING": "266.10",
  "NRL": "50.79",
  "NSIL": "5675.50",
  "NSLNISP": "37.74",
  "NTPCGREEN": "86.73",
  "NUCLEUS": "769.90",
  "NURECA": "260.35",
  "NUVAMA": "1212.50",
  "NUVOCO": "297.65",
  "NV20": "14.44",
  "NV20BEES": "144.25",
  "NV20IETF": "14.06",
  "NYKAA": "251.70",
  "OAL": "251.45",
  "OBCL": "55.55",
  "OBEROIRLTY": "1488.80",
  "OCCLLTD": "84.92",
  "ODIGMA": "23.67",
  "OFSS": "6792.00",
  "OIL": "482.70",
  "OILCOUNTUB": "43.26",
  "OILIETF": "11.66",
  "OLAELEC": "23.92",
  "OLECTRA": "900.55",
  "OMAXAUTO": "102.06",
  "OMAXE": "74.99",
  "OMFREIGHT": "77.62",
  "OMINFRAL": "86.26",
  "OMNI": "208.95",
  "ONELIFECAP": "15.22",
  "ONEPOINT": "46.18",
  "ONESOURCE": "1473.60",
  "ONMOBILE": "51.14",
  "ONWARDTEC": "251.20",
  "OPTIEMUS": "347.95",
  "ORBTEXP": "162.82",
  "ORCHASP": "2.03",
  "ORCHPHARMA": "524.00",
  "ORICONENT": "65.71",
  "ORIENTALTL": "6.11",
  "ORIENTBELL": "256.45",
  "ORIENTCEM": "143.32",
  "ORIENTCER": "38.02",
  "ORIENTELEC": "175.49",
  "ORIENTHOT": "92.14",
  "ORIENTLTD": "70.12",
  "ORIENTPPR": "16.97",
  "ORIENTTECH": "268.95",
  "ORISSAMINE": "3682.80",
  "ORKLAINDIA": "542.80",
  "OSIAHYPER": "7.04",
  "OSWALAGRO": "43.61",
  "OSWALGREEN": "25.15",
  "OSWALPUMPS": "318.50",
  "OSWALSEEDS": "12.13",
  "PACEDIGITK": "157.37",
  "PAGEIND": "31595.00",
  "PAISALO": "32.73",
  "PAKKA": "81.82",
  "PALASHSECU": "89.84",
  "PALREDTEC": "31.21",
  "PANACEABIO": "347.55",
  "PANAMAPET": "273.15",
  "PANSARI": "296.85",
  "PAR": "90.29",
  "PARACABLES": "32.63",
  "PARADEEP": "112.52",
  "PARAGMILK": "202.88",
  "PARAS": "680.80",
  "PARKHOSPS": "203.40",
  "PARKHOTELS": "115.60",
  "PARSVNATH": "7.18",
  "PASHUPATI": "990.00",
  "PASUPTAC": "46.94",
  "PATANJALI": "497.85",
  "PATELENG": "25.26",
  "PATELRMART": "167.18",
  "PATINTLOG": "10.03",
  "PAUSHAKLTD": "418.25",
  "PAVNAIND": "20.12",
  "PAYTM": "1025.70",
  "PCBL": "273.15",
  "PCJEWELLER": "8.83",
  "PDMJEPAPER": "76.65",
  "PDSL": "291.05",
  "PEARLPOLY": "17.11",
  "PENIND": "146.16",
  "PENINLAND": "16.14",
  "PERSISTENT": "4747.70",
  "PETRONET": "289.65",
  "PFIZER": "4704.50",
  "PFOCUS": "275.55",
  "PFS": "28.51",
  "PGEL": "550.10",
  "PGHH": "10839.00",
  "PGHL": "4898.00",
  "PGIL": "1488.50",
  "PHARMABEES": "24.00",
  "PHOENIXLTD": "1575.70",
  "PICCADIL": "542.00",
  "PIGL": "102.22",
  "PIIND": "3012.30",
  "PILANIINVS": "4423.00",
  "PILITA": "8.07",
  "PINELABS": "171.32",
  "PIONEEREMB": "25.58",
  "PIRAMALFIN": "1779.70",
  "PITTIENG": "816.85",
  "PIXTRANS": "1462.70",
  "PKTEA": "780.00",
  "PLASTIBLEN": "141.93",
  "PLATIND": "214.87",
  "PLAZACABLE": "35.88",
  "PNBGILTS": "75.83",
  "PNBHOUSING": "776.50",
  "PNC": "22.87",
  "PNCINFRA": "202.06",
  "PNGJL": "568.60",
  "PNGSREVA": "390.15",
  "POCL": "1097.90",
  "PODDARMENT": "225.80",
  "POKARNA": "902.50",
  "POLICYBZR": "1463.20",
  "POLYMED": "1333.40",
  "POLYPLEX": "835.55",
  "PONNIERODE": "272.95",
  "POONAWALLA": "417.70",
  "POWERINDIA": "24955.00",
  "POWERMECH": "1974.90",
  "PPAP": "201.05",
  "PPL": "203.14",
  "PPLPHARMA": "155.42",
  "PRABHA": "151.00",
  "PRAENG": "22.00",
  "PRAJIND": "313.95",
  "PRAKASH": "124.55",
  "PRAKASHSTL": "4.17",
  "PRAXIS": "6.74",
  "PRECAM": "124.94",
  "PRECWIRE": "342.95",
  "PREMEXPLN": "479.05",
  "PREMIERENE": "788.10",
  "PREMIERPOL": "58.95",
  "PRESTIGE": "1271.50",
  "PRICOLLTD": "551.30",
  "PRIMESECU": "272.95",
  "PRIMO": "17.32",
  "PRINCEPIPE": "262.05",
  "PRITI": "36.81",
  "PRITIKAUTO": "12.48",
  "PRIVISCL": "2899.90",
  "PROSTARM": "131.36",
  "PROTEAN": "534.70",
  "PROZONER": "45.93",
  "PRSMJOHNSN": "125.61",
  "PRUDENT": "2234.70",
  "PRUDMOULI": "15.04",
  "PSB": "24.34",
  "PSPPROJECT": "684.45",
  "PSUBANK": "885.18",
  "PSUBANKADD": "89.20",
  "PSUBNKBEES": "98.35",
  "PSUBNKIETF": "89.51",
  "PTC": "157.51",
  "PTCIL": "17980.00",
  "PTL": "37.78",
  "PUNJABCHEM": "1071.70",
  "PURVA": "193.57",
  "PVP": "25.95",
  "PVRINOX": "1028.30",
  "PVSL": "93.65",
  "PVTBANIETF": "26.73",
  "PVTBANKADD": "26.86",
  "PWL": "83.17",
  "PYRAMID": "146.91",
  "QGOLDHALF": "133.17",
  "QNIFTY": "261.53",
  "QPOWER": "824.65",
  "QUADFUTURE": "301.45",
  "QUAL30IETF": "20.09",
  "QUALITY30": "19.75",
  "QUESS": "193.14",
  "QUICKHEAL": "157.34",
  "RACE": "110.83",
  "RACLGEAR": "1355.20",
  "RADAAN": "2.94",
  "RADHIKAJWE": "62.14",
  "RADIANTCMS": "38.11",
  "RADICO": "2894.00",
  "RADIOCITY": "5.81",
  "RAILTEL": "283.50",
  "RAIN": "118.86",
  "RAINBOW": "1203.90",
  "RAJMET": "3.63",
  "RAJOOENG": "60.18",
  "RAJRATAN": "389.10",
  "RAJSREESUG": "28.44",
  "RAJTV": "39.45",
  "RALLIS": "248.60",
  "RAMANEWS": "39.41",
  "RAMAPHO": "119.32",
  "RAMASTEEL": "5.97",
  "RAMCOCEM": "995.10",
  "RAMCOIND": "279.50",
  "RAMCOSYS": "419.40",
  "RAMKY": "458.50",
  "RAMRAT": "328.65",
  "RANASUG": "11.85",
  "RANEHOLDIN": "1191.60",
  "RATEGAIN": "510.90",
  "RATNAMANI": "2372.00",
  "RATNAVEER": "142.25",
  "RAYMOND": "378.30",
  "RAYMONDLSL": "798.85",
  "RAYMONDREL": "391.85",
  "RBA": "62.04",
  "RBLBANK": "297.70",
  "RBZJEWEL": "118.34",
  "RCF": "123.02",
  "REDINGTON": "247.30",
  "REDTAPE": "114.42",
  "REFEX": "210.08",
  "REGAAL": "73.08",
  "REGENCERAM": "43.75",
  "RELAXO": "304.65",
  "RELCHEMQ": "113.00",
  "RELIABLE": "119.96",
  "RELIGARE": "219.77",
  "RELTD": "138.64",
  "REMSONSIND": "107.82",
  "RENUKA": "24.67",
  "REPCOHOME": "364.05",
  "REPL": "75.51",
  "REPRO": "379.55",
  "RESPONIND": "165.48",
  "RETAIL": "21.11",
  "RGL": "103.23",
  "RHETAN": "24.77",
  "RHIM": "380.20",
  "RHL": "186.43",
  "RICOAUTO": "111.83",
  "RIIL": "687.30",
  "RISHABH": "393.75",
  "RITCO": "197.15",
  "RITES": "199.71",
  "RKDL": "18.62",
  "RKEC": "39.99",
  "RKFORGE": "554.90",
  "RKSWAMY": "97.28",
  "RMDRIP": "44.24",
  "RML": "820.60",
  "ROHLTD": "326.90",
  "ROLEXRINGS": "122.89",
  "ROML": "45.97",
  "ROSSARI": "462.20",
  "ROSSELLIND": "45.51",
  "ROSSTECH": "710.05",
  "ROTO": "60.97",
  "ROUTE": "481.70",
  "RPEL": "681.70",
  "RPGLIFE": "1901.10",
  "RPOWER": "22.86",
  "RPPINFRA": "71.40",
  "RPPL": "15.75",
  "RPSGVENT": "622.05",
  "RPTECH": "349.45",
  "RRKABEL": "1424.60",
  "RSSOFTWARE": "27.94",
  "RSWM": "145.34",
  "RSYSTEMS": "301.00",
  "RTNINDIA": "26.70",
  "RTNPOWER": "8.08",
  "RUBFILA": "63.75",
  "RUBICON": "781.55",
  "RUBYMILLS": "199.62",
  "RUCHINFRA": "5.56",
  "RUCHIRA": "104.63",
  "RUDRA": "17.28",
  "RUPA": "130.17",
  "RUSHIL": "16.55",
  "RUSTOMJEE": "403.15",
  "RVHL": "38.37",
  "RVNL": "277.20",
  "RVTH": "594.15",
  "SAATVIKGL": "347.05",
  "SADBHIN": "2.98",
  "SADHNANIQ": "1.54",
  "SAFARI": "1653.50",
  "SAGARDEEP": "23.21",
  "SAGCEM": "182.88",
  "SAGILITY": "39.79",
  "SAHYADRI": "239.00",
  "SAIL": "153.88",
  "SAILIFE": "1014.00",
  "SAKAR": "555.50",
  "SAKHTISUG": "15.18",
  "SAKSOFT": "131.59",
  "SAKUMA": "1.63",
  "SALASAR": "7.29",
  "SALONA": "275.70",
  "SALZERELEC": "600.70",
  "SAMBHAAV": "6.41",
  "SAMBHV": "91.45",
  "SAMHI": "150.84",
  "SAMMAANCAP": "145.72",
  "SAMPANN": "27.59",
  "SANATHAN": "417.25",
  "SANDESH": "952.40",
  "SANDHAR": "505.80",
  "SANDUMA": "200.86",
  "SANGAMIND": "428.15",
  "SANGHIIND": "54.83",
  "SANGHVIMOV": "240.00",
  "SANOFI": "3649.30",
  "SANOFICONR": "4443.20",
  "SANSERA": "2177.70",
  "SANSTAR": "82.94",
  "SAPPHIRE": "171.01",
  "SARDAEN": "544.35",
  "SAREGAMA": "329.30",
  "SARLAPOLY": "80.39",
  "SARVESHWAR": "3.27",
  "SASKEN": "1081.80",
  "SASTASUNDR": "282.50",
  "SATIA": "62.63",
  "SATIN": "149.70",
  "SAURASHCEM": "62.44",
  "SBC": "32.17",
  "SBCL": "433.30",
  "SBFC": "92.34",
  "SBGLP": "27.47",
  "SBIBPB": "51.09",
  "SBICARD": "715.00",
  "SBIETFCON": "112.57",
  "SBIETFIT": "327.03",
  "SBIETFPB": "269.82",
  "SBIETFQLTY": "211.76",
  "SBILIQETF": "1029.96",
  "SBIMIDMOM": "58.80",
  "SBINEQWETF": "31.87",
  "SBISILVER": "257.15",
  "SCHAEFFLER": "4050.40",
  "SCHAND": "149.75",
  "SCI": "240.05",
  "SCILAL": "44.37",
  "SCODATUBES": "124.09",
  "SDBL": "76.73",
  "SDL26BEES": "136.76",
  "SEAMECLTD": "1320.10",
  "SECMARK": "119.21",
  "SECURKLOUD": "22.51",
  "SEDEMAC": "1451.10",
  "SEJALLTD": "524.65",
  "SELECTIPO": "40.50",
  "SELMC": "31.20",
  "SEMAC": "219.99",
  "SENCO": "297.35",
  "SENORES": "741.95",
  "SENSEXADD": "78.73",
  "SENSEXBETA": "853.54",
  "SENSEXETF": "78.88",
  "SENSEXIETF": "879.14",
  "SEPC": "6.52",
  "SERVOTECH": "68.16",
  "SESHAPAPER": "249.25",
  "SETCO": "18.01",
  "SETF10GILT": "261.23",
  "SETFGOLD": "136.87",
  "SETFNIF50": "255.70",
  "SETFNIFBK": "571.53",
  "SETFNN50": "709.88",
  "SETL": "122.71",
  "SFL": "524.85",
  "SGFIN": "394.00",
  "SGIL": "499.65",
  "SGL": "11.33",
  "SGMART": "446.70",
  "SHADOWFAX": "112.30",
  "SHAH": "4.80",
  "SHAHALLOYS": "57.69",
  "SHAILY": "1908.50",
  "SHALBY": "146.94",
  "SHALPAINTS": "52.26",
  "SHANKARA": "106.64",
  "SHANTI": "6.32",
  "SHANTIGEAR": "465.45",
  "SHANTIGOLD": "198.96",
  "SHARDACROP": "1036.70",
  "SHARDAMOTR": "819.65",
  "SHAREINDIA": "134.35",
  "SHARIABEES": "460.31",
  "SHEKHAWATI": "12.35",
  "SHEMAROO": "100.72",
  "SHILCTECH": "3856.80",
  "SHILPAMED": "336.00",
  "SHIVALIK": "279.15",
  "SHIVAMAUTO": "16.89",
  "SHIVAMILLS": "53.71",
  "SHIVATEX": "146.82",
  "SHIVAUM": "275.00",
  "SHK": "130.80",
  "SHOPERSTOP": "304.80",
  "SHRADHA": "33.97",
  "SHREDIGCEM": "64.14",
  "SHREEJISPG": "369.85",
  "SHREEPUSHK": "318.10",
  "SHREERAMA": "48.74",
  "SHREYANIND": "150.31",
  "SHRINGARMS": "204.28",
  "SHRIPISTON": "3039.70",
  "SHRIRAMPPS": "72.94",
  "SHYAMCENT": "4.81",
  "SHYAMMETL": "785.55",
  "SHYAMTEL": "10.17",
  "SIGACHI": "19.45",
  "SIGIND": "45.67",
  "SIGMA": "40.57",
  "SIGMAADV": "154.75",
  "SIGNATURE": "842.45",
  "SIGNPOST": "230.05",
  "SIKKO": "4.78",
  "SIL": "13.95",
  "SILGO": "74.32",
  "SILINV": "416.40",
  "SILLYMONKS": "16.38",
  "SILVER": "262.63",
  "SILVER1": "25.59",
  "SILVER360": "258.18",
  "SILVERADD": "253.01",
  "SILVERAG": "256.37",
  "SILVERBETA": "253.19",
  "SILVERBND": "262.13",
  "SILVERCASE": "26.70",
  "SILVERIETF": "262.49",
  "SILVERTUC": "121.60",
  "SIMPLEXINF": "178.50",
  "SINCLAIR": "73.29",
  "SINDHUTRAD": "25.37",
  "SINTERCOM": "82.12",
  "SIRCA": "428.50",
  "SIS": "291.50",
  "SIYSIL": "497.60",
  "SJS": "1621.60",
  "SJVN": "70.53",
  "SKFINDIA": "1605.40",
  "SKFINDUS": "2213.20",
  "SKIPPER": "340.50",
  "SKMEGGPROD": "154.48",
  "SKYGOLD": "341.40",
  "SMALL250": "15.41",
  "SMALLADD": "15.45",
  "SMALLCAP": "40.54",
  "SMARTLINK": "117.62",
  "SMARTWORKS": "387.85",
  "SMCGLOBAL": "72.89",
  "SML100CASE": "9.29",
  "SMLMAH": "3973.70",
  "SMLT": "69.70",
  "SMSPHARMA": "413.40",
  "SNOWMAN": "36.29",
  "SNXT30BEES": "40.04",
  "SNXT50BETA": "87.06",
  "SOBHA": "1354.90",
  "SOFTTECH": "261.45",
  "SOLARA": "452.05",
  "SOLARWORLD": "165.97",
  "SOLEX": "879.35",
  "SOMANYCERA": "370.25",
  "SOMICONVEY": "99.90",
  "SONACOMS": "516.35",
  "SONAMLTD": "55.25",
  "SONATSOFTW": "244.80",
  "SOTL": "348.90",
  "SOUTHBANK": "39.43",
  "SOUTHWEST": "209.52",
  "SPAL": "692.60",
  "SPANDANA": "228.70",
  "SPARC": "125.55",
  "SPCENET": "3.91",
  "SPECIALITY": "100.13",
  "SPECTRUM": "1444.60",
  "SPENCERS": "31.49",
  "SPIC": "63.47",
  "SPLIL": "27.11",
  "SPLPETRO": "693.60",
  "SPMLINFRA": "182.71",
  "SPORTKING": "114.62",
  "SRD": "50.07",
  "SREEL": "192.66",
  "SRF": "2488.70",
  "SRGHFL": "257.00",
  "SRHHYPOLTD": "430.40",
  "SRM": "373.70",
  "SSDL": "60.53",
  "SSWL": "195.44",
  "STALLION": "109.53",
  "STANLEY": "162.44",
  "STAR": "893.95",
  "STARCEMENT": "201.95",
  "STARHEALTH": "455.90",
  "STARPAPER": "134.72",
  "STARTECK": "255.80",
  "STCINDIA": "109.10",
  "STEELCAS": "229.87",
  "STEELCITY": "81.64",
  "STEELXIND": "8.01",
  "STEL": "478.80",
  "STERTOOLS": "194.09",
  "STLNETWORK": "18.89",
  "STLTECH": "190.58",
  "STOVEKRAFT": "544.95",
  "STUDDS": "520.30",
  "STYL": "259.88",
  "STYLAMIND": "2212.30",
  "STYLEBAAZA": "275.10",
  "STYRENIX": "2038.00",
  "SUBEXLTD": "8.76",
  "SUBROS": "698.20",
  "SUDARCOLOR": "335.70",
  "SUDARSCHEM": "866.80",
  "SUDEEPPHRM": "618.90",
  "SUKHJITS": "178.02",
  "SULA": "162.09",
  "SUMEETINDS": "28.65",
  "SUMICHEM": "393.65",
  "SUMIT": "33.40",
  "SUMMITSEC": "1592.30",
  "SUNCLAY": "1285.10",
  "SUNDARAM": "1.26",
  "SUNDARMFIN": "5324.50",
  "SUNDRMBRAK": "566.15",
  "SUNDRMFAST": "836.45",
  "SUNDROP": "635.40",
  "SUNFLAG": "228.12",
  "SUNTECK": "342.35",
  "SUNTV": "578.00",
  "SUPERHOUSE": "144.85",
  "SUPERSPIN": "5.30",
  "SUPRAJIT": "420.00",
  "SUPREME": "55.14",
  "SUPREMEIND": "4038.00",
  "SUPRIYA": "596.55",
  "SURAJEST": "206.08",
  "SURAJLTD": "229.54",
  "SURAKSHA": "259.55",
  "SURANASOL": "20.80",
  "SURANAT&P": "17.05",
  "SURYALAXMI": "53.22",
  "SURYAROSNI": "212.12",
  "SURYODAY": "134.04",
  "SUTLEJTEX": "31.71",
  "SUVEN": "141.33",
  "SUVIDHAA": "2.84",
  "SUYOG": "687.40",
  "SUZLON": "41.62",
  "SVLL": "540.00",
  "SWANCORP": "353.20",
  "SWARAJENG": "3470.50",
  "SWELECTES": "516.35",
  "SWIGGY": "284.60",
  "SWSOLAR": "178.57",
  "SYMPHONY": "821.15",
  "SYNCOMF": "12.40",
  "SYNGENE": "408.15",
  "SYRMA": "757.50",
  "SYSTMTXC": "69.57",
  "TAINWALCHM": "199.12",
  "TAJGVK": "306.05",
  "TALBROAUTO": "242.15",
  "TANLA": "439.20",
  "TARACHAND": "59.80",
  "TARAPUR": "25.28",
  "TARC": "136.85",
  "TARIL": "289.40",
  "TARSONS": "195.37",
  "TASTYBITE": "7048.50",
  "TATACAP": "319.80",
  "TATACHEM": "688.80",
  "TATACOMM": "1482.90",
  "TATAELXSI": "4343.40",
  "TATAGOLD": "15.54",
  "TATAINVEST": "622.90",
  "TATATECH": "556.90",
  "TATSILV": "25.51",
  "TATVA": "1150.00",
  "TBOTEK": "1207.20",
  "TBZ": "133.46",
  "TCC": "401.35",
  "TCI": "1001.60",
  "TCIEXP": "503.40",
  "TCPLPACK": "2441.00",
  "TDPOWERSYS": "802.65",
  "TEAMGTY": "248.10",
  "TEAMLEASE": "1131.40",
  "TECH": "32.11",
  "TECHNOE": "1105.70",
  "TECILCHEM": "12.70",
  "TEGA": "1756.00",
  "TEMBO": "524.25",
  "TENNIND": "528.15",
  "TERASOFT": "352.95",
  "TEXINFRA": "92.67",
  "TEXMOPIPES": "44.47",
  "TEXRAIL": "96.92",
  "TFCILTD": "66.07",
  "TFL": "12.70",
  "TGBHOTELS": "8.95",
  "THANGAMAYL": "3540.40",
  "THEINVEST": "97.47",
  "THEJO": "1659.60",
  "THELEELA": "436.30",
  "THEMISMED": "82.17",
  "THERMAX": "3182.30",
  "THOMASCOOK": "93.07",
  "THOMASCOTT": "243.75",
  "THYROCARE": "370.15",
  "TI": "456.75",
  "TICL": "25.99",
  "TIGERLOGS": "27.76",
  "TIIL": "2078.10",
  "TIINDIA": "2566.00",
  "TIL": "194.98",
  "TIMETECHNO": "171.88",
  "TIMKEN": "3410.30",
  "TINNARUBR": "673.50",
  "TIPSFILMS": "337.75",
  "TIPSMUSIC": "516.05",
  "TIRUMALCHM": "177.74",
  "TIRUPATIFL": "41.48",
  "TITAGARH": "655.95",
  "TMB": "619.75",
  "TMCV": "445.45",
  "TNIDETF": "78.45",
  "TNPETRO": "84.78",
  "TNPL": "138.34",
  "TNTELE": "8.93",
  "TOKYOPLAST": "74.47",
  "TOLINS": "103.07",
  "TOP100CASE": "10.26",
  "TOP10ADD": "88.84",
  "TOP15IETF": "9.85",
  "TOP20": "8.71",
  "TORNTPOWER": "1439.00",
  "TOTAL": "60.28",
  "TOUCHWOOD": "71.98",
  "TPHQ": "0.53",
  "TPLPLASTEH": "61.98",
  "TRACXN": "32.15",
  "TRANSRAILL": "515.45",
  "TRANSWORLD": "134.83",
  "TRAVELFOOD": "1189.00",
  "TREJHARA": "165.98",
  "TREL": "23.09",
  "TRF": "237.35",
  "TRIDENT": "23.10",
  "TRIGYN": "48.24",
  "TRITURBINE": "474.60",
  "TRIVENI": "367.40",
  "TRU": "6.75",
  "TRUALT": "388.65",
  "TSFINV": "385.90",
  "TTKHLTCARE": "854.80",
  "TTKPRESTIG": "535.45",
  "TTML": "38.97",
  "TVSELECT": "382.95",
  "TVSHLTD": "14072.00",
  "TVSSRICHAK": "3574.90",
  "TVTODAY": "112.63",
  "TWCGOLDETF": "158.17",
  "UBL": "1653.30",
  "UCAL": "100.83",
  "UCOBANK": "26.40",
  "UDS": "148.12",
  "UEL": "159.18",
  "UFBL": "223.64",
  "UFLEX": "449.50",
  "UFO": "66.57",
  "UGARSUGAR": "37.45",
  "UGROCAP": "101.62",
  "UJJIVANSFB": "53.90",
  "UMAEXPORTS": "25.64",
  "UMESLTD": "4.99",
  "UMIYA-MRO": "80.02",
  "UNICHEMLAB": "331.10",
  "UNIDT": "177.03",
  "UNIECOM": "98.93",
  "UNIENTER": "97.56",
  "UNIINFO": "10.77",
  "UNIMECH": "856.95",
  "UNIONBANK": "180.92",
  "UNIONGOLD": "156.55",
  "UNIPARTS": "458.95",
  "UNITECH": "4.65",
  "UNITEDPOLY": "27.53",
  "UNITEDTEA": "506.45",
  "UNIVASTU": "64.52",
  "UNIVCABLES": "623.30",
  "UNOMINDA": "1081.70",
  "UPL": "625.85",
  "URAVIDEF": "133.57",
  "URBANCO": "111.31",
  "URJA": "9.01",
  "USHAMART": "425.10",
  "UTIAMC": "983.30",
  "UTKARSHBNK": "12.55",
  "UTLSOLAR": "188.21",
  "UTTAMSUGAR": "200.81",
  "UYFINCORP": "13.66",
  "V2RETAIL": "1967.40",
  "VADILALIND": "4995.40",
  "VAIBHAVGBL": "216.26",
  "VAISHALI": "6.50",
  "VAKRANGEE": "5.99",
  "VAL30IETF": "15.41",
  "VALIANTLAB": "56.33",
  "VALIANTORG": "215.58",
  "VARDHACRLC": "33.89",
  "VARROC": "494.35",
  "VASCONEQ": "34.23",
  "VASWANI": "54.02",
  "VCL": "1.68",
  "VEEDOL": "1337.40",
  "VENKEYS": "1292.80",
  "VENTIVE": "670.90",
  "VENUSPIPES": "1023.10",
  "VENUSREM": "861.70",
  "VERANDA": "155.49",
  "VERTOZ": "40.98",
  "VESUVIUS": "504.45",
  "VETO": "100.22",
  "VGL": "62.83",
  "VGUARD": "314.65",
  "VHL": "3115.90",
  "VIDHIING": "287.70",
  "VIDYAWIRES": "54.03",
  "VIJAYA": "962.10",
  "VIJIFIN": "2.51",
  "VIKASECO": "1.30",
  "VIKASLIFE": "1.33",
  "VIKRAMSOLR": "180.20",
  "VIKRAN": "62.56",
  "VIMTALABS": "442.10",
  "VINATIORGA": "1415.80",
  "VINCOFE": "129.91",
  "VINDHYATEL": "1177.60",
  "VINEETLAB": "30.31",
  "VINNY": "1.11",
  "VINYLINDIA": "199.71",
  "VIPCLOTHNG": "18.93",
  "VIPIND": "350.50",
  "VIRINCHI": "18.89",
  "VISAKAIND": "58.57",
  "VISASTEEL": "35.15",
  "VISHNU": "491.10",
  "VISHWARAJ": "5.33",
  "VITAL": "41.50",
  "VIVIDHA": "0.54",
  "VIVIMEDLAB": "7.16",
  "VIYASH": "195.32",
  "VLEGOV": "13.45",
  "VLSFINANCE": "235.30",
  "VMART": "535.95",
  "VMM": "108.02",
  "VMSTMT": "41.82",
  "VOLTAMP": "8528.00",
  "VOLTAS": "1471.40",
  "VPRPL": "40.77",
  "VRAJ": "118.03",
  "VRLLOG": "262.30",
  "VSSL": "240.95",
  "VSTIND": "222.53",
  "VSTL": "112.53",
  "VSTTILLERS": "5228.50",
  "VTL": "546.00",
  "WAAREEENER": "2682.80",
  "WAAREERTL": "821.05",
  "WABAG": "1251.90",
  "WAKEFIT": "172.02",
  "WALCHANNAG": "160.94",
  "WCIL": "98.28",
  "WEALTH": "961.55",
  "WEBELSOLAR": "56.36",
  "WEIZMANIND": "81.59",
  "WEL": "139.56",
  "WELCORP": "832.50",
  "WELENT": "480.75",
  "WELINV": "1272.30",
  "WELSPUNLIV": "118.68",
  "WENDT": "6547.00",
  "WESTLIFE": "477.20",
  "WEWIN": "41.89",
  "WEWORK": "469.65",
  "WHEELS": "918.35",
  "WHIRLPOOL": "891.45",
  "WILLAMAGOR": "26.77",
  "WINDLAS": "742.35",
  "WINDMACHIN": "243.45",
  "WIPL": "152.47",
  "WOCKPHARMA": "1305.40",
  "WONDERLA": "523.80",
  "WORTHPERI": "136.01",
  "WSI": "67.76",
  "WSTCSTPAPR": "401.25",
  "XCHANGING": "61.04",
  "XELPMOC": "116.91",
  "XPROINDIA": "859.30",
  "XTGLOBAL": "33.97",
  "YASHO": "1406.50",
  "YATHARTH": "699.15",
  "YATRA": "106.47",
  "YESBANK": "19.53",
  "YUKEN": "713.25",
  "ZAGGLE": "227.88",
  "ZEEL": "80.48",
  "ZEELEARN": "5.48",
  "ZENITHEXPO": "184.00",
  "ZENITHSTL": "5.68",
  "ZENSARTECH": "564.50",
  "ZENTEC": "1408.60",
  "ZFCVINDIA": "13984.00",
  "ZIMLAB": "67.65",
  "ZODIAC": "241.56",
  "ZODIACLOTH": "71.11",
  "ZOTA": "1180.10",
  "ZUARI": "209.32",
  "ZUARIIND": "252.50",
  "ZYDUSWELL": "384.30",
  "ABB": "6280.50",
  "BEL": "454.05",
  "DISAQ": "11868.90",
  "CIPLA": "1329.90",
  "CGPOWER": "726.85",
  "TITAN": "4139.20",
  "ELANTAS": "8315.90",
  "COCKERILL": "4862.75",
  "GOODYEAR": "778.75",
  "HINDZINC": "587.45",
  "JSWSTEEL": "1178.75",
  "KIRLFER": "378.95",
  "TRENT": "3624.25",
  "SPICEJET": "15.02",
  "GRASIM": "2738.75",
  "NIRLON": "491.90",
  "ONGC": "270.75",
  "PIDILITIND": "1403.85",
  "PUNJCOMMU": "51.52",
  "WELSPLSOL": "35.83",
  "SHREECEM": "23750.30",
  "TATAPOWER": "385.20",
  "TIMEX": "281.85",
  "TORNTPHARM": "4429.25",
  "AMBUJACEM": "457.65",
  "HINDALCO": "959.00",
  "HOCL": "28.52",
  "TATASTEEL": "194.70",
  "BAJAJHLDNG": "10173.30",
  "HINDMOTORS": "14.47",
  "BOSCHLTD": "31693.25",
  "BPCL": "325.25",
  "SIEMENS": "3272.10",
  "TMPV": "335.35",
  "NOVARTIND": "951.55",
  "HINDUNILVR": "2161.75",
  "NESTLEIND": "1233.35",
  "TATACONSUM": "1073.25",
  "ASIANPAINT": "2231.60",
  "BRITANNIA": "5920.00",
  "INDHOTEL": "623.85",
  "ITC": "308.95",
  "INDPRUD": "5207.60",
  "ELCIDIN": "98602.15",
  "ELPROINTL": "85.46",
  "NATIONSTD": "1285.90",
  "ACGL": "1640.05",
  "ZFSTEERING": "690.10",
  "GRAUWEIL": "62.92",
  "HERCULES": "119.45",
  "WPIL": "395.40",
  "KENNAMET": "2255.55",
  "CITURGIA": "131.30",
  "AGVENTURES": "106.05",
  "ULTRAMAR": "415.20",
  "TANFACIND": "1915.25",
  "WIPRO": "202.10",
  "TGVSL": "83.08",
  "BAJAJST": "397.90",
  "HAWKINCOOK": "7540.80",
  "ISTLTD": "659.65",
  "APOLLOHOSP": "7688.10",
  "BENARAS": "9501.00",
  "KOTIC": "177.05",
  "CHOLAFIN": "1557.30",
  "ZSARACOM": "10071.30",
  "DECNGOLD": "104.25",
  "MMWL": "10.06",
  "ADANIENT": "1975.30",
  "GUJTLRM": "0.57",
  "BPAGRI": "42.04",
  "JYOTIRES": "813.85",
  "WINSOMTX": "71.33",
  "SEKURITIND": "95.71",
  "RIR": "162.55",
  "MOTHERSON": "121.20",
  "HAVELLS": "1367.20",
  "MARSONS": "134.50",
  "BGDL": "90.13",
  "KLBRENG-B": "505.80",
  "FRONTSP": "4607.75",
  "GVTD": "3783.60",
  "CROPSTER": "6.97",
  "KOVAI": "5315.50",
  "INDBNK": "42.10",
  "LOTUSCHO": "753.65",
  "SIKA": "1020.50",
  "GRANDOAK": "31.00",
  "KMCSHIL": "84.10",
  "BIBCL": "16.89",
  "BNAGROCHEM": "236.35",
  "ANDREWYU": "19.13",
  "ASMTEC": "2324.65",
  "DRAGARWQ": "4801.30",
  "ECORECO": "326.40",
  "IOC": "160.70",
  "MERCURYEV": "32.03",
  "ARIHANT": "1063.65",
  "PRAVEG": "229.50",
  "ASTAR": "598.00",
  "ORIRAIL": "117.95",
  "3BBLACKBIO": "1253.15",
  "BANKBARODA": "289.35",
  "GAIL": "147.95",
  "GUJSTATFIN": "10.69",
  "HCLTECH": "1350.05",
  "JINDALSTEL": "1186.90",
  "ZYDUSLIFE": "922.00",
  "TVSMOTOR": "3600.05",
  "GODREJCP": "1089.65",
  "UNITDSPR": "1380.30",
  "PNB": "115.80",
  "HAZOOR": "29.09",
  "KAMAHOLD": "2501.55",
  "CANBK": "139.30",
  "BLIL": "72.37",
  "DIVISLAB": "6349.15",
  "MARUTI": "13502.40",
  "ULTRACEMCO": "11457.10",
  "TCS": "2465.15",
  "SOLARINDS": "14513.60",
  "TECHM": "1333.95",
  "NAUKRI": "957.40",
  "PFC": "406.80",
  "DLF": "572.95",
  "POWERGRID": "298.80",
  "ADANIPORTS": "1410.70",
  "RECLTD": "332.70",
  "BAJAJ-AUTO": "9330.95",
  "SENSEX1": "84.07",
  "BENGALASM": "5901.95",
  "ADANIPOWER": "138.85",
  "JSWENERGY": "487.70",
  "SBISENSEX": "857.27",
  "GCMSECU": "0.64",
  "MMLF": "0.69",
  "ALSL": "54.93",
  "BRPL": "110.90",
  "VISHAL": "19.45",
  "MIIL": "537.50",
  "SENSEXBEES": "880.87",
  "ARYACAPM": "423.95",
  "CAPPIPES": "9.27",
  "SETFBSE100": "277.34",
  "URSUGAR": "2.37",
  "GROWINGTON": "0.96",
  "ADANIENSOL": "992.00",
  "UNIAUTO": "54.55",
  "VISHALBL": "55.57",
  "NAKSH": "4.80",
  "PANORAMA": "44.13",
  "LICNETFSEN": "868.53",
  "ELITECON": "54.84",
  "BLUECLOUDS": "19.70",
  "KAMATS": "50.20",
  "RELICAB": "33.57",
  "KPL": "1662.90",
  "LTM": "4262.75",
  "SPRAYKING": "1.49",
  "VBL": "431.10",
  "VSL": "9.30",
  "DMART": "3936.90",
  "IFL": "0.40",
  "CHEMCRUX": "87.62",
  "PRIMEFRESH": "239.65",
  "ESCORP": "109.90",
  "MEERA": "32.50",
  "ANG": "23.34",
  "ICICIGI": "1877.75",
  "PQIF": "18.02",
  "SBILIFE": "1936.80",
  "TTFL": "52.44",
  "POOJA": "24.34",
  "STL": "7.15",
  "HDFCLIFE": "647.75",
  "SHARIKA": "10.64",
  "MRCAGRO": "41.68",
  "GGL": "3.12",
  "KENVI": "2.37",
  "ACTIVE": "94.00",
  "HAL": "4005.35",
  "TRL": "97.25",
  "UHZAVERI": "12.41",
  "PALMJEWELS": "16.74",
  "ADANIGREEN": "849.80",
  "RAJNISH": "0.48",
  "RAWEDGE": "15.39",
  "DEEP": "32.03",
  "ASRL": "6.97",
  "SETFSN50": "872.01",
  "A1L": "22.41",
  "DOLFIN": "178.40",
  "SHUBHAM": "56.13",
  "SMGOLD": "12.26",
  "BCPL": "60.45",
  "DECCAN": "12.92",
  "KRANTI": "58.00",
  "AGOL": "4.42",
  "NSL": "115.50",
  "VRFILMS": "12.00",
  "GKP": "5.82",
  "BMW": "33.47",
  "ARL": "78.90",
  "SNXT50BEES": "85.25",
  "ALPHALOGIC": "37.42",
  "GALACTICO": "1.74",
  "ANUROOP": "11.58",
  "08MPD": "5.75",
  "08GPG": "2.65",
  "08AGG": "30.98",
  "ROJL": "1.39",
  "11DPR": "14.58",
  "11GPG": "2.41",
  "11MPD": "3.91",
  "11MPR": "55.12",
  "11QPD": "7.55",
  "11QPR": "28.82",
  "11AGG": "28.87",
  "11AMD": "41.48",
  "11AQD": "39.43",
  "11DPD": "5.52",
  "MAXHEALTH": "1031.75",
  "MAZDOCK": "2436.75",
  "IRFC": "99.30",
  "EKI": "83.21",
  "LODHA": "878.55",
  "ETERNAL": "223.80",
  "SAMOR": "67.50",
  "ACHYUT": "5.14",
  "LICI": "802.40",
  "ASHIKA": "361.05",
  "BAJAJHFL": "83.73",
  "HYUNDAI": "2020.35",
  "ENRIN": "2943.85",
  "NSDL": "876.60",
  "SSFLPP": "119.90",
  "ATLPP": "9.69",
  "KRISHPP": "106.80"
}