{
  "Bhavdate": "20-Apr-2026",
  "HDFCBANK": "799.90",
  "TRITURBINE": "576.20",
  "SBIN": "1107.85",
  "ICICIBANK": "1346.80",
  "RELIANCE": "1365.00",
  "BHARTIARTL": "1846.90",
  "ADANIPOWER": "198.50",
  "BHEL": "325.63",
  "GROWW": "196.11",
  "SWSOLAR": "212.08",
  "LT": "4096.10",
  "SCI": "299.96",
  "ATHERENERG": "889.45",
  "BSE": "3470.70",
  "LIQUIDBEES": "999.99",
  "APOLLO": "289.29",
  "M&M": "3200.20",
  "ETERNAL": "252.61",
  "INFY": "1318.70",
  "TRENT": "4242.80",
  "JIOFIN": "237.15",
  "ADANIGREEN": "1127.30",
  "GRAPHITE": "711.75",
  "VEDL": "787.50",
  "SUZLON": "52.50",
  "JSWSTEEL": "1274.50",
  "ASIANPAINT": "2516.80",
  "GRASIM": "2760.10",
  "HINDALCO": "1015.25",
  "TMPV": "355.70",
  "KOTAKBANK": "379.20",
  "BEL": "457.55",
  "20MICRONS": "177.22",
  "21STCENMGM": "33.05",
  "360ONE": "1109.25",
  "3BBLACKBIO": "1301.90",
  "3IINFOLTD": "17.65",
  "3MINDIA": "31480.00",
  "3PLAND": "34.71",
  "5PAISA": "318.99",
  "63MOONS": "700.45",
  "AAATECH": "103.25",
  "AADHARHFC": "480.55",
  "AAREYDRUGS": "84.94",
  "AARNAV": "24.10",
  "AARON": "139.43",
  "AARTECH": "51.68",
  "AARTIDRUGS": "365.20",
  "AARTIIND": "445.65",
  "AARTIPHARM": "676.15",
  "AARTISURF": "394.90",
  "AARVI": "131.98",
  "AAVAS": "1355.80",
  "ABANSENT": "26.50",
  "ABBOTINDIA": "25550.00",
  "ABCAPITAL": "341.60",
  "ABCOTS": "401.40",
  "ABDL": "573.40",
  "ABFRL": "64.78",
  "ABGSEC": "111.83",
  "ABINFRA": "16.24",
  "ABLBL": "104.73",
  "ABMKNO": "252.00",
  "ABREL": "1403.60",
  "ABSL10BANK": "168.41",
  "ABSLAMC": "1066.70",
  "ABSLBANETF": "57.65",
  "ABSLLIQUID": "999.99",
  "ABSLMSCIN": "29.26",
  "ABSLNN50ET": "73.72",
  "ABSLPSE": "11.03",
  "ACC": "1428.80",
  "ACCELYA": "1196.20",
  "ACE": "904.55",
  "ACEINTEG": "18.26",
  "ACI": "599.55",
  "ACL": "56.60",
  "ACMESOLAR": "299.05",
  "ACSTECH": "40.00",
  "ACUTAAS": "2410.70",
  "ADFFOODS": "220.62",
  "ADL": "75.89",
  "ADOR": "1037.90",
  "ADROITINFO": "9.66",
  "ADSL": "118.40",
  "ADVAIT": "1862.10",
  "ADVANCE": "107.59",
  "ADVANIHOTR": "54.53",
  "ADVENTHTL": "160.23",
  "ADVENZYMES": "298.85",
  "AEGISLOG": "740.50",
  "AEGISVOPAK": "197.17",
  "AEQUS": "194.59",
  "AEROENTER": "87.27",
  "AEROFLEX": "300.89",
  "AERONEU": "83.05",
  "AETHER": "1185.40",
  "AFCONS": "334.30",
  "AFFLE": "1444.90",
  "AFSL": "202.99",
  "AGARIND": "445.15",
  "AGARWALEYE": "450.85",
  "AGI": "570.40",
  "AGIIL": "372.05",
  "AGRITECH": "118.83",
  "AGROPHOS": "32.28",
  "AHCL": "144.82",
  "AHLADA": "47.30",
  "AHLEAST": "160.13",
  "AHLUCONT": "833.30",
  "AHLWEST": "223.10",
  "AIAENG": "4001.20",
  "AIIL": "466.50",
  "AIRAN": "17.20",
  "AIROLAM": "86.97",
  "AJANTPHARM": "2781.30",
  "AJAXENGG": "497.50",
  "AJMERA": "120.18",
  "AJOONI": "4.26",
  "AKASH": "27.07",
  "AKCAPIT": "1549.20",
  "AKG": "11.80",
  "AKI": "5.10",
  "AKSHAR": "0.50",
  "AKSHARCHEM": "208.82",
  "AKUMS": "533.30",
  "ALANKIT": "9.34",
  "ALBERTDAVD": "714.95",
  "ALEMBICLTD": "90.22",
  "ALGOQUANT": "55.00",
  "ALICON": "701.90",
  "ALIVUS": "1068.05",
  "ALKALI": "65.70",
  "ALKEM": "5642.00",
  "ALKYLAMINE": "1407.60",
  "ALLCARGO": "9.57",
  "ALLDIGI": "853.60",
  "ALLTIME": "212.83",
  "ALMONDZ": "16.59",
  "ALOKINDS": "13.74",
  "ALPA": "67.06",
  "ALPHA": "48.95",
  "ALPHAETF": "25.41",
  "ALPHAGEO": "220.37",
  "ALPL30IETF": "26.73",
  "AMAGI": "367.45",
  "AMANTA": "135.00",
  "AMBALALSA": "32.45",
  "AMBER": "7980.50",
  "AMBICAAGAR": "23.60",
  "AMBIKCO": "1428.20",
  "AMDIND": "45.05",
  "AMIRCHAND": "134.01",
  "AMJLAND": "42.98",
  "AMNPLST": "161.71",
  "AMRUTANJAN": "544.35",
  "ANANDRATHI": "3663.90",
  "ANANTRAJ": "506.80",
  "ANDHRAPAP": "66.86",
  "ANDHRSUGAR": "89.77",
  "ANGELONE": "319.16",
  "ANMOL": "12.13",
  "ANTELOPUS": "612.30",
  "ANTGRAPHIC": "0.84",
  "ANTHEM": "724.20",
  "ANUHPHR": "81.34",
  "ANUP": "2028.30",
  "ANURAS": "1309.00",
  "AONEGOLD": "14.11",
  "AONELIQUID": "1055.92",
  "AONENIFTY": "10.00",
  "AONESILVER": "9.47",
  "AONETMMQ50": "10.02",
  "AONETOTAL": "11.54",
  "APARINDS": "11977.00",
  "APCL": "115.96",
  "APCOTEXIND": "391.50",
  "APEX": "484.95",
  "APLAPOLLO": "2143.90",
  "APLLTD": "757.50",
  "APOLLOPIPE": "457.35",
  "APOLLOTYRE": "441.40",
  "APOLSINHOT": "1149.80",
  "APTECHT": "99.45",
  "APTUS": "245.07",
  "AQYLON": "47.28",
  "ARCHIDPLY": "75.90",
  "ARCHIES": "14.64",
  "ARE&M": "765.25",
  "ARENTERP": "41.98",
  "ARFIN": "96.42",
  "ARIES": "381.65",
  "ARIHANT": "907.55",
  "ARIHANTCAP": "70.80",
  "ARIHANTSUP": "267.42",
  "ARIS": "127.87",
  "ARKADE": "114.01",
  "ARMANFIN": "1513.70",
  "AROGRANITE": "27.34",
  "ARROWGREEN": "544.15",
  "ARSSBL": "576.00",
  "ARTEMISMED": "229.62",
  "ARVEE": "164.00",
  "ARVIND": "385.20",
  "ARVINDFASN": "466.30",
  "ARVSMART": "594.95",
  "ASAHIINDIA": "843.70",
  "ASAHISONG": "240.35",
  "ASAL": "469.90",
  "ASALCBR": "884.70",
  "ASHAPURMIN": "599.95",
  "ASHIANA": "331.80",
  "ASHIKA": "382.25",
  "ASHIMASYN": "14.56",
  "ASHOKA": "134.16",
  "ASHOKAMET": "16.01",
  "ASHOKLEY": "175.96",
  "ASIANENE": "315.38",
  "ASIANHOTNR": "296.65",
  "ASIANTILES": "77.37",
  "ASKAUTOLTD": "438.25",
  "ASMS": "8.74",
  "ASPINWALL": "225.09",
  "ASTAR": "625.00",
  "ASTEC": "706.50",
  "ASTERDM": "679.50",
  "ASTRAL": "1591.40",
  "ASTRAMICRO": "1064.55",
  "ASTRAZEN": "8531.50",
  "ATALREAL": "25.09",
  "ATAM": "68.95",
  "ATGL": "620.35",
  "ATL": "25.61",
  "ATLANTAA": "41.06",
  "ATLANTAELE": "1385.90",
  "ATLASCYCLE": "107.39",
  "ATUL": "6536.00",
  "ATULAUTO": "460.15",
  "AUBANK": "997.65",
  "AURIGROW": "0.34",
  "AURIONPRO": "899.15",
  "AUROPHARMA": "1367.80",
  "AURUM": "180.94",
  "AUTOAXLES": "1787.50",
  "AUTOBEES": "271.86",
  "AUTOIETF": "27.27",
  "AUTOIND": "67.01",
  "AVADHSUGAR": "490.30",
  "AVAILFC": "153.65",
  "AVALON": "1076.90",
  "AVANTEL": "157.12",
  "AVANTIFEED": "1503.40",
  "AVG": "159.85",
  "AVL": "512.10",
  "AVONMORE": "12.28",
  "AVROIND": "125.20",
  "AVTNPL": "65.27",
  "AWFIS": "347.12",
  "AWHCL": "526.30",
  "AWL": "184.62",
  "AXISBNKETF": "581.81",
  "AXISBPSETF": "13.30",
  "AXISCADES": "1855.40",
  "AXISCETF": "117.54",
  "AXISGOLD": "125.98",
  "AXISHCETF": "147.21",
  "AXISILVER": "246.73",
  "AXISNIFTY": "267.73",
  "AXISTECETF": "345.85",
  "AXISVALUE": "33.93",
  "AXITA": "9.06",
  "AXSENSEX": "81.33",
  "AYE": "123.93",
  "AYMSYNTEX": "201.34",
  "AZAD": "1893.30",
  "BAGFILMS": "5.39",
  "BAIDFIN": "11.13",
  "BAJAJCON": "474.30",
  "BAJAJELEC": "397.35",
  "BAJAJHCARE": "333.80",
  "BAJAJHFL": "89.53",
  "BAJAJHIND": "18.25",
  "BAJAJINDEF": "285.15",
  "BAJAJST": "483.95",
  "BAJEL": "179.71",
  "BALAJEE": "33.23",
  "BALAJITELE": "93.62",
  "BALAMINES": "1149.75",
  "BALAXI": "26.67",
  "BALKRISHNA": "17.65",
  "BALKRISIND": "2282.00",
  "BALMLAWRIE": "177.06",
  "BALPHARMA": "77.69",
  "BALRAMCHIN": "515.70",
  "BALUFORGE": "471.15",
  "BANARBEADS": "114.51",
  "BANARISUG": "3627.30",
  "BANCOINDIA": "613.35",
  "BANDHANBNK": "175.43",
  "BANG": "37.89",
  "BANK10ADD": "16.81",
  "BANKADD": "57.61",
  "BANKBEES": "582.73",
  "BANKBETA": "58.24",
  "BANKBETF": "57.20",
  "BANKETF": "573.99",
  "BANKIETF": "57.73",
  "BANKINDIA": "148.31",
  "BANKNIFTY1": "58.46",
  "BANKPSU": "89.57",
  "BANSALWIRE": "309.03",
  "BANSWRAS": "113.00",
  "BASF": "3651.00",
  "BASML": "23.19",
  "BATAINDIA": "757.75",
  "BATLIBOI": "81.85",
  "BAYERCROP": "4853.30",
  "BBETF0432": "1316.04",
  "BBL": "2827.10",
  "BBNPNBETF": "56.76",
  "BBNPPGOLD": "146.20",
  "BBOX": "526.55",
  "BBTC": "1510.90",
  "BBTCL": "201.00",
  "BCLIND": "32.70",
  "BCONCEPTS": "247.12",
  "BCPL": "67.78",
  "BDL": "1369.80",
  "BEARDSELL": "27.10",
  "BECTORFOOD": "192.75",
  "BEEKAY": "424.30",
  "BELLACASA": "268.62",
  "BELRISE": "222.18",
  "BEML": "1744.20",
  "BENGALASM": "5880.45",
  "BEPL": "100.27",
  "BERGEPAINT": "483.95",
  "BETA": "1333.80",
  "BFINVEST": "406.55",
  "BFSI": "27.41",
  "BHAGCHEM": "236.26",
  "BHAGERIA": "160.50",
  "BHAGYANGR": "214.79",
  "BHANDARI": "3.22",
  "BHARATCOAL": "35.84",
  "BHARATFORG": "1866.20",
  "BHARATGEAR": "108.05",
  "BHARATRAS": "1542.10",
  "BHARATSE": "180.19",
  "BHARATWIRE": "232.15",
  "BHARTIHEXA": "1533.60",
  "BI": "63.70",
  "BIGBLOC": "50.75",
  "BIKAJI": "654.10",
  "BIL": "776.80",
  "BIMETAL": "600.00",
  "BIOCON": "359.05",
  "BIOFILCHEM": "34.30",
  "BIRLACABLE": "150.70",
  "BIRLACORPN": "959.85",
  "BIRLAMONEY": "150.81",
  "BIRLANU": "1435.10",
  "BIRLAPREC": "35.05",
  "BLACKBUCK": "617.90",
  "BLACKROSE": "83.25",
  "BLAL": "192.69",
  "BLIL": "73.15",
  "BLISSGVS": "253.64",
  "BLKASHYAP": "55.09",
  "BLS": "292.52",
  "BLSE": "172.93",
  "BLUECOAST": "25.72",
  "BLUEDART": "5502.90",
  "BLUEJET": "412.35",
  "BLUESTARCO": "1889.00",
  "BLUESTONE": "536.35",
  "BLUSPRING": "64.73",
  "BMWVENTLTD": "59.18",
  "BNAGROCHEM": "244.40",
  "BNALTD": "420.00",
  "BODALCHEM": "67.58",
  "BOMDYEING": "110.68",
  "BONLON": "48.25",
  "BOROLTD": "254.90",
  "BORORENEW": "492.40",
  "BOROSCI": "116.22",
  "BOSCH-HCIL": "1346.10",
  "BPL": "53.87",
  "BRIGADE": "775.70",
  "BRIGHOTEL": "67.57",
  "BRNL": "20.99",
  "BSE500IETF": "38.54",
  "BSHSL": "99.93",
  "BSL": "125.13",
  "BSLGOLDETF": "132.78",
  "BSLNIFTY": "28.37",
  "BSLSENETFG": "78.65",
  "BSOFT": "381.60",
  "BTML": "6.39",
  "BTTL": "36.70",
  "BUILDPRO": "1185.45",
  "BUTTERFLY": "619.10",
  "BVCL": "42.49",
  "CALSOFT": "12.40",
  "CAMLINFINE": "103.89",
  "CAMPUS": "253.22",
  "CAMS": "749.25",
  "CANFINHOME": "870.60",
  "CANHLIFE": "150.56",
  "CANTABIL": "247.04",
  "CAPACITE": "253.10",
  "CAPILLARY": "563.15",
  "CAPITALSFB": "256.27",
  "CAPLIPOINT": "1754.20",
  "CARBORUNIV": "941.15",
  "CARERATING": "1632.00",
  "CARRARO": "577.60",
  "CARTRADE": "1770.40",
  "CARYSIL": "863.40",
  "CASHIETF": "1058.51",
  "CASTROLIND": "182.17",
  "CCAVENUE": "14.78",
  "CCCL": "17.49",
  "CCHHL": "14.34",
  "CCL": "1085.90",
  "CDSL": "1370.30",
  "CEATLTD": "3799.40",
  "CEIGALL": "308.35",
  "CEINSYS": "1176.80",
  "CELEBRITY": "7.99",
  "CELLO": "424.25",
  "CEMPRO": "637.55",
  "CENTENKA": "433.65",
  "CENTEXT": "21.30",
  "CENTRALBK": "35.73",
  "CENTRUM": "25.02",
  "CENTUM": "2881.80",
  "CENTURYPLY": "743.55",
  "CERA": "5306.40",
  "CESC": "179.42",
  "CEWATER": "326.20",
  "CGCL": "185.00",
  "CHALET": "787.50",
  "CHAMBLFERT": "450.75",
  "CHEMBOND": "150.28",
  "CHEMBONDCH": "150.91",
  "CHEMCON": "159.36",
  "CHEMFAB": "396.55",
  "CHEMICAL": "27.70",
  "CHEMPLASTS": "226.75",
  "CHENNPETRO": "1007.55",
  "CHEVIOT": "1105.85",
  "CHOICEGOLD": "149.97",
  "CHOICEIN": "722.65",
  "CHOLAHLDNG": "1608.80",
  "CIEINDIA": "486.10",
  "CIFL": "29.47",
  "CIGNITITEC": "1263.30",
  "CINELINE": "85.51",
  "CINEVISTA": "15.19",
  "CLEAN": "742.70",
  "CLEANMAX": "1015.45",
  "CLSEL": "281.47",
  "CMPDI": "188.99",
  "CMSINFO": "317.90",
  "CNL": "591.25",
  "COASTCORP": "51.05",
  "COCHINSHIP": "1544.90",
  "COCKERILL": "5204.60",
  "COFFEEDAY": "27.46",
  "COFORGE": "1288.10",
  "COHANCE": "369.20",
  "COLPAL": "2129.00",
  "COMFINTE": "7.45",
  "COMMOIETF": "102.82",
  "COMPUSOFT": "14.34",
  "COMSYN": "160.20",
  "CONCOR": "501.05",
  "CONCORDBIO": "1066.40",
  "CONFIPET": "55.60",
  "CONS": "11.74",
  "CONSUMBEES": "126.83",
  "CONSUMER": "11.13",
  "CONSUMIETF": "117.61",
  "CONTROLPR": "658.85",
  "CORALFINAC": "35.11",
  "CORDSCABLE": "174.34",
  "COROMANDEL": "2074.90",
  "CORONA": "1698.30",
  "COSMOFIRST": "660.30",
  "COUNCODOS": "5.55",
  "CPCAP": "97.11",
  "CPEDU": "194.82",
  "CPPLUS": "2273.80",
  "CPSEETF": "106.93",
  "CRAFTSMAN": "7721.50",
  "CRAMC": "277.29",
  "CREATIVEYE": "7.22",
  "CREDITACC": "1253.80",
  "CREST": "361.80",
  "CRISIL": "4335.30",
  "CRIZAC": "228.64",
  "CROMPTON": "261.22",
  "CROWN": "127.36",
  "CSBBANK": "390.40",
  "CSLFINANCE": "237.84",
  "CUB": "265.75",
  "CUBEXTUB": "91.86",
  "CUPID": "105.42",
  "CYBERMEDIA": "18.88",
  "CYBERTECH": "130.13",
  "CYIENT": "948.05",
  "CYIENTDLM": "345.80",
  "DABUR": "441.70",
  "DAICHI": "263.40",
  "DALBHARAT": "1981.80",
  "DALMIASUG": "390.55",
  "DAMCAPITAL": "157.48",
  "DAMODARIND": "27.72",
  "DANGEE": "3.64",
  "DATAMATICS": "727.45",
  "DATAPATTNS": "3467.60",
  "DAVANGERE": "3.68",
  "DBCORP": "212.83",
  "DBEIL": "74.64",
  "DBL": "449.45",
  "DBREALTY": "106.49",
  "DBSTOCKBRO": "27.97",
  "DCAL": "167.48",
  "DCBBANK": "193.48",
  "DCM": "71.41",
  "DCMNVL": "119.75",
  "DCMSHRIRAM": "1199.60",
  "DCMSRIND": "39.46",
  "DCW": "46.30",
  "DCXINDIA": "188.23",
  "DDEVPLSTIK": "237.73",
  "DECCANCE": "667.50",
  "DECNGOLD": "120.20",
  "DEEDEV": "388.50",
  "DEEPAKFERT": "1229.05",
  "DEEPAKNTR": "1535.40",
  "DEEPINDS": "476.80",
  "DEFENCE": "72.06",
  "DELHIVERY": "464.50",
  "DELPHIFX": "13.03",
  "DELTACORP": "61.60",
  "DELTAMAGNT": "61.85",
  "DEN": "28.72",
  "DENORA": "810.05",
  "DENTA": "303.11",
  "DEVIT": "30.53",
  "DEVX": "40.82",
  "DEVYANI": "106.70",
  "DGCONTENT": "29.97",
  "DHAMPURSUG": "142.69",
  "DHANBANK": "27.83",
  "DHANUKA": "1016.60",
  "DHARMAJ": "276.31",
  "DHRUV": "36.35",
  "DHUNINV": "929.25",
  "DIACABS": "160.76",
  "DIAMINESQ": "255.59",
  "DIAMONDYD": "992.90",
  "DICIND": "546.10",
  "DIFFNKG": "309.57",
  "DIGIDRIVE": "23.86",
  "DIGISPICE": "18.94",
  "DIGITIDE": "94.81",
  "DIGJAMLMTD": "47.61",
  "DISAQ": "12055.30",
  "DISHTV": "3.88",
  "DIVGIITTS": "755.45",
  "DIVIDEND": "37.05",
  "DIVOPPBEES": "81.59",
  "DIXON": "11211.00",
  "DLINKINDIA": "454.60",
  "DMCC": "283.33",
  "DNAMEDIA": "3.20",
  "DODLA": "1069.25",
  "DOLATALGO": "78.96",
  "DOLLAR": "276.57",
  "DOLPHIN": "402.40",
  "DOMS": "2364.80",
  "DONEAR": "92.29",
  "DPABHUSHAN": "1107.60",
  "DPSCLTD": "9.95",
  "DPWIRES": "188.52",
  "DRAGARWQ": "4787.85",
  "DRCSYSTEMS": "16.83",
  "DREAMFOLKS": "83.18",
  "DREDGECORP": "1003.55",
  "DSFCL": "26.37",
  "DSSL": "1046.10",
  "DTIL": "146.09",
  "DVL": "247.69",
  "DWARKESH": "46.92",
  "DYCL": "349.18",
  "DYNAMATECH": "10140.00",
  "DYNPRO": "243.58",
  "EASEMYTRIP": "7.74",
  "EBANKNIFTY": "57.04",
  "EBBETF0430": "1572.97",
  "EBBETF0431": "1401.96",
  "EBBETF0433": "1279.70",
  "EBGNG": "412.10",
  "ECAPINSURE": "24.47",
  "ECLERX": "1619.80",
  "ECOSMOBLTY": "146.86",
  "EDELWEISS": "117.35",
  "EFCIL": "197.08",
  "EGOLD": "151.20",
  "EIDPARRY": "850.80",
  "EIEL": "206.24",
  "EIFFL": "242.94",
  "EIHAHOTELS": "328.30",
  "EIHOTEL": "332.50",
  "EIMCOELECO": "1642.40",
  "EKC": "118.41",
  "ELANTAS": "9255.00",
  "ELCIDIN": "133779.50",
  "ELDEHSG": "842.55",
  "ELECON": "435.55",
  "ELECTCAST": "78.36",
  "ELECTHERM": "756.85",
  "ELGIEQUIP": "551.95",
  "ELGIRUBCO": "55.71",
  "ELIN": "115.66",
  "ELIQUID": "1027.34",
  "ELITECON": "45.60",
  "ELLEN": "254.50",
  "ELM250": "16.28",
  "ELPROINTL": "102.50",
  "EMAMILTD": "445.20",
  "EMAMIPAP": "74.15",
  "EMAMIREAL": "67.03",
  "EMCURE": "1632.60",
  "EMIL": "105.26",
  "EMKAY": "231.69",
  "EMMBI": "86.79",
  "EMMVEE": "261.19",
  "EMPOWER": "1.40",
  "EMSLIMITED": "371.10",
  "EMUDHRA": "501.10",
  "EMULTIMQ": "41.96",
  "ENDURANCE": "2358.10",
  "ENERGY": "39.41",
  "ENERGYDEV": "17.11",
  "ENGINERSIN": "242.06",
  "ENIFTY": "24.40",
  "ENIL": "119.09",
  "ENTERO": "1271.90",
  "EPACK": "248.63",
  "EPACKPEB": "193.10",
  "EPIGRAL": "1167.40",
  "EPL": "236.24",
  "EQUAL200": "13.36",
  "EQUAL50": "327.51",
  "EQUAL50ADD": "337.47",
  "EQUITASBNK": "63.92",
  "ERIS": "1432.40",
  "ESABINDIA": "5791.50",
  "ESAFSFB": "23.89",
  "ESCORTS": "3316.00",
  "ESENSEX": "78.62",
  "ESG": "41.71",
  "ESILVER": "246.64",
  "ESSARSHPNG": "27.16",
  "ESSENTIA": "1.38",
  "ESTER": "91.26",
  "ETHOSLTD": "2345.20",
  "EUREKAFORB": "502.70",
  "EUROBOND": "175.53",
  "EUROPRATIK": "257.93",
  "EUROTEXIND": "13.88",
  "EVEREADY": "304.40",
  "EVERESTIND": "404.65",
  "EVIETF": "29.82",
  "EVINDIA": "29.81",
  "EXCELINDUS": "953.35",
  "EXCELSOFT": "91.75",
  "EXICOM": "113.14",
  "EXIDEIND": "329.70",
  "EXPLEOSOL": "828.35",
  "EXXARO": "7.03",
  "FABTECH": "157.45",
  "FACT": "891.05",
  "FAIRCHEMOR": "559.75",
  "FCL": "22.98",
  "FDC": "359.95",
  "FEDDERSHOL": "36.25",
  "FEDERALBNK": "294.35",
  "FEDFINA": "148.66",
  "FERMENTA": "318.40",
  "FIEMIND": "2250.50",
  "FILATEX": "44.25",
  "FINCABLES": "946.55",
  "FINEORG": "4995.20",
  "FINIETF": "32.01",
  "FINKURVE": "69.15",
  "FINOPB": "137.67",
  "FINPIPE": "173.82",
  "FIRSTCRY": "253.19",
  "FISCHER": "40.98",
  "FIVESTAR": "470.45",
  "FLAIR": "331.85",
  "FLEXIADD": "9.91",
  "FLEXITUFF": "6.40",
  "FLUOROCHEM": "3271.80",
  "FMCGIETF": "53.15",
  "FMGOETZE": "444.30",
  "FMNL": "9.02",
  "FOCUS": "79.51",
  "FOODSIN": "61.05",
  "FORCEMOT": "21925.00",
  "FORTIS": "890.90",
  "FOSECOIND": "4636.80",
  "FRACTAL": "841.60",
  "FRONTSP": "1513.35",
  "FSL": "233.04",
  "FUSION": "170.37",
  "GABRIEL": "1017.85",
  "GAEL": "146.73",
  "GALAPREC": "769.95",
  "GALAXYSURF": "1799.60",
  "GALLANTT": "869.05",
  "GANDHAR": "143.01",
  "GANDHITUBE": "868.50",
  "GANECOS": "1035.15",
  "GANESHBE": "94.65",
  "GANESHCP": "191.15",
  "GANESHHOU": "635.55",
  "GANGAFORGE": "2.89",
  "GANGESSECU": "125.49",
  "GARFIBRES": "652.70",
  "GARUDA": "175.64",
  "GATECH": "0.48",
  "GATECHDVR": "0.47",
  "GATEWAY": "58.25",
  "GAUDIUMIVF": "95.94",
  "GAYAHWS": "2.68",
  "GCSL": "352.65",
  "GEECEE": "305.32",
  "GEEKAYWIRE": "28.73",
  "GENCON": "43.81",
  "GENESYS": "258.79",
  "GENUSPAPER": "14.30",
  "GENUSPOWER": "286.26",
  "GEOJITFSL": "67.86",
  "GESHIP": "1423.60",
  "GFLLIMITED": "47.03",
  "GHCL": "499.95",
  "GHCLTEXTIL": "90.64",
  "GICHSGFIN": "153.55",
  "GICL": "40.49",
  "GICRE": "395.90",
  "GILLANDERS": "92.00",
  "GILLETTE": "7859.50",
  "GILT10BETA": "25.86",
  "GILT5BETA": "65.32",
  "GILT5YBEES": "64.57",
  "GINNIFILA": "41.57",
  "GIPCL": "154.79",
  "GKENERGY": "130.89",
  "GKSL": "112.60",
  "GKWLIMITED": "1535.60",
  "GLAND": "1794.60",
  "GLAXO": "2429.90",
  "GLENMARK": "2230.70",
  "GLFL": "5.73",
  "GLOBAL": "98.86",
  "GLOBALE": "12.72",
  "GLOBALVECT": "197.53",
  "GLOBE": "2.50",
  "GLOBECIVIL": "47.64",
  "GLOBUSSPR": "1002.35",
  "GLOSTERLTD": "578.65",
  "GLOTTIS": "56.12",
  "GMBREW": "974.45",
  "GMDCLTD": "691.25",
  "GMMPFAUDLR": "910.70",
  "GMRAIRPORT": "97.45",
  "GMRP&UI": "107.30",
  "GNA": "448.50",
  "GNFC": "481.25",
  "GNRL": "99.50",
  "GOACARBON": "369.55",
  "GOCLCORP": "337.55",
  "GOCOLORS": "291.02",
  "GODAVARIB": "313.75",
  "GODFRYPHLP": "2137.80",
  "GODIGIT": "321.25",
  "GODREJAGRO": "609.70",
  "GODREJIND": "919.55",
  "GODREJPROP": "1759.70",
  "GOKEX": "720.80",
  "GOKUL": "41.25",
  "GOKULAGRO": "206.05",
  "GOLD1": "125.91",
  "GOLD360": "147.35",
  "GOLDADD": "146.72",
  "GOLDBEES": "125.00",
  "GOLDBETA": "127.25",
  "GOLDBND": "150.99",
  "GOLDCASE": "23.79",
  "GOLDETF": "146.87",
  "GOLDIAM": "407.25",
  "GOLDIETF": "129.46",
  "GOLDTECH": "40.49",
  "GOODLUCK": "1227.05",
  "GOODYEAR": "797.45",
  "GOPAL": "278.00",
  "GOYALALUM": "7.08",
  "GPIL": "300.05",
  "GPPL": "157.80",
  "GPTHEALTH": "136.84",
  "GPTINFRA": "114.24",
  "GRANDOAK": "28.90",
  "GRANULES": "664.45",
  "GRAUWEIL": "68.16",
  "GRAVISSHO": "28.05",
  "GRAVITA": "1648.40",
  "GREAVESCOT": "157.88",
  "GREENLAM": "225.23",
  "GREENPANEL": "212.22",
  "GREENPLY": "232.24",
  "GREENPOWER": "10.67",
  "GRINDWELL": "1627.10",
  "GRINFRA": "890.75",
  "GRMOVER": "161.88",
  "GROBTEA": "915.10",
  "GROWWCAPM": "11.02",
  "GROWWCHEM": "27.72",
  "GROWWDEFNC": "87.79",
  "GROWWEV": "29.81",
  "GROWWGOLD": "14.77",
  "GROWWHOSPI": "47.89",
  "GROWWLIQID": "108.71",
  "GROWWLOVOL": "10.40",
  "GROWWMC150": "221.39",
  "GROWWMETAL": "12.16",
  "GROWWMOM50": "10.43",
  "GROWWN200": "11.26",
  "GROWWNET": "9.20",
  "GROWWNIFTY": "9.77",
  "GROWWNXT50": "70.37",
  "GROWWPOWER": "11.90",
  "GROWWPSE": "106.13",
  "GROWWPSUBK": "89.59",
  "GROWWRAIL": "32.68",
  "GROWWRLTY": "8.77",
  "GROWWSC250": "9.41",
  "GROWWSLVR": "24.33",
  "GRPLTD": "1980.70",
  "GRSE": "2667.80",
  "GRWRHITECH": "3977.50",
  "GSEC10ABSL": "111.38",
  "GSEC10IETF": "258.54",
  "GSEC10YEAR": "29.65",
  "GSEC5IETF": "64.77",
  "GSFC": "171.54",
  "GSLSU": "62.49",
  "GSPCROP": "409.50",
  "GSPL": "275.04",
  "GTECJAINX": "19.64",
  "GTLINFRA": "1.23",
  "GTPL": "67.74",
  "GUFICBIO": "293.30",
  "GUJALKALI": "734.80",
  "GUJAPOLLO": "427.25",
  "GUJGASLTD": "367.50",
  "GUJRAFFIA": "39.37",
  "GUJTHEM": "333.12",
  "GULFOILLUB": "964.00",
  "GULFPETRO": "33.75",
  "GULPOLY": "178.54",
  "GVPTECH": "7.33",
  "GVT&D": "4232.30",
  "HALDER": "259.26",
  "HALDYNGL": "89.05",
  "HALEOSLABS": "1327.80",
  "HAPPSTMNDS": "378.45",
  "HAPPYFORGE": "1310.00",
  "HARDWYN": "24.90",
  "HARIOMPIPE": "312.20",
  "HARRMALAYA": "211.55",
  "HARSHA": "393.15",
  "HATHWAY": "11.05",
  "HATSUN": "973.80",
  "HAVELLS": "1302.10",
  "HAWKINCOOK": "7573.60",
  "HBESD": "66.30",
  "HBLENGINE": "775.40",
  "HBSL": "61.44",
  "HCC": "19.24",
  "HCG": "570.15",
  "HCL-INSYS": "12.69",
  "HDBFS": "669.95",
  "HDFCBSE500": "36.66",
  "HDFCGOLD": "129.12",
  "HDFCGROWTH": "116.59",
  "HDFCLIQUID": "1057.01",
  "HDFCLOWVOL": "20.27",
  "HDFCMID150": "22.25",
  "HDFCMOMENT": "31.22",
  "HDFCNEXT50": "71.81",
  "HDFCNIF100": "26.06",
  "HDFCNIFBAN": "57.90",
  "HDFCNIFIT": "33.50",
  "HDFCNIFTY": "273.09",
  "HDFCPSUBK": "89.89",
  "HDFCPVTBAN": "27.40",
  "HDFCQUAL": "57.32",
  "HDFCSENSEX": "88.54",
  "HDFCSILVER": "237.52",
  "HDFCSML250": "164.62",
  "HDFCVALUE": "133.47",
  "HEADSUP": "7.29",
  "HEALTHADD": "145.51",
  "HEALTHCARE": "18.50",
  "HEALTHIETF": "148.44",
  "HEALTHY": "14.86",
  "HECPROJECT": "139.97",
  "HEG": "629.30",
  "HEIDELBERG": "158.58",
  "HEMIPROP": "129.60",
  "HERANBA": "218.60",
  "HERITGFOOD": "355.30",
  "HEROMOTOCO": "5282.50",
  "HESTERBIO": "1479.40",
  "HEXATRADEX": "171.17",
  "HEXT": "488.05",
  "HFCL": "93.30",
  "HGINFRA": "624.60",
  "HGM": "52.97",
  "HGS": "417.70",
  "HIKAL": "188.39",
  "HILINFRA": "56.32",
  "HILTON": "25.12",
  "HIMATSEIDE": "89.56",
  "HINDCOMPOS": "468.25",
  "HINDCOPPER": "556.60",
  "HINDOILEXP": "152.26",
  "HINDPETRO": "379.50",
  "HINDWAREAP": "210.80",
  "HIRECT": "884.80",
  "HISARMETAL": "153.55",
  "HITECH": "85.54",
  "HITECHCORP": "142.36",
  "HLEGLAS": "323.90",
  "HLVLTD": "8.81",
  "HMAAGRO": "24.60",
  "HMVL": "67.46",
  "HNDFDS": "493.40",
  "HNGSNGBEES": "533.91",
  "HOMEFIRST": "1122.00",
  "HONASA": "342.75",
  "HONAUT": "32555.00",
  "HONDAPOWER": "2283.40",
  "HPAL": "39.16",
  "HPIL": "141.21",
  "HPL": "362.60",
  "HSBCGOLD": "131.55",
  "HSCL": "489.00",
  "HTMEDIA": "22.93",
  "HUBTOWN": "212.13",
  "HUDCO": "199.40",
  "HUHTAMAKI": "188.86",
  "HYBRIDFIN": "21.22",
  "IBULLSLTD": "16.99",
  "ICEMAKE": "808.30",
  "ICICIAMC": "3295.70",
  "ICICIB22": "125.06",
  "ICICIGI": "1876.50",
  "ICICIPRULI": "557.90",
  "ICIL": "268.21",
  "ICRA": "5471.50",
  "IDBI": "74.13",
  "IDEA": "9.47",
  "IDEAFORGE": "461.95",
  "IDFCFIRSTB": "67.50",
  "IDFNIFTYET": "267.50",
  "IEX": "124.99",
  "IFBAGRO": "836.05",
  "IFBIND": "1098.00",
  "IFCI": "60.49",
  "IFGLEXPOR": "173.15",
  "IGARASHI": "336.20",
  "IGCL": "62.25",
  "IGIL": "357.15",
  "IGL": "166.39",
  "IGPL": "423.30",
  "IIFL": "468.75",
  "IIFLCAPS": "310.75",
  "IITL": "166.36",
  "IKIO": "142.44",
  "IKS": "1430.10",
  "IMAGICAA": "48.72",
  "IMFA": "1532.00",
  "IMPAL": "1020.45",
  "INA": "142.86",
  "INCREDIBLE": "36.82",
  "INDBANK": "35.90",
  "INDGN": "482.50",
  "INDIACEM": "416.50",
  "INDIAGLYCO": "959.00",
  "INDIAMART": "2184.60",
  "INDIANB": "928.30",
  "INDIANCARD": "211.27",
  "INDIANHUME": "324.40",
  "INDIASHLTR": "803.50",
  "INDIGOPNTS": "835.85",
  "INDIQUBE": "156.64",
  "INDNIPPON": "770.45",
  "INDOAMIN": "112.22",
  "INDOBORAX": "254.32",
  "INDOCO": "215.63",
  "INDOFARM": "144.27",
  "INDORAMA": "38.45",
  "INDOSTAR": "215.11",
  "INDOTECH": "1917.90",
  "INDOTHAI": "308.75",
  "INDOUS": "106.78",
  "INDOWIND": "10.25",
  "INDPRUD": "6572.65",
  "INDRAMEDCO": "413.20",
  "INDSWFTLAB": "138.90",
  "INDTERRAIN": "33.32",
  "INDUSINDBK": "851.95",
  "INDUSTOWER": "405.80",
  "INFOBEAN": "181.08",
  "INFOMEDIA": "5.95",
  "INFRA": "11.82",
  "INFRABEES": "958.45",
  "INFRAIETF": "95.61",
  "INGERRAND": "4148.60",
  "INNOVACAP": "731.20",
  "INNOVANA": "391.20",
  "INNOVISION": "322.55",
  "INOXGREEN": "160.96",
  "INOXINDIA": "1477.30",
  "INOXWIND": "97.35",
  "INSECTICID": "716.85",
  "INTELLECT": "679.80",
  "INTENTECH": "106.71",
  "INTERARCH": "1991.00",
  "INTERNET": "12.38",
  "INTLCONV": "78.23",
  "INVENTURE": "1.02",
  "INVPRECQ": "672.10",
  "IOB": "34.80",
  "IOLCP": "87.65",
  "IONEXCHANG": "396.55",
  "IPCALAB": "1468.60",
  "IPL": "155.65",
  "IRB": "22.00",
  "IRCON": "151.49",
  "IRCTC": "565.20",
  "IREDA": "130.14",
  "IRIS": "243.02",
  "IRISDOREME": "34.16",
  "IRMENERGY": "213.13",
  "ISFT": "76.66",
  "ISGEC": "1046.45",
  "ISHANCH": "61.10",
  "IT": "34.77",
  "ITADD": "33.28",
  "ITBEES": "34.80",
  "ITBETA": "330.86",
  "ITCHOTELS": "162.14",
  "ITDC": "608.10",
  "ITETF": "33.21",
  "ITI": "291.91",
  "ITIETF": "34.85",
  "IVALUE": "279.15",
  "IVC": "7.61",
  "IVP": "143.02",
  "IVZINGOLD": "13123.95",
  "IVZINNIFTY": "2770.49",
  "IWP": "33.00",
  "IXIGO": "177.36",
  "J&KBANK": "131.23",
  "JAGRAN": "65.88",
  "JAGSNPHARM": "185.42",
  "JAIBALAJI": "73.40",
  "JAICORPLTD": "113.55",
  "JAINREC": "419.05",
  "JAIPURKURT": "30.03",
  "JAMNAAUTO": "126.11",
  "JARO": "438.05",
  "JASH": "396.85",
  "JAYAGROGN": "198.19",
  "JAYBARMARU": "94.19",
  "JAYKAY": "161.12",
  "JAYNECOIND": "95.34",
  "JAYSREETEA": "88.39",
  "JBCHEPHARM": "1991.20",
  "JBMA": "615.65",
  "JETFREIGHT": "19.02",
  "JGCHEM": "383.55",
  "JINDALPHOT": "1143.85",
  "JINDALPOLY": "715.30",
  "JINDALSAW": "240.18",
  "JINDRILL": "543.85",
  "JINDWORLD": "25.76",
  "JISLDVREQS": "24.14",
  "JISLJALEQS": "33.20",
  "JKCEMENT": "5731.00",
  "JKIL": "511.45",
  "JKIPL": "104.87",
  "JKLAKSHMI": "662.80",
  "JKPAPER": "367.50",
  "JKTYRE": "419.05",
  "JLHL": "1286.50",
  "JMA": "83.65",
  "JMFINANCIL": "133.31",
  "JNKINDIA": "336.69",
  "JOCIL": "122.31",
  "JPOLYINVST": "1136.40",
  "JPPOWER": "19.08",
  "JSFB": "383.35",
  "JSL": "789.90",
  "JSLL": "675.70",
  "JSWCEMENT": "129.45",
  "JSWDULUX": "2895.60",
  "JSWENERGY": "543.05",
  "JSWHL": "13065.00",
  "JSWINFRA": "278.50",
  "JTEKTINDIA": "132.25",
  "JTLIND": "67.94",
  "JUBLCPL": "1861.60",
  "JUBLFOOD": "456.15",
  "JUBLINGREA": "667.35",
  "JUBLPHARMA": "905.50",
  "JUNIORBEES": "756.55",
  "JUNIPER": "209.96",
  "JUSTDIAL": "546.45",
  "JWL": "278.95",
  "JYOTHYLAB": "242.82",
  "JYOTICNC": "743.45",
  "JYOTISTRUC": "13.20",
  "KABRAEXTRU": "236.54",
  "KAJARIACER": "1187.20",
  "KAKATCEM": "138.08",
  "KALAMANDIR": "101.57",
  "KALPATARU": "321.95",
  "KALYANIFRG": "607.85",
  "KALYANKJIL": "417.50",
  "KAMAHOLD": "2506.10",
  "KAMATHOTEL": "168.08",
  "KAMDHENU": "21.81",
  "KANANIIND": "1.68",
  "KANCHI": "400.65",
  "KANORICHEM": "77.32",
  "KANPRPLA": "201.77",
  "KANSAINER": "204.07",
  "KARMAENG": "53.34",
  "KARURVYSYA": "274.75",
  "KAUSHALYA": "875.70",
  "KAYA": "280.65",
  "KAYNES": "4222.60",
  "KCP": "165.78",
  "KCPSUGIND": "26.13",
  "KDDL": "2394.20",
  "KEC": "559.55",
  "KECL": "143.72",
  "KEEPLEARN": "2.01",
  "KEI": "4880.60",
  "KELLTONTEC": "15.92",
  "KENNAMET": "2462.00",
  "KERNEX": "1154.45",
  "KESORAMIND": "10.61",
  "KEYFINSERV": "278.26",
  "KFINTECH": "975.10",
  "KHADIM": "102.32",
  "KHAICHEM": "60.97",
  "KHAITANLTD": "132.24",
  "KHANDSE": "15.86",
  "KICL": "4768.40",
  "KILITCH": "135.37",
  "KIMS": "678.20",
  "KINGFA": "4761.00",
  "KIOCL": "397.15",
  "KIRANVYPAR": "189.50",
  "KIRIINDUS": "415.20",
  "KIRLFER": "427.25",
  "KIRLOSBROS": "1736.30",
  "KIRLOSENG": "1639.90",
  "KIRLOSIND": "3102.00",
  "KIRLPNU": "1363.80",
  "KITEX": "167.24",
  "KKCL": "476.00",
  "KLBRENG-B": "519.80",
  "KMEW": "1700.20",
  "KMSUGAR": "27.89",
  "KNAGRI": "197.47",
  "KNRCON": "120.96",
  "KOHINOOR": "25.26",
  "KOKUYOCMLN": "89.03",
  "KOLTEPATIL": "401.40",
  "KOPRAN": "155.33",
  "KOTARISUG": "27.61",
  "KOTHARIPET": "138.60",
  "KOTHARIPRO": "71.53",
  "KOTIC": "174.80",
  "KOTYARK": "372.40",
  "KOVAI": "5487.90",
  "KPEL": "347.45",
  "KPIGREEN": "440.55",
  "KPIL": "1241.50",
  "KPITTECH": "734.40",
  "KPL": "1662.60",
  "KPRMILL": "919.60",
  "KRBL": "345.60",
  "KRIDHANINF": "2.60",
  "KRISHANA": "638.75",
  "KRISHIVAL": "327.80",
  "KRISHNADEF": "1024.85",
  "KRITI": "81.75",
  "KRITIKA": "6.31",
  "KRITINUT": "98.03",
  "KRN": "1245.80",
  "KRONOX": "130.54",
  "KROSS": "194.35",
  "KRSNAA": "625.00",
  "KRYSTAL": "578.65",
  "KSB": "981.95",
  "KSCL": "933.60",
  "KSHINTL": "563.25",
  "KSL": "755.15",
  "KSOLVES": "345.10",
  "KTKBANK": "245.67",
  "KUANTUM": "81.31",
  "KWIL": "27.86",
  "LAGNAM": "73.87",
  "LAHOTIOV": "44.10",
  "LAL": "7.30",
  "LALPATHLAB": "1418.60",
  "LAMBODHARA": "106.07",
  "LANDMARK": "415.15",
  "LANDSMILL": "1.05",
  "LAOPALA": "182.54",
  "LATENTVIEW": "302.95",
  "LATTEYS": "21.85",
  "LAURUSLABS": "1129.50",
  "LAXMIDENTL": "193.42",
  "LAXMIINDIA": "122.12",
  "LEMERITE": "433.55",
  "LEMONTREE": "113.13",
  "LENSKART": "532.70",
  "LFIC": "139.35",
  "LGBBROSLTD": "1743.00",
  "LGEINDIA": "1594.10",
  "LGHL": "264.09",
  "LIBAS": "11.84",
  "LIBERTSHOE": "264.97",
  "LICHSGFIN": "536.70",
  "LICI": "828.10",
  "LICMFGOLD": "135.85",
  "LICNETFGSC": "28.81",
  "LICNETFN50": "270.35",
  "LICNETFSEN": "882.00",
  "LICNFNHGP": "276.19",
  "LICNMID100": "60.06",
  "LINC": "99.28",
  "LINCOLN": "616.05",
  "LINDEINDIA": "7065.00",
  "LIQGRWBEES": "1036.13",
  "LIQUID": "999.99",
  "LIQUID1": "1100.61",
  "LIQUIDADD": "1122.77",
  "LIQUIDBETF": "1078.11",
  "LIQUIDCASE": "113.68",
  "LIQUIDETF": "1000.00",
  "LIQUIDIETF": "1000.00",
  "LIQUIDPLUS": "1081.73",
  "LIQUIDSBI": "999.99",
  "LIQUIDSHRI": "1100.86",
  "LLOYDSENGG": "55.53",
  "LLOYDSENT": "65.88",
  "LLOYDSME": "1629.10",
  "LMW": "14142.00",
  "LOKESHMACH": "279.03",
  "LORDSCHLO": "152.55",
  "LOTUSDEV": "145.28",
  "LOTUSEYE": "111.29",
  "LOVABLE": "72.17",
  "LOWVOL": "203.23",
  "LOWVOL1": "20.72",
  "LOWVOLIETF": "21.70",
  "LTF": "290.15",
  "LTFOODS": "415.65",
  "LTGILTBEES": "29.23",
  "LTGILTCASE": "29.82",
  "LTTS": "3572.50",
  "LUMAXIND": "5517.10",
  "LUMAXTECH": "1795.40",
  "LUPIN": "2328.70",
  "LUXIND": "1490.00",
  "LXCHEM": "141.58",
  "LYPSAGEMS": "5.45",
  "M&MFIN": "303.60",
  "MAANALU": "139.73",
  "MACPOWER": "1121.00",
  "MADHAV": "36.02",
  "MADHAVIPL": "8.90",
  "MADRASFERT": "68.55",
  "MAFANG": "175.90",
  "MAFATIND": "130.65",
  "MAGADSUGAR": "507.00",
  "MAHABANK": "75.54",
  "MAHAPEXLTD": "50.36",
  "MAHEPC": "125.38",
  "MAHESHWARI": "50.01",
  "MAHKTECH": "24.37",
  "MAHLIFE": "320.75",
  "MAHLOG": "432.35",
  "MAHSCOOTER": "13039.00",
  "MAHSEAMLES": "644.90",
  "MAITHANALL": "1016.60",
  "MAJESAUT": "300.00",
  "MAKEINDIA": "158.20",
  "MALLCOM": "1087.35",
  "MALUPAPER": "32.79",
  "MAMATA": "402.10",
  "MANAKCOAT": "110.62",
  "MANAKSIA": "59.29",
  "MANAKSTEEL": "66.86",
  "MANALIPETC": "54.92",
  "MANAPPURAM": "269.10",
  "MANBA": "109.17",
  "MANCREDIT": "171.12",
  "MANGLMCEM": "909.30",
  "MANINDS": "535.75",
  "MANINFRA": "96.08",
  "MANKIND": "2144.00",
  "MANOMAY": "231.34",
  "MANORAMA": "1384.10",
  "MANORG": "467.20",
  "MANUFGBEES": "155.82",
  "MANUGRAPH": "13.65",
  "MANYAVAR": "448.70",
  "MAPMYINDIA": "926.70",
  "MARALOVER": "44.98",
  "MARATHON": "479.65",
  "MARICO": "760.70",
  "MARINE": "206.91",
  "MARKOLINES": "151.75",
  "MARKSANS": "176.90",
  "MARSONS": "164.10",
  "MASFIN": "314.90",
  "MASPTOP50": "74.60",
  "MASTEK": "1682.90",
  "MASTERTR": "76.51",
  "MATRIMONY": "438.10",
  "MAWANASUG": "104.52",
  "MAXESTATES": "389.20",
  "MAXIND": "149.93",
  "MAYURUNIQ": "571.10",
  "MAZDA": "211.61",
  "MBAPL": "520.30",
  "MBEL": "338.84",
  "MCCHRLS-B": "676.00",
  "MCLOUD": "26.72",
  "MCX": "2859.10",
  "MEDANTA": "1079.35",
  "MEDIASSIST": "369.05",
  "MEDICAMEQ": "268.30",
  "MEDICO": "40.79",
  "MEDPLUS": "869.80",
  "MEESHO": "162.58",
  "MEGASTAR": "291.10",
  "MEIL": "316.54",
  "MENNPIS": "57.00",
  "MENONBE": "123.98",
  "MERCANTILE": "22.10",
  "METAL": "12.92",
  "METALIETF": "12.91",
  "METROBRAND": "1064.10",
  "METROGLOBL": "129.20",
  "METROPOLIS": "475.40",
  "MFML": "24.60",
  "MFSL": "1688.80",
  "MGEL": "14.19",
  "MGL": "1137.75",
  "MHLXMIRU": "182.33",
  "MHRIL": "267.06",
  "MICEL": "41.34",
  "MID150": "22.31",
  "MID150BEES": "227.17",
  "MID150CASE": "11.04",
  "MIDCAP": "17.35",
  "MIDCAPADD": "22.00",
  "MIDCAPBETA": "222.78",
  "MIDCAPETF": "22.46",
  "MIDCAPIETF": "22.70",
  "MIDHANI": "378.55",
  "MIDQ50ADD": "240.91",
  "MIDSELIETF": "17.93",
  "MIDSMALL": "49.62",
  "MIDWESTLTD": "1337.90",
  "MINDACORP": "537.95",
  "MINDTECK": "206.11",
  "MIRCELECTR": "31.22",
  "MIRZAINT": "33.41",
  "MITCON": "74.84",
  "MITTAL": "0.95",
  "MKPL": "5.33",
  "MMFL": "485.60",
  "MMP": "252.01",
  "MMTC": "66.67",
  "MMWL": "10.90",
  "MNC": "32.18",
  "MOALPHA50": "51.09",
  "MOBANK10": "16.86",
  "MOBIKWIK": "200.98",
  "MOCAPITAL": "52.62",
  "MODEFENCE": "96.22",
  "MODINATUR": "361.00",
  "MODIRUBBER": "128.37",
  "MODIS": "336.90",
  "MODISONLTD": "146.08",
  "MODTHREAD": "48.00",
  "MOENERGY": "39.31",
  "MOGOLD": "149.45",
  "MOGSEC": "63.74",
  "MOHEALTH": "44.04",
  "MOHITIND": "23.82",
  "MOIL": "321.20",
  "MOINFRA": "63.50",
  "MOIPO": "43.04",
  "MOKSH": "11.45",
  "MOL": "52.48",
  "MOLDTECH": "135.29",
  "MOLDTKPAC": "552.30",
  "MOLOWVOL": "36.46",
  "MOM100": "64.32",
  "MOM30IETF": "31.40",
  "MOM50": "253.55",
  "MOMENTUM": "31.28",
  "MOMENTUM30": "30.95",
  "MOMENTUM50": "51.69",
  "MOMGF": "155.27",
  "MOMIDMTM": "62.57",
  "MOMNC": "31.26",
  "MOMOMENTUM": "62.11",
  "MON100": "285.16",
  "MON50EQUAL": "32.72",
  "MONARCH": "293.47",
  "MONEXT50": "69.98",
  "MONEYBOXX": "72.80",
  "MONIFTY100": "25.30",
  "MONIFTY500": "23.30",
  "MONQ50": "123.24",
  "MONTECARLO": "562.75",
  "MOPSE": "108.46",
  "MOQUALITY": "200.94",
  "MOREALTY": "78.24",
  "MOREPENLAB": "41.29",
  "MOSCHIP": "198.02",
  "MOSERVICE": "31.38",
  "MOSILVER": "244.94",
  "MOSMALL250": "16.43",
  "MOTILALOFS": "807.95",
  "MOTISONS": "13.93",
  "MOTOGENFIN": "25.92",
  "MOTOUR": "74.51",
  "MOVALUE": "118.35",
  "MPHASIS": "2417.00",
  "MPSLTD": "1727.40",
  "MRF": "139225.00",
  "MRPL": "180.00",
  "MSCIADD": "29.38",
  "MSCIINDIA": "29.64",
  "MSPL": "35.85",
  "MSTCLTD": "456.20",
  "MSUMI": "39.19",
  "MTARTECH": "4942.00",
  "MTNL": "32.26",
  "MUFIN": "115.99",
  "MUFTI": "77.79",
  "MUKANDLTD": "133.21",
  "MUKKA": "23.62",
  "MUKTAARTS": "48.92",
  "MULTICAP": "16.03",
  "MUNJALAU": "80.79",
  "MUNJALSHOW": "130.59",
  "MURUDCERA": "32.76",
  "MUTHOOTCAP": "207.99",
  "MUTHOOTMF": "172.17",
  "MVGJL": "176.53",
  "MWL": "277.60",
  "NACLIND": "166.91",
  "NAGREEKCAP": "30.81",
  "NAGREEKEXP": "26.96",
  "NAHARCAP": "251.88",
  "NAHARINDUS": "106.16",
  "NAHARPOLY": "257.32",
  "NAHARSPING": "253.81",
  "NAM-INDIA": "1003.00",
  "NARMADA": "34.40",
  "NATCAPSUQ": "166.26",
  "NATCOPHARM": "1100.05",
  "NATHBIOGEN": "171.13",
  "NATIONALUM": "426.65",
  "NATIONSTD": "1411.65",
  "NAUKRI": "1067.90",
  "NAVA": "702.10",
  "NAVINFLUOR": "6471.50",
  "NAVKARCORP": "112.04",
  "NAVKARURB": "0.89",
  "NAVNETEDUL": "151.40",
  "NAZARA": "270.08",
  "NBCC": "93.32",
  "NBIFIN": "2174.70",
  "NCC": "160.53",
  "NCLIND": "179.42",
  "NDGL": "2636.30",
  "NDL": "2.95",
  "NDLVENTURE": "133.12",
  "NDRAUTO": "748.75",
  "NDTV": "81.50",
  "NECCLTD": "15.84",
  "NECLIFE": "12.29",
  "NELCAST": "135.89",
  "NELCO": "673.55",
  "NEOGEN": "1494.40",
  "NEPHROPLUS": "573.15",
  "NESCO": "1185.40",
  "NETF": "263.90",
  "NETWEB": "3779.70",
  "NETWORK18": "35.89",
  "NEULANDLAB": "15202.00",
  "NEWGEN": "471.95",
  "NEXT30ADD": "41.31",
  "NEXT50": "724.35",
  "NEXT50ADD": "70.60",
  "NEXT50BETA": "75.72",
  "NEXT50ETF": "70.71",
  "NEXT50IETF": "73.93",
  "NEXTMEDIA": "4.38",
  "NFL": "76.31",
  "NGIL": "36.76",
  "NGLFINE": "2299.30",
  "NH": "1800.20",
  "NHPC": "83.10",
  "NIACL": "164.95",
  "NIBE": "1063.05",
  "NIBL": "32.91",
  "NIF100BEES": "266.02",
  "NIF100IETF": "28.00",
  "NIFTY1": "267.93",
  "NIFTY100EW": "34.10",
  "NIFTYADD": "254.37",
  "NIFTYBEES": "275.21",
  "NIFTYBETA": "268.24",
  "NIFTYBETF": "249.04",
  "NIFTYCASE": "9.69",
  "NIFTYETF": "262.99",
  "NIFTYIETF": "274.10",
  "NIFTYQLITY": "21.12",
  "NIITLTD": "71.47",
  "NIITMTS": "331.85",
  "NILAINFRA": "8.34",
  "NILASPACES": "13.64",
  "NILE": "1703.65",
  "NILKAMAL": "1317.30",
  "NIMBSPROJ": "191.82",
  "NINSYS": "466.00",
  "NIPPOBATRY": "325.05",
  "NIRAJ": "30.42",
  "NIRLON": "539.79",
  "NITCO": "91.62",
  "NITINSPIN": "413.55",
  "NITIRAJ": "204.09",
  "NITTAGELA": "863.20",
  "NIVABUPA": "77.61",
  "NKIND": "67.84",
  "NLCINDIA": "304.35",
  "NMDC": "88.90",
  "NOCIL": "171.67",
  "NOIDATOLL": "3.82",
  "NORBTEAEXP": "72.36",
  "NORTHARC": "240.02",
  "NOVAAGRI": "29.20",
  "NOVARTIND": "995.45",
  "NPBET": "278.92",
  "NPST": "1266.55",
  "NRAIL": "475.85",
  "NRBBEARING": "294.06",
  "NRL": "54.75",
  "NSIL": "5849.10",
  "NSLNISP": "41.80",
  "NTPCGREEN": "113.00",
  "NUCLEUS": "797.95",
  "NURECA": "259.51",
  "NUVAMA": "1379.10",
  "NUVOCO": "308.20",
  "NV20": "14.76",
  "NV20BEES": "148.03",
  "NV20IETF": "14.44",
  "NYKAA": "264.55",
  "OAL": "314.85",
  "OBCL": "55.10",
  "OBEROIRLTY": "1694.90",
  "OCCLLTD": "98.20",
  "OFSS": "8082.50",
  "OIL": "471.70",
  "OILCOUNTUB": "63.57",
  "OILIETF": "11.59",
  "OLAELEC": "39.22",
  "OLECTRA": "1196.90",
  "OMAXAUTO": "114.83",
  "OMAXE": "78.88",
  "OMFREIGHT": "78.61",
  "OMINFRAL": "93.94",
  "OMNI": "343.85",
  "ONELIFECAP": "15.35",
  "ONEPOINT": "54.72",
  "ONESOURCE": "1549.20",
  "ONMOBILE": "47.48",
  "ONWARDTEC": "245.16",
  "OPTIEMUS": "400.95",
  "ORBTEXP": "165.44",
  "ORCHASP": "2.06",
  "ORCHPHARMA": "545.30",
  "ORICONENT": "66.15",
  "ORIENTALTL": "7.00",
  "ORIENTBELL": "302.25",
  "ORIENTCEM": "144.07",
  "ORIENTCER": "41.98",
  "ORIENTELEC": "180.96",
  "ORIENTHOT": "97.15",
  "ORIENTLTD": "63.13",
  "ORIENTPPR": "18.73",
  "ORIENTTECH": "287.30",
  "ORISSAMINE": "4089.00",
  "ORKLAINDIA": "633.55",
  "OSIAHYPER": "5.15",
  "OSWALAGRO": "49.93",
  "OSWALGREEN": "28.57",
  "OSWALPUMPS": "414.85",
  "OSWALSEEDS": "12.59",
  "PACEDIGITK": "171.98",
  "PAGEIND": "38405.00",
  "PAISALO": "43.42",
  "PAKKA": "98.90",
  "PALASHSECU": "95.40",
  "PALREDTEC": "38.00",
  "PANACEABIO": "341.60",
  "PANAMAPET": "269.98",
  "PAR": "92.70",
  "PARACABLES": "38.58",
  "PARADEEP": "126.93",
  "PARAGMILK": "214.39",
  "PARAS": "781.50",
  "PARKHOSPS": "221.79",
  "PARKHOTELS": "120.08",
  "PARSVNATH": "8.62",
  "PASHUPATI": "95.85",
  "PASUPTAC": "48.00",
  "PATANJALI": "459.65",
  "PATELENG": "27.83",
  "PATELRMART": "207.99",
  "PATINTLOG": "11.61",
  "PAUSHAKLTD": "494.55",
  "PAYTM": "1161.35",
  "PCBL": "283.37",
  "PCJEWELLER": "9.69",
  "PDMJEPAPER": "86.40",
  "PDSL": "293.90",
  "PEARLPOLY": "22.35",
  "PENIND": "169.77",
  "PENINLAND": "21.00",
  "PERSISTENT": "5325.20",
  "PETRONET": "272.13",
  "PFIZER": "4894.70",
  "PFOCUS": "327.55",
  "PFS": "31.43",
  "PGEL": "559.05",
  "PGHH": "9933.00",
  "PGHL": "5086.00",
  "PGIL": "1635.50",
  "PHARMABEES": "23.02",
  "PHOENIXLTD": "1767.90",
  "PICCADIL": "601.00",
  "PIGL": "120.71",
  "PIIND": "3037.00",
  "PILANIINVS": "4871.40",
  "PILITA": "8.13",
  "PINELABS": "194.00",
  "PIONEEREMB": "26.77",
  "PIONRINV": "106.15",
  "PIRAMALFIN": "1646.80",
  "PITTIENG": "950.50",
  "PIXTRANS": "1523.30",
  "PKTEA": "769.00",
  "PLASTIBLEN": "151.18",
  "PLATIND": "224.77",
  "PLAZACABLE": "39.44",
  "PML": "607.00",
  "PNBGILTS": "74.25",
  "PNBHOUSING": "906.75",
  "PNCINFRA": "201.96",
  "PNGJL": "670.05",
  "PNGSREVA": "378.60",
  "POCL": "1187.30",
  "PODDARMENT": "256.15",
  "POKARNA": "908.75",
  "POLICYBZR": "1616.80",
  "POLYCAB": "8198.50",
  "POLYMED": "1456.30",
  "POLYPLEX": "866.05",
  "PONNIERODE": "291.25",
  "POONAWALLA": "418.20",
  "POWERICA": "455.65",
  "POWERINDIA": "29645.00",
  "POWERMECH": "2432.70",
  "PPAP": "209.74",
  "PPL": "214.87",
  "PPLPHARMA": "148.79",
  "PRABHA": "161.50",
  "PRADPME": "370.60",
  "PRAENG": "25.27",
  "PRAJIND": "356.50",
  "PRAKASH": "141.26",
  "PRAKASHSTL": "4.80",
  "PRAVEG": "266.60",
  "PRAXIS": "7.23",
  "PRECAM": "152.62",
  "PRECWIRE": "365.00",
  "PREMCO": "420.35",
  "PREMEXPLN": "487.95",
  "PREMIERENE": "1010.75",
  "PRESTIGE": "1373.80",
  "PRICOLLTD": "588.45",
  "PRIMESECU": "281.25",
  "PRIMO": "23.69",
  "PRINCEPIPE": "257.02",
  "PRITIKAUTO": "13.44",
  "PRIVISCL": "3086.90",
  "PROSTARM": "150.56",
  "PROTEAN": "545.65",
  "PROZONER": "63.40",
  "PRSMJOHNSN": "130.88",
  "PRUDENT": "2711.30",
  "PRUDMOULI": "17.27",
  "PSB": "25.06",
  "PSPPROJECT": "711.90",
  "PSUBANK": "890.40",
  "PSUBANKADD": "90.03",
  "PSUBNKBEES": "99.28",
  "PSUBNKIETF": "90.44",
  "PTC": "192.16",
  "PTCIL": "16126.00",
  "PTL": "38.59",
  "PUNJABCHEM": "1062.85",
  "PURVA": "217.39",
  "PVP": "33.14",
  "PVRINOX": "939.30",
  "PVSL": "102.66",
  "PVTBANIETF": "27.21",
  "PVTBANKADD": "27.71",
  "PWL": "107.01",
  "PYRAMID": "158.90",
  "QGOLDHALF": "125.30",
  "QNIFTY": "266.21",
  "QPOWER": "1277.25",
  "QUADFUTURE": "321.90",
  "QUAL30IETF": "20.91",
  "QUALITY30": "20.59",
  "QUESS": "193.28",
  "QUICKHEAL": "170.44",
  "QUINT": "42.70",
  "RACLGEAR": "1363.60",
  "RADAAN": "3.36",
  "RADHIKAJWE": "66.05",
  "RADIANTCMS": "41.81",
  "RADICO": "3340.10",
  "RAILTEL": "326.28",
  "RAIN": "133.14",
  "RAINBOW": "1246.10",
  "RAJOOENG": "65.38",
  "RAJPALAYAM": "794.50",
  "RAJRATAN": "435.45",
  "RAJSREESUG": "34.17",
  "RAJTV": "22.76",
  "RALLIS": "261.37",
  "RAMANEWS": "33.39",
  "RAMAPHO": "141.23",
  "RAMASTEEL": "6.04",
  "RAMCOCEM": "1010.45",
  "RAMCOIND": "273.16",
  "RAMCOSYS": "421.35",
  "RAMKY": "513.35",
  "RAMRAT": "372.40",
  "RANASUG": "13.89",
  "RANEHOLDIN": "1091.75",
  "RATEGAIN": "569.60",
  "RATNAMANI": "2427.20",
  "RATNAVEER": "145.74",
  "RAYMOND": "420.70",
  "RAYMONDLSL": "797.85",
  "RAYMONDREL": "464.05",
  "RBA": "62.91",
  "RBLBANK": "317.50",
  "RBZJEWEL": "144.75",
  "RCF": "130.34",
  "REDINGTON": "227.49",
  "REDTAPE": "121.36",
  "REFEX": "250.39",
  "REGAAL": "83.05",
  "REGENCERAM": "45.17",
  "RELAXO": "305.32",
  "RELCHEMQ": "121.93",
  "RELIABLE": "133.43",
  "RELIGARE": "224.31",
  "RELTD": "135.86",
  "REMSONSIND": "103.14",
  "RENUKA": "27.91",
  "REPCOHOME": "403.65",
  "REPRO": "359.25",
  "RESPONIND": "153.12",
  "RETAIL": "22.01",
  "RGL": "105.89",
  "RHETAN": "25.42",
  "RHIM": "401.75",
  "RHL": "189.36",
  "RICOAUTO": "115.90",
  "RIIL": "788.90",
  "RISHABH": "477.30",
  "RITCO": "213.06",
  "RITES": "218.91",
  "RKDL": "21.51",
  "RKEC": "39.87",
  "RKFORGE": "529.95",
  "RKSWAMY": "96.46",
  "RMDRIP": "22.08",
  "RML": "757.05",
  "ROHLTD": "356.40",
  "ROLEXRINGS": "139.48",
  "ROLLT": "1.46",
  "ROML": "44.03",
  "ROSSARI": "496.40",
  "ROSSELLIND": "52.70",
  "ROSSTECH": "932.90",
  "ROTO": "59.02",
  "ROUTE": "502.35",
  "RPEL": "711.90",
  "RPGLIFE": "2014.90",
  "RPOWER": "28.09",
  "RPPINFRA": "78.38",
  "RPPL": "16.07",
  "RPSGVENT": "951.95",
  "RPTECH": "474.35",
  "RRIL": "15.35",
  "RRKABEL": "1469.20",
  "RSDFIN": "84.45",
  "RSL": "128.31",
  "RSWM": "159.57",
  "RSYSTEMS": "289.23",
  "RTNINDIA": "34.40",
  "RTNPOWER": "9.51",
  "RUBFILA": "70.46",
  "RUBICON": "927.55",
  "RUBYMILLS": "234.54",
  "RUCHINFRA": "6.14",
  "RUCHIRA": "114.22",
  "RUDRA": "22.86",
  "RUPA": "143.30",
  "RUSHIL": "16.53",
  "RUSTOMJEE": "400.90",
  "RVHL": "42.69",
  "RVNL": "296.33",
  "RVTH": "608.55",
  "SAATVIKGL": "464.05",
  "SADBHIN": "3.06",
  "SADHNANIQ": "2.28",
  "SAFARI": "1558.60",
  "SAGARDEEP": "23.88",
  "SAGCEM": "186.45",
  "SAGILITY": "42.18",
  "SAHLIBHFI": "83.11",
  "SAHYADRI": "244.44",
  "SAIL": "172.71",
  "SAILIFE": "959.40",
  "SAIPARENT": "489.55",
  "SAKAR": "609.55",
  "SAKHTISUG": "18.20",
  "SAKSOFT": "145.29",
  "SALASAR": "7.41",
  "SALONA": "284.40",
  "SALSTEEL": "55.34",
  "SALZERELEC": "628.80",
  "SAMBHV": "120.05",
  "SAMHI": "163.20",
  "SAMMAANCAP": "152.07",
  "SAMPANN": "31.18",
  "SANATHAN": "419.55",
  "SANDESH": "982.45",
  "SANDHAR": "494.25",
  "SANDUMA": "213.39",
  "SANGAMIND": "490.30",
  "SANGHVIMOV": "299.40",
  "SANOFI": "3578.30",
  "SANOFICONR": "4724.10",
  "SANSERA": "2275.50",
  "SANSTAR": "88.64",
  "SAPPHIRE": "173.23",
  "SARDAEN": "583.90",
  "SAREGAMA": "341.50",
  "SARLAPOLY": "92.15",
  "SARVESHWAR": "3.97",
  "SASKEN": "1328.30",
  "SASTASUNDR": "270.35",
  "SATIA": "64.44",
  "SATIN": "169.03",
  "SAURASHCEM": "63.43",
  "SBC": "33.84",
  "SBCL": "521.15",
  "SBFC": "96.17",
  "SBGLP": "29.13",
  "SBIBPB": "51.58",
  "SBICARD": "675.30",
  "SBIETFCON": "118.03",
  "SBIETFIT": "347.70",
  "SBIETFPB": "275.39",
  "SBIETFQLTY": "221.11",
  "SBILIQETF": "1035.45",
  "SBIMIDMOM": "61.71",
  "SBINEQWETF": "33.28",
  "SBINMID150": "22.12",
  "SBISILVER": "243.00",
  "SCANSTL": "33.70",
  "SCHAEFFLER": "4086.70",
  "SCHAND": "161.82",
  "SCILAL": "46.76",
  "SCODATUBES": "152.89",
  "SDBL": "86.17",
  "SDL26BEES": "137.55",
  "SEAMECLTD": "1559.70",
  "SEDEMAC": "1635.50",
  "SEIL": "178.20",
  "SEJALLTD": "651.15",
  "SELECTIPO": "42.99",
  "SELMC": "32.66",
  "SEMAC": "287.84",
  "SENCO": "323.60",
  "SENORES": "912.40",
  "SENSEXADD": "80.54",
  "SENSEXBETA": "862.39",
  "SENSEXETF": "80.38",
  "SENSEXIETF": "898.50",
  "SEPC": "7.38",
  "SERVOTECH": "82.55",
  "SESHAPAPER": "267.68",
  "SETF10GILT": "258.17",
  "SETFGOLD": "128.89",
  "SETFNIF50": "260.42",
  "SETFNIFBK": "579.06",
  "SETFNN50": "748.47",
  "SETL": "137.07",
  "SFL": "546.65",
  "SGFIN": "496.75",
  "SGIL": "520.70",
  "SGL": "12.03",
  "SGMART": "533.75",
  "SHADOWFAX": "146.13",
  "SHAH": "5.19",
  "SHAHALLOYS": "72.54",
  "SHAILY": "1845.70",
  "SHAKTIPUMP": "554.90",
  "SHALBY": "158.17",
  "SHALPAINTS": "53.91",
  "SHANTI": "7.39",
  "SHANTIGEAR": "466.70",
  "SHANTIGOLD": "207.90",
  "SHARDACROP": "1102.75",
  "SHARDAMOTR": "860.90",
  "SHARDUL": "27.70",
  "SHAREINDIA": "144.47",
  "SHARIABEES": "474.07",
  "SHBAJRG": "176.40",
  "SHEKHAWATI": "13.49",
  "SHEMAROO": "105.49",
  "SHILCTECH": "4983.30",
  "SHILPAMED": "411.25",
  "SHINDL": "148.80",
  "SHIVALIK": "271.05",
  "SHIVAMAUTO": "19.48",
  "SHIVAMILLS": "61.24",
  "SHIVATEX": "153.70",
  "SHK": "147.09",
  "SHOPERSTOP": "305.80",
  "SHRADHA": "40.63",
  "SHREDIGCEM": "73.26",
  "SHREEJISPG": "372.65",
  "SHREEPUSHK": "345.90",
  "SHREERAMA": "46.94",
  "SHREYANIND": "172.23",
  "SHRIKRISH": "42.60",
  "SHRINGARMS": "201.80",
  "SHRIPISTON": "3627.60",
  "SHRIRAMPPS": "83.05",
  "SHYAMCENT": "5.50",
  "SHYAMMETL": "851.55",
  "SHYAMTEL": "10.70",
  "SICAGEN": "54.55",
  "SIGACHI": "22.56",
  "SIGIND": "50.61",
  "SIGMA": "45.54",
  "SIGMAADV": "205.90",
  "SIGNATURE": "826.00",
  "SIGNPOST": "270.41",
  "SIKA": "958.85",
  "SIKKO": "4.78",
  "SIL": "15.84",
  "SILGO": "76.93",
  "SILINV": "466.70",
  "SILLYMONKS": "16.79",
  "SILVER": "247.57",
  "SILVER1": "24.09",
  "SILVER360": "244.07",
  "SILVERADD": "239.15",
  "SILVERAG": "241.18",
  "SILVERBEES": "237.27",
  "SILVERBETA": "239.50",
  "SILVERBND": "248.13",
  "SILVERCASE": "25.19",
  "SILVERIETF": "247.72",
  "SILVERTUC": "123.34",
  "SIMPLEXINF": "216.62",
  "SINCLAIR": "80.19",
  "SINDHUTRAD": "24.59",
  "SINGERIND": "72.87",
  "SINTERCOM": "79.14",
  "SIRCA": "443.50",
  "SIS": "326.35",
  "SIYSIL": "560.30",
  "SJS": "1682.20",
  "SJVN": "76.98",
  "SKFINDIA": "1752.80",
  "SKFINDUS": "2287.80",
  "SKIPPER": "436.60",
  "SKMEGGPROD": "171.98",
  "SKYGOLD": "411.50",
  "SMALL250": "16.39",
  "SMALLADD": "16.62",
  "SMALLCAP": "43.73",
  "SMARTLINK": "139.33",
  "SMARTWORKS": "440.40",
  "SMCGLOBAL": "64.16",
  "SML100CASE": "9.91",
  "SMLMAH": "4321.60",
  "SMLT": "73.58",
  "SMSPHARMA": "417.70",
  "SNOWMAN": "41.55",
  "SNXT30BEES": "41.35",
  "SNXT50BETA": "91.54",
  "SOBHA": "1311.40",
  "SOLARA": "491.60",
  "SOLARWORLD": "212.52",
  "SOLEX": "1327.65",
  "SOMANYCERA": "450.10",
  "SOMATEX": "106.11",
  "SOMICONVEY": "110.84",
  "SONACOMS": "576.55",
  "SONAMLTD": "53.39",
  "SONATSOFTW": "272.86",
  "SOTL": "364.45",
  "SOUTHBANK": "39.29",
  "SOUTHWEST": "251.35",
  "SPAL": "777.10",
  "SPANDANA": "220.94",
  "SPARC": "144.50",
  "SPCENET": "4.71",
  "SPECIALITY": "101.17",
  "SPECTRUM": "1159.60",
  "SPENCERS": "34.52",
  "SPIC": "70.47",
  "SPLIL": "35.18",
  "SPLPETRO": "769.90",
  "SPMLINFRA": "215.29",
  "SPORTKING": "144.54",
  "SRD": "44.87",
  "SREEL": "180.19",
  "SRF": "2465.10",
  "SRGHFL": "284.89",
  "SRHHYPOLTD": "482.20",
  "SRM": "508.90",
  "SRTL": "48.17",
  "SSDL": "62.15",
  "SSWL": "217.76",
  "STALLION": "155.12",
  "STANLEY": "140.56",
  "STAR": "996.50",
  "STARCEMENT": "221.02",
  "STARHEALTH": "506.45",
  "STARPAPER": "148.30",
  "STARTECK": "245.74",
  "STCINDIA": "120.73",
  "STEELCAS": "298.32",
  "STEELCITY": "85.89",
  "STEELXIND": "9.76",
  "STEL": "470.20",
  "STERTOOLS": "249.52",
  "STLNETWORK": "30.18",
  "STLTECH": "271.63",
  "STOVEKRAFT": "540.45",
  "STUDDS": "488.25",
  "STYL": "246.21",
  "STYLAMIND": "2240.00",
  "STYLEBAAZA": "339.00",
  "STYRENIX": "2183.90",
  "SUBEXLTD": "9.13",
  "SUBROS": "772.55",
  "SUDARCOLOR": "352.65",
  "SUDARSCHEM": "833.25",
  "SUDEEPPHRM": "664.55",
  "SUKHJITS": "176.61",
  "SULA": "173.53",
  "SUMEETINDS": "30.05",
  "SUMICHEM": "446.25",
  "SUMIT": "56.12",
  "SUMMITSEC": "1658.40",
  "SUNCLAY": "1473.40",
  "SUNDARAM": "1.47",
  "SUNDARMFIN": "5015.00",
  "SUNDRMBRAK": "616.15",
  "SUNDRMFAST": "828.95",
  "SUNDROP": "652.60",
  "SUNFLAG": "267.19",
  "SUNTECK": "326.50",
  "SUNTV": "648.45",
  "SUPERHOUSE": "151.09",
  "SUPERSPIN": "5.59",
  "SUPRAJIT": "414.40",
  "SUPREME": "55.37",
  "SUPREMEIND": "3711.80",
  "SUPRIYA": "619.80",
  "SURAJEST": "239.31",
  "SURAJLTD": "247.52",
  "SURAKSHA": "281.11",
  "SURANASOL": "25.12",
  "SURANAT&P": "19.03",
  "SURYALA": "357.25",
  "SURYALAXMI": "59.23",
  "SURYAROSNI": "237.74",
  "SURYODAY": "144.18",
  "SUTLEJTEX": "36.30",
  "SUVEN": "210.18",
  "SUYOG": "782.75",
  "SVLL": "590.10",
  "SVPGLOB": "3.39",
  "SWANCORP": "346.90",
  "SWARAJENG": "4036.20",
  "SWELECTES": "663.05",
  "SWIGGY": "279.15",
  "SYMPHONY": "809.05",
  "SYNCOMF": "13.59",
  "SYNGENE": "436.45",
  "SYRMA": "963.35",
  "SYSTMTXC": "71.48",
  "TAALTECH": "2986.00",
  "TAINWALCHM": "201.00",
  "TAJGVK": "330.95",
  "TALBROAUTO": "281.41",
  "TAMBOLIIN": "169.20",
  "TANLA": "482.65",
  "TARACHAND": "64.03",
  "TARAPUR": "25.12",
  "TARC": "136.10",
  "TARIL": "321.35",
  "TARSONS": "212.78",
  "TASTYBITE": "7096.50",
  "TATACHEM": "704.05",
  "TATACOMM": "1515.70",
  "TATAELXSI": "4516.60",
  "TATAGOLD": "14.66",
  "TATAINVEST": "713.15",
  "TATATECH": "576.45",
  "TATSILV": "24.09",
  "TATVA": "1300.40",
  "TBOTEK": "1282.90",
  "TBZ": "149.07",
  "TCC": "388.70",
  "TCI": "971.80",
  "TCIEXP": "526.65",
  "TCIFINANCE": "14.92",
  "TCPLPACK": "2613.50",
  "TDPOWERSYS": "1030.70",
  "TEAMGTY": "263.10",
  "TEAMLEASE": "1263.30",
  "TECH": "34.20",
  "TECHNOE": "1264.25",
  "TECILCHEM": "13.29",
  "TEGA": "1709.80",
  "TEJASNET": "414.85",
  "TEMBO": "601.70",
  "TENNIND": "595.90",
  "TERASOFT": "354.10",
  "TEXINFRA": "99.43",
  "TEXMOPIPES": "46.51",
  "TEXRAIL": "103.23",
  "TFCILTD": "72.89",
  "TFL": "12.70",
  "TGBHOTELS": "9.94",
  "THACKER": "1033.45",
  "THANGAMAYL": "4134.50",
  "THEINVEST": "105.00",
  "THEJO": "1842.00",
  "THELEELA": "429.65",
  "THEMISMED": "90.89",
  "THERMAX": "4185.20",
  "THOMASCOOK": "104.89",
  "THOMASCOTT": "269.78",
  "THYROCARE": "392.65",
  "TI": "472.80",
  "TICL": "21.01",
  "TIGERLOGS": "30.87",
  "TIIL": "2469.60",
  "TIINDIA": "2873.10",
  "TIL": "204.57",
  "TIMETECHNO": "196.30",
  "TIMEX": "322.05",
  "TIMKEN": "3502.90",
  "TINNARUBR": "712.85",
  "TIPSFILMS": "382.95",
  "TIPSMUSIC": "574.15",
  "TIRUMALCHM": "197.03",
  "TITAGARH": "730.20",
  "TMB": "663.85",
  "TNIDETF": "83.78",
  "TNPETRO": "90.66",
  "TNPL": "139.83",
  "TNTELE": "10.35",
  "TOKYOPLAST": "108.54",
  "TOLINS": "111.44",
  "TOP100CASE": "10.55",
  "TOP10ADD": "90.35",
  "TOP15IETF": "10.04",
  "TOP20": "8.89",
  "TORNTPOWER": "1606.30",
  "TOTAL": "57.28",
  "TOUCHWOOD": "74.58",
  "TPHQ": "0.58",
  "TPLPLASTEH": "70.81",
  "TRACXN": "33.60",
  "TRANSPEK": "1136.82",
  "TRANSRAILL": "566.05",
  "TRANSWORLD": "168.87",
  "TRAVELFOOD": "1295.20",
  "TREJHARA": "165.22",
  "TREL": "27.13",
  "TRF": "270.89",
  "TRIDENT": "25.65",
  "TRIGYN": "57.27",
  "TRIVENI": "393.15",
  "TRU": "6.20",
  "TRUALT": "458.00",
  "TSFINV": "416.20",
  "TTKHLTCARE": "889.00",
  "TTKPRESTIG": "494.60",
  "TTML": "44.30",
  "TVSELECT": "455.05",
  "TVSHLTD": "14491.00",
  "TVSSRICHAK": "3939.20",
  "TVTODAY": "116.08",
  "TVVISION": "5.50",
  "TWCGOLDETF": "150.26",
  "UBL": "1522.30",
  "UCAL": "102.88",
  "UCOBANK": "26.50",
  "UDS": "159.40",
  "UEL": "168.72",
  "UFBL": "321.79",
  "UFLEX": "402.95",
  "UFO": "73.74",
  "UGARSUGAR": "39.82",
  "UGROCAP": "112.23",
  "UJJIVANSFB": "57.41",
  "ULTRAMAR": "419.25",
  "UMIYA-MRO": "86.36",
  "UNICHEMLAB": "345.45",
  "UNIDT": "209.34",
  "UNIECOM": "99.19",
  "UNIENTER": "108.33",
  "UNIINFO": "15.05",
  "UNIMECH": "953.60",
  "UNIONGOLD": "147.70",
  "UNIPARTS": "508.30",
  "UNITECH": "4.90",
  "UNITEDPOLY": "29.46",
  "UNITEDTEA": "543.90",
  "UNIVASTU": "68.90",
  "UNIVCABLES": "830.70",
  "UNOMINDA": "1129.40",
  "UPL": "656.65",
  "URBANCO": "134.34",
  "URJA": "10.60",
  "USHAMART": "445.25",
  "UTIAMC": "1032.30",
  "UTKARSHBNK": "13.56",
  "UTLSOLAR": "261.99",
  "UTTAMSUGAR": "243.98",
  "UYFINCORP": "14.31",
  "V2RETAIL": "191.61",
  "VADILALIND": "4551.60",
  "VAIBHAVGBL": "219.92",
  "VAISHALI": "7.75",
  "VAKRANGEE": "7.10",
  "VAL30IETF": "16.07",
  "VALIANTLAB": "66.45",
  "VALIANTORG": "270.59",
  "VALUE": "16.72",
  "VARDHACRLC": "35.44",
  "VARROC": "526.15",
  "VASCONEQ": "37.78",
  "VASWANI": "58.22",
  "VCL": "1.74",
  "VEEDOL": "1423.20",
  "VELJAN": "990.70",
  "VENKEYS": "1583.30",
  "VENTIVE": "606.95",
  "VENUSPIPES": "1311.40",
  "VENUSREM": "1022.85",
  "VERANDA": "154.97",
  "VERTOZ": "53.21",
  "VESUVIUS": "498.30",
  "VETO": "107.29",
  "VGL": "61.09",
  "VGUARD": "330.75",
  "VHL": "3361.00",
  "VIDHIING": "320.10",
  "VIDYAWIRES": "73.65",
  "VIJAYA": "1023.40",
  "VIKRAMSOLR": "225.61",
  "VIKRAN": "68.09",
  "VIMTALABS": "482.45",
  "VINATIORGA": "1274.50",
  "VINCOFE": "139.59",
  "VINDHYATEL": "1340.60",
  "VINEETLAB": "36.21",
  "VINNY": "1.18",
  "VINYLINDIA": "273.19",
  "VIPCLOTHNG": "22.75",
  "VIPIND": "320.75",
  "VISAKAIND": "65.05",
  "VISASTEEL": "35.34",
  "VISHNU": "570.40",
  "VIVIDHA": "0.60",
  "VIYASH": "207.31",
  "VLSFINANCE": "237.92",
  "VMART": "640.00",
  "VMM": "118.61",
  "VMSTMT": "46.54",
  "VOLTAMP": "10307.00",
  "VOLTAS": "1438.00",
  "VPRPL": "42.01",
  "VRAJ": "129.20",
  "VRLLOG": "260.95",
  "VSSL": "255.52",
  "VSTIND": "264.05",
  "VSTL": "128.11",
  "VSTTILLERS": "5269.30",
  "VTL": "549.90",
  "WAAREEENER": "3489.10",
  "WAAREEINDO": "540.85",
  "WAAREERTL": "1085.70",
  "WABAG": "1423.30",
  "WAKEFIT": "146.94",
  "WALCHANNAG": "189.83",
  "WCIL": "101.79",
  "WEALTH": "927.95",
  "WEBELSOLAR": "88.56",
  "WEIZMANIND": "81.87",
  "WEL": "94.76",
  "WELCORP": "1076.65",
  "WELENT": "482.00",
  "WELINV": "1303.80",
  "WELSPLSOL": "37.05",
  "WELSPUNLIV": "126.91",
  "WENDT": "7082.00",
  "WESTLIFE": "457.10",
  "WEWIN": "55.62",
  "WEWORK": "545.00",
  "WHEELS": "1074.35",
  "WHIRLPOOL": "925.60",
  "WILLAMAGOR": "28.07",
  "WIMPLAST": "385.26",
  "WINDLAS": "876.20",
  "WINDMACHIN": "294.67",
  "WIPL": "155.99",
  "WOCKPHARMA": "1403.50",
  "WONDERLA": "529.45",
  "WORTHPERI": "139.09",
  "WPIL": "428.40",
  "WSI": "73.82",
  "WSTCSTPAPR": "478.65",
  "XCHANGING": "64.48",
  "XELPMOC": "106.04",
  "XPROINDIA": "1052.60",
  "XTGLOBAL": "32.41",
  "YASHO": "1484.20",
  "YATHARTH": "743.75",
  "YATRA": "119.21",
  "YESBANK": "19.84",
  "YUKEN": "743.25",
  "ZAGGLE": "253.83",
  "ZEEL": "87.60",
  "ZEELEARN": "4.89",
  "ZENITHEXPO": "216.69",
  "ZENITHSTL": "7.07",
  "ZENSARTECH": "594.55",
  "ZENTEC": "1643.90",
  "ZFCVINDIA": "15032.00",
  "ZIMLAB": "79.71",
  "ZODIAC": "296.11",
  "ZODIACLOTH": "81.00",
  "ZOTA": "1294.00",
  "ZSARACOM": "9809.50",
  "ZUARI": "226.58",
  "ZUARIIND": "266.82",
  "ZYDUSWELL": "499.45",
  "ABB": "7155.70",
  "BAJFINANCE": "918.55",
  "CIPLA": "1228.90",
  "CGPOWER": "796.65",
  "TITAN": "4512.90",
  "DRREDDY": "1232.25",
  "HINDZINC": "589.95",
  "SPICEJET": "13.27",
  "ONGC": "283.35",
  "PIDILITIND": "1390.15",
  "PUNJCOMMU": "54.26",
  "SHREECEM": "25461.55",
  "TATAPOWER": "433.65",
  "TORNTPHARM": "4188.15",
  "AMBUJACEM": "454.50",
  "HOCL": "33.35",
  "TATASTEEL": "211.65",
  "CUMMINSIND": "5203.70",
  "BAJAJHLDNG": "10376.40",
  "BOSCHLTD": "37764.95",
  "BPCL": "316.00",
  "SIEMENS": "3709.60",
  "HINDUNILVR": "2235.50",
  "NESTLEIND": "1287.40",
  "TATACONSUM": "1118.70",
  "BRITANNIA": "5701.55",
  "INDHOTEL": "657.50",
  "ITC": "305.00",
  "ACGL": "1848.50",
  "EICHERMOT": "7240.55",
  "AMAL": "654.65",
  "TANFACIND": "2414.20",
  "WIPRO": "202.40",
  "TGVSL": "108.46",
  "LKPFIN": "198.05",
  "ISTLTD": "701.25",
  "APOLLOHOSP": "7653.85",
  "BENARAS": "10012.55",
  "SHRIRAMFIN": "1045.05",
  "CHOLAFIN": "1568.80",
  "ADANIENT": "2228.00",
  "GUJTLRM": "0.66",
  "BPAGRI": "30.05",
  "JYOTIRES": "891.15",
  "WINSOMTX": "76.94",
  "SEKURITIND": "101.37",
  "RIR": "180.20",
  "MOTHERSON": "123.20",
  "CIANAGRO": "1103.20",
  "BGDL": "120.44",
  "GVTD": "4232.75",
  "CROPSTER": "7.04",
  "INDBNK": "45.23",
  "LOTUSCHO": "733.65",
  "KMCSHIL": "90.05",
  "SHUKRAPHAR": "34.90",
  "BIBCL": "17.93",
  "SUNPHARMA": "1668.00",
  "ANDREWYU": "20.82",
  "ASMTEC": "3211.60",
  "ECORECO": "394.15",
  "IOC": "147.00",
  "ORIRAIL": "131.20",
  "BANKBARODA": "280.85",
  "GAIL": "157.70",
  "GUJSTATFIN": "10.96",
  "AXISBANK": "1353.65",
  "HCLTECH": "1428.35",
  "JINDALSTEL": "1287.40",
  "ZYDUSLIFE": "936.35",
  "TVSMOTOR": "3764.45",
  "GODREJCP": "1104.25",
  "UNITDSPR": "1306.75",
  "PNB": "113.75",
  "HAZOOR": "30.00",
  "UNIONBANK": "189.05",
  "CANBK": "142.70",
  "DIVISLAB": "6281.35",
  "MARUTI": "13445.95",
  "ULTRACEMCO": "11911.30",
  "TCS": "2578.45",
  "NTPC": "397.90",
  "SOLARINDS": "14900.95",
  "TECHM": "1504.10",
  "PFC": "472.85",
  "DLF": "595.85",
  "POWERGRID": "319.60",
  "ADANIPORTS": "1577.55",
  "RECLTD": "382.20",
  "BAJAJ-AUTO": "9795.05",
  "BAJAJFINSV": "1829.40",
  "SENSEX1": "85.94",
  "COALINDIA": "441.65",
  "MUTHOOTFIN": "3532.05",
  "SBISENSEX": "870.24",
  "GCMSECU": "0.71",
  "MMLF": "0.71",
  "ALSL": "61.11",
  "BRPL": "121.05",
  "VISHAL": "23.37",
  "MIIL": "619.25",
  "SENSEXBEES": "895.90",
  "ARYACAPM": "426.80",
  "CAPPIPES": "11.85",
  "SETFBSE100": "285.51",
  "URSUGAR": "3.24",
  "ADANIENSOL": "1261.40",
  "UNIAUTO": "60.60",
  "NAKSH": "4.42",
  "INDIGO": "4679.25",
  "PANORAMA": "43.48",
  "BLUECLOUDS": "19.02",
  "RELICAB": "39.35",
  "SPICELOUNG": "27.24",
  "LTM": "4718.50",
  "SPRAYKING": "1.49",
  "VBL": "466.40",
  "VSL": "12.25",
  "LLFICL": "1.63",
  "DMART": "4605.65",
  "IFL": "0.49",
  "CHEMCRUX": "91.60",
  "PRIMEFRESH": "235.00",
  "ESCORP": "118.00",
  "SHISHIND": "13.14",
  "ANG": "26.56",
  "PQIF": "24.34",
  "SBILIFE": "1980.85",
  "TTFL": "54.75",
  "POOJA": "25.29",
  "STL": "9.08",
  "HDFCLIFE": "610.45",
  "MRCAGRO": "32.07",
  "KENVI": "2.31",
  "ACTIVE": "136.99",
  "HAL": "4342.70",
  "TRL": "104.76",
  "UHZAVERI": "15.00",
  "PALMJEWELS": "18.13",
  "RAWEDGE": "20.69",
  "HDFCAMC": "2767.35",
  "DEEP": "42.34",
  "ASRL": "7.43",
  "SETFSN50": "921.70",
  "A1L": "13.30",
  "DOLFIN": "179.20",
  "SMGOLD": "12.84",
  "DECCAN": "12.72",
  "KRANTI": "61.30",
  "AGOL": "5.02",
  "NSL": "130.39",
  "VRFILMS": "15.60",
  "GKP": "6.25",
  "BMW": "43.35",
  "PARSHVA": "173.85",
  "ARL": "62.77",
  "SNXT50BEES": "89.36",
  "GALACTICO": "1.91",
  "ANUROOP": "12.50",
  "COLAB": "161.35",
  "08MPD": "5.29",
  "08GPG": "2.30",
  "08AGG": "33.80",
  "08QPR": "1669.00",
  "ROJL": "1.32",
  "11DPR": "12.84",
  "11GPG": "2.09",
  "11MPD": "3.42",
  "11MPR": "53.11",
  "11QPD": "6.76",
  "11QPR": "34.15",
  "11AGG": "33.82",
  "11AMD": "42.80",
  "11AQD": "24.42",
  "11DPD": "5.54",
  "MAXHEALTH": "1010.35",
  "MAZDOCK": "2620.85",
  "IRFC": "103.00",
  "LODHA": "855.85",
  "SAMOR": "75.80",
  "ACHYUT": "5.45",
  "HYUNDAI": "1885.75",
  "ENRIN": "3138.40",
  "NSDL": "922.85",
  "TMCV": "438.25",
  "TATACAP": "335.25",
  "SSFLPP": "107.00",
  "ATLPP": "10.50",
  "PRABHAPP": "52.88",
  "505196": "160.05"
}